Workbook
Name _Growth_M_Data: 'ST Forecast (M)'!$N$11:$AQ$67
Name _Growth_M_Data: '[1]Growth Rnd Forecast (M)'!$I$8:$AT$76
Name _Growth_M_Labels: 'ST Forecast (M)'!$C$11:$C$67
Name _Growth_M_Labels: '[1]Growth Rnd Forecast (M)'!$C$8:$C$76
Name _Growth_M_MonthEnd: 'ST Forecast (M)'!$N$5:$AQ$5
Name _Growth_M_QuarterEnd: 'ST Forecast (M)'!#REF!
Name _Growth_M_QuarterEnd: '[1]Growth Rnd Forecast (M)'!$I$3:$AT$3
Name _Growth_M_YearEnd: 'ST Forecast (M)'!$N$7:$AQ$7
Name _GrowthSource2_M_Data: '[1]Cost Forecast (v2)'!$F$9:$AQ$55
Name _GrowthSource2_M_Labels: '[1]Cost Forecast (v2)'!$D$9:$D$55
Name _GrowthSource2_M_MonthEnd: '[1]Cost Forecast (v2)'!$F$3:$AQ$3
Name _Hist_M_Data: '[1]Hist PnL (M)'!$H$11:$V$123
Name _Hist_M_Data: 'Historical PnL (M)'!$H$12:$AE$129
Name _Hist_M_Labels: '[1]Hist PnL (M)'!$C$11:$C$123
Name _Hist_M_Labels: 'Historical PnL (M)'!$C$12:$C$129
Name _Hist_M_MonthEnd: 'Historical PnL (M)'!$H$5:$AE$5
Name _Hist_M_QuarterEnd: '[1]Hist PnL (M)'!$H$3:$V$3
Name _Hist_M_YearEnd: 'Historical PnL (M)'!$H$7:$AE$7
Name _HistBS_M_Data: 'Historical BS'!$E$9:$AB$102
Name _HistBS_M_Labels: 'Historical BS'!$C$9:$C$102
Name _HistBS_M_MonthEnd: 'Historical BS'!$E$5:$AB$5
Name _HistCFS_M_Data: '[1]Historical CFS'!$D$9:$R$41
Name _HistCFS_M_Data: 'Historical CFS'!$D$9:$AA$102
Name _HistCFS_M_Labels: '[1]Historical CFS'!$C$9:$C$41
Name _HistCFS_M_Labels: 'Historical CFS'!$C$9:$C$102
Name _HistCFS_M_MonthEnd: '[1]Historical CFS'!$D$5:$R$5
Name _HistCFS_M_MonthEnd: 'Historical CFS'!$D$5:$AA$5
Name _HistIS_M_Data: '[1]Historical IS'!$D$8:$R$123
Name _HistIS_M_Data: 'Historical IS'!$E$8:$AC$145
Name _HistIS_M_Labels: '[1]Historical IS'!$C$8:$C$123
Name _HistIS_M_Labels: 'Historical IS'!$C$8:$C$145
Name _HistIS_M_MonthEnd: '[1]Historical IS'!$D$5:$R$5
Name _HistIS_M_MonthEnd: 'Historical IS'!$E$5:$AC$5
Name _STForecast_M_Data: 'ST Forecast (M)'!$H$12:$AQ$65
Name _STForecast_M_Labels: 'ST Forecast (M)'!$C$12:$C$65
Name _STForecast_M_MonthEnd: 'ST Forecast (M)'!$H$5:$AQ$5
Name _STForecast_M_YearEnd: 'ST Forecast (M)'!$H$7:$AQ$7

Sheet Cover
C5: XGS Enterprise Model
C9: Version: | D9: =MID(CELL("filename"),SEARCH("[",CELL("filename"))+1,SEARCH("]",CELL("filename"))-SEARCH("[",CELL("filename"))-6) -> 5.10 XGS Enterprise Model_Confidential_2026.02.17
C10: Date: | D10: =TODAY() -> 46071
C22: CONFIDENTIAL

Sheet Intro
B2: XGS Enterprise Model
B3: Intro
B5: Description
B6: This is a dynamic multi-year model that integrates historical performance data from the previous fiscal year with forward-looking projections across two time horizons. The model provides detailed three-year forecasts incorporating operational assumptions, alongside strategic ten-year projections to capture the full growth trajectory.
B9: Sheet | C9: Type | D9: Description | E9: Time Range
B10: =HYPERLINK($A$1, "Intro") -> Intro | C10: Index | D10: Model navigation index and links
B11: =HYPERLINK("#Inputs!$A$1", "Inputs") -> Inputs | C11: Inputs | D11: Key drivers and assumptions for the model, primarily around long-term forecasts
B12: =HYPERLINK("#'Consolidated Forecast (A)'!A1", "Consolidated Forecast (A)") -> Consolidated Forecast (A) | C12: Summary Financials | D12: Annual consolidated enterprise model incorporating historical financials, short term forecasts, and long term forecasts | E12: 2024-2035
B13: =HYPERLINK("#'ST Forecast (M)'!A1", "ST Forecast (M)") -> ST Forecast (M) | C13: Financials | D13: Monthly short term expense forecasts focused on uses of growth round proceeds | E13: 2025Q2-2028
B14: =HYPERLINK("#'Historical PnL (M)'!A1", "Historical PnL (M)") -> Historical PnL (M) | C14: Financials | D14: Monthly historical PnL | E14: 2024-2025
B15: =HYPERLINK("#'Historical IS'!A1", "Historical IS") -> Historical IS | C15: Historical Financials | D15: Monthly audited Income Statements | E15: 2024-2025
B16: =HYPERLINK("#'Historical BS'!A1", "Historical BS") -> Historical BS | C16: Historical Financials | D16: Monthly audited Balance Sheets | E16: 2024-2025
B17: =HYPERLINK("#'Historical CFS'!A1", "Historical CFS") -> Historical CFS | C17: Historical Financials | D17: Monthly audited Cash Flow Statements | E17: 2024-2025

Sheet Consolidated Model >

Sheet Inputs
B2: XGS Enterprise Model
B3: Inputs & Assumptions
B5: Time Period
C7: Model Month Start | F7: 45322
C8: Model Month End | F8: 49674
B10: Project Phasing by Geography
C12: MW Deployed By Geography | F12: 2027 | G12: =F12+1 -> 2028 | H12: =G12+1 -> 2029 | I12: =H12+1 -> 2030 | J12: =I12+1 -> 2031 | K12: =J12+1 -> 2032 | L12: =K12+1 -> 2033 | M12: =L12+1 -> 2034 | N12: =M12+1 -> 2035 | P12: 2030 TOTAL | Q12: 2035 TOTAL
D13: SoCal (Imperial + Coso) | E13: MW | F13: 0 | G13: 50 | H13: 400 | I13: 200 | J13: 300 | K13: 300 | L13: 0 | M13: 0 | N13: 0 | P13: =SUM(F13:I13) -> 650 | Q13: =SUM(F13:N13) -> 1250
D14: NorCal (Geysers) | E14: MW | F14: 0 | G14: 150 | H14: 500 | I14: 1000 | J14: 1500 | K14: 1000 | L14: 0 | M14: 0 | N14: 0 | P14: =SUM(F14:I14) -> 1650 | Q14: =SUM(F14:N14) -> 4150
D15: New Mexico | E15: MW | F15: 30 | G15: 150 | H15: 250 | I15: 400 | J15: 720 | K15: 1000 | L15: 0 | M15: 0 | N15: 0 | P15: =SUM(F15:I15) -> 830 | Q15: =SUM(F15:N15) -> 2550
D16: Oregon | E16: MW | F16: 0 | G16: 0 | H16: 0 | I16: 50 | J16: 200 | K16: 1750 | L16: 1500 | M16: 0 | N16: 0 | P16: =SUM(F16:I16) -> 50 | Q16: =SUM(F16:N16) -> 3500
D17: US West | E17: MW | F17: 0 | G17: 0 | H17: 0 | I17: 0 | J17: 0 | K17: 0 | L17: 500 | M17: 2000 | N17: 2500 | P17: =SUM(F17:I17) -> 0 | Q17: =SUM(F17:N17) -> 5000
D18: Philippines | E18: MW | F18: 0 | G18: 0 | H18: 0 | I18: 0 | J18: 0 | K18: 500 | L18: 0 | M18: 0 | N18: 0 | P18: =SUM(F18:I18) -> 0 | Q18: =SUM(F18:N18) -> 500
D19: APAC (Indonesia, NZ , Taiwan) | E19: MW | F19: 0 | G19: 0 | H19: 0 | I19: 0 | J19: 0 | K19: 0 | L19: 500 | M19: 500 | N19: 500 | P19: =SUM(F19:I19) -> 0 | Q19: =SUM(F19:N19) -> 1500
D20: Saudi Arabia | E20: MW | F20: 0 | G20: 0 | H20: 0 | I20: 0 | J20: 0 | K20: 0 | L20: 1000 | M20: 2000 | N20: 2500 | P20: =SUM(F20:I20) -> 0 | Q20: =SUM(F20:N20) -> 5500
D21: Japan | E21: MW | F21: 0 | G21: 0 | H21: 0 | I21: 0 | J21: 0 | K21: 0 | L21: 1500 | M21: 2500 | N21: 3000 | P21: =SUM(F21:I21) -> 0 | Q21: =SUM(F21:N21) -> 7000
D22: All Geographies | E22: MW | F22: =SUM(F13:F21) -> 30 | G22: =SUM(G13:G21) -> 350 | H22: =SUM(H13:H21) -> 1150 | I22: =SUM(I13:I21) -> 1650 | J22: =SUM(J13:J21) -> 2720 | K22: =SUM(K13:K21) -> 4550 | L22: =SUM(L13:L21) -> 5000 | M22: =SUM(M13:M21) -> 7000 | N22: =SUM(N13:N21) -> 8500 | P22: =SUM(F22:I22) -> 3180 | Q22: =SUM(F22:N22) -> 30950
C25: Capex & Project Curve | E25: year | F25: 2027 | G25: =F25+1 -> 2028 | H25: =G25+1 -> 2029 | I25: =H25+1 -> 2030 | J25: =I25+1 -> 2031 | K25: =J25+1 -> 2032 | L25: =K25+1 -> 2033 | M25: =L25+1 -> 2034 | N25: =M25+1 -> 2035
D26: Capex Cost | E26: $000/MW | F26: 11000 | G26: 10000 | H26: 10000 | I26: 9000 | J26: 9000 | K26: 8500 | L26: 8500 | M26: 7000 | N26: 6300
D27: Project Devex Reimbursement | E27: # | F27: 1 | G27: 1 | H27: 2 | I27: 0 | J27: 0 | K27: 0 | L27: 0 | M27: 0 | N27: 0
D28: Project Capacity Delivered | E28: MW | F28: =F22 -> 30 | G28: =G22 -> 350 | H28: =H22 -> 1150 | I28: =I22 -> 1650 | J28: =J22 -> 2720 | K28: =K22 -> 4550 | L28: =L22 -> 5000 | M28: =M22 -> 7000 | N28: =N22 -> 8500
D29: MW Operational | E29: MW | F29: =SUM($F28:F$28) -> 30 | G29: =SUM($F28:G$28) -> 380 | H29: =SUM($F28:H$28) -> 1530 | I29: =SUM($F28:I$28) -> 3180 | J29: =SUM($F28:J$28) -> 5900 | K29: =SUM($F28:K$28) -> 10450 | L29: =SUM($F28:L$28) -> 15450 | M29: =SUM($F28:M$28) -> 22450 | N29: =SUM($F28:N$28) -> 30950
D31: Project Capex | E31: $m | F31: =F26*F28/1000 -> 330 | G31: =G26*G28/1000 -> 3500 | H31: =H26*H28/1000 -> 11500 | I31: =I26*I28/1000 -> 14850 | J31: =J26*J28/1000 -> 24480 | K31: =K26*K28/1000 -> 38675 | L31: =L26*L28/1000 -> 42500 | M31: =M26*M28/1000 -> 49000 | N31: =N26*N28/1000 -> 53550
B33: Revenue Model & Operating Margin
C35: Fee Structure to XGS
D36: EPCM Fee | E36: % Capex | F36: 0.04
D37: LTSA Fee | E37: $000/MW/yr | F37: 6
C39: Operating Expenses (2027Q2-2028)
D40: Operating Headcount Escalator | E40: % p.a. | F40: 0.3
D41: Operating Expenses Escalator | E41: % p.a. | F41: 0.3
C43: Operating Margin (2029 Onwards)
D44: R&D Spend Growth (vs 2028 Baseline) | E44: % p.a. | F44: 0.1
B46: Devex Assumptions
C48: Reimbursable Devex @ TopCo
D49: Resource evaluation | E49: $000/Project | F49: 750
D50: Subsurface engineering services | E50: $000/Project | F50: 100
D51: Surface engineering services | E51: $000/Project | F51: 335
D52: Other development | E52: $000/Project | F52: 500
D53: Total | E53: $000/Project | F53: =SUM(F49:F52) -> 1685
B55: Other
C57: Venture Debt
D58: Size | E58: $000/MW | F58: 4500
D59: Closing Year | E59: year | F59: 2025
D60: Amort Horizon | E60: years | F60: 3
D61: Interest Rate | E61: % | F61: 0.08

Sheet Consolidated Forecast (A)
B2: XGS Enterprise Model
B3: Consolidated Forecasts (Annual)
B5: Date | E5: =Inputs!$F$7 -> 45322 | G5: =EOMONTH(E5,-1) -> 45291 | H5: =EOMONTH(G5,12) -> 45657 | I5: =EOMONTH(H5,12) -> 46022 | J5: =EOMONTH(I5,12) -> 46387 | K5: =EOMONTH(J5,12) -> 46752 | L5: =EOMONTH(K5,12) -> 47118 | M5: =EOMONTH(L5,12) -> 47483 | N5: =EOMONTH(M5,12) -> 47848 | O5: =EOMONTH(N5,12) -> 48213 | ... S5: =EOMONTH(R5,12) -> 49674 | U5: =I5 -> 46022 | V5: =I5 -> 46022
B6: YearFrac | F6: =SUM(G6:BJ6) -> 138.00278 | H6: =YEARFRAC(H5,G5) -> 1 | I6: =YEARFRAC(I5,H5) -> 1 | J6: =YEARFRAC(J5,I5) -> 1 | K6: =YEARFRAC(K5,J5) -> 1 | L6: =YEARFRAC(L5,K5) -> 1 | M6: =YEARFRAC(M5,L5) -> 1 | N6: =YEARFRAC(N5,M5) -> 1 | O6: =YEARFRAC(O5,N5) -> 1 | ... S6: =YEARFRAC(S5,R5) -> 1 | U6: =YEARFRAC(U5,T5) -> 126.00278 | V6: =YEARFRAC(V5,U5) -> 0
B7: Year | H7: =YEAR(H5) -> 2024 | I7: =YEAR(I5) -> 2025 | J7: =YEAR(J5) -> 2026 | K7: =YEAR(K5) -> 2027 | L7: =YEAR(L5) -> 2028 | M7: =YEAR(M5) -> 2029 | N7: =YEAR(N5) -> 2030 | O7: =YEAR(O5) -> 2031 | ... S7: =YEAR(S5) -> 2035 | U7: =YEAR(U5) -> 2025 | V7: =YEAR(V5) -> 2025
A9: SUMMARY
B11: Projects
C12: MW Reaching COD | D12: MW | F12: =SUM(H12:S12) -> 30950 | H12: =IFERROR(INDEX(Inputs!#REF!,MATCH('Consolidated Forecast (A)'!H$7,Inputs!$F$25:$N$25,0)),0) -> 0 | I12: =I38 -> 0 | J12: =J38 -> 0 | K12: =K38 -> 30 | L12: =L38 -> 350 | M12: =M38 -> 1150 | N12: =N38 -> 1650 | O12: =O38 -> 2720 | P12: =P38 -> 4550 | ... S12: =S38 -> 8500
C13: MW Operational | D13: MW | H13: =IFERROR(INDEX(Inputs!#REF!,MATCH('Consolidated Forecast (A)'!H$7,Inputs!$F$25:$N$25,0)),0) -> 0 | I13: =I39 -> 0 | J13: =J39 -> 0 | K13: =K39 -> 30 | L13: =L39 -> 380 | M13: =M39 -> 1530 | N13: =N39 -> 3180 | O13: =O39 -> 5900 | P13: =P39 -> 10450 | ... S13: =S39 -> 30950
B15: Cash Flows
C16: Revenue | D16: $000 | F16: =SUM(H16:S16) -> 10077320 | H16: =H46 -> 0 | I16: =I46 -> 0 | J16: =J46 -> 0 | K16: =K46 -> 13380 | L16: =L46 -> 142280 | M16: =M46 -> 469180 | N16: =N46 -> 613080 | O16: =O46 -> 1014600 | ... S16: =S46 -> 2327700
C17: Expenses | D17: $000 | F17: =SUM(H17:S17) -> -1982759.9 | H17: =-H55 -> -4320.9147 | I17: =-I55 -> -8192.9836 | J17: =-J55 -> -15293.786 | K17: =-K55 -> -22572.078 | L17: =-L55 -> -29380.111 | M17: =-M55 -> -81800 | N17: =-N55 -> -111600 | O17: =-O55 -> -186600 | ... S17: =-S55 -> -464400
C18: Operating Profit | D18: $000 | F18: =SUM(H18:S18) -> 8094560.1 | H18: =SUM(H16:H17) -> -4320.9147 | I18: =SUM(I16:I17) -> -8192.9836 | J18: =SUM(J16:J17) -> -15293.786 | K18: =SUM(K16:K17) -> -9192.0783 | L18: =SUM(L16:L17) -> 112899.89 | M18: =SUM(M16:M17) -> 387380 | N18: =SUM(N16:N17) -> 501480 | O18: =SUM(O16:O17) -> 828000 | ... S18: =SUM(S16:S17) -> 1863300
C19: Operating Profit Margin | H19: =MAX(IFERROR(H18/H$16,0),0) -> 0 | I19: =MAX(IFERROR(I18/I$16,0),0) -> 0 | J19: =MAX(IFERROR(J18/J$16,0),0) -> 0 | K19: =MAX(IFERROR(K18/K$16,0),0) -> 0 | L19: =MAX(IFERROR(L18/L$16,0),0) -> 0.79350498 | M19: =MAX(IFERROR(M18/M$16,0),0) -> 0.82565327 | N19: =MAX(IFERROR(N18/N$16,0),0) -> 0.81796829 | O19: =MAX(IFERROR(O18/O$16,0),0) -> 0.81608516 | ... S19: =MAX(IFERROR(S18/S$16,0),0) -> 0.80048975
C20: R&D / Cost Reduction | D20: $000 | F20: =SUM(H20:S20) -> -83939.773 | H20: =-H61 -> -10301.761 | I20: =-I61 -> -6626.7779 | J20: =-J61 -> -3722 | K20: =-K61 -> -3994.7021 | L20: =-L61 -> -5184.9521 | M20: =-M61 -> -5703.4473 | N20: =-N61 -> -6273.792 | O20: =-O61 -> -6901.1712 | ... S20: =-S61 -> -10104.005
C21: EBITDA Excl Projects | F21: =SUM(H21:S21) -> 8010620.4 | H21: =SUM(H20,H18) -> -14622.676 | I21: =SUM(I20,I18) -> -14819.762 | J21: =SUM(J20,J18) -> -19015.786 | K21: =SUM(K20,K18) -> -13186.78 | L21: =SUM(L20,L18) -> 107714.94 | M21: =SUM(M20,M18) -> 381676.55 | N21: =SUM(N20,N18) -> 495206.21 | O21: =SUM(O20,O18) -> 821098.83 | ... S21: =SUM(S20,S18) -> 1853196
C22: Non-Project EBITDA Margin | H22: =MAX(IFERROR(H21/H$16,0),0) -> 0 | I22: =MAX(IFERROR(I21/I$16,0),0) -> 0 | J22: =MAX(IFERROR(J21/J$16,0),0) -> 0 | K22: =MAX(IFERROR(K21/K$16,0),0) -> 0 | L22: =MAX(IFERROR(L21/L$16,0),0) -> 0.75706309 | M22: =MAX(IFERROR(M21/M$16,0),0) -> 0.81349706 | N22: =MAX(IFERROR(N21/N$16,0),0) -> 0.80773506 | O22: =MAX(IFERROR(O21/O$16,0),0) -> 0.80928329 | ... S22: =MAX(IFERROR(S21/S$16,0),0) -> 0.79614899
C23: Project Expenses excl Wells | D23: $000 | F23: =SUM(H23:S23) -> -5183.1486 | H23: =-H150 -> -55.8603 | I23: =-I150 -> -424.955 | J23: =-J150 -> -4702.3333 | K23: =-K150 -> 0 | L23: =-L150 -> 0 | M23: =-M151 -> 0 | N23: =-N151 -> 0 | O23: =-O151 -> 0 | P23: =-P151 -> 0 | Q23: =-Q151 -> 0 | R23: =-R151 -> 0 | S23: =-S151 -> 0
C24: EBITDA Incl Projects | F24: =SUM(H24:S24) -> 8005437.2 | H24: =H21+SUM(H23:H23) -> -14678.536 | I24: =I21+SUM(I23:I23) -> -15244.717 | J24: =J21+SUM(J23:J23) -> -23718.119 | K24: =K21+SUM(K23:K23) -> -13186.78 | L24: =L21+SUM(L23:L23) -> 107714.94 | M24: =M21+SUM(M23:M23) -> 381676.55 | N24: =N21+SUM(N23:N23) -> 495206.21 | O24: =O21+SUM(O23:O23) -> 821098.83 | ... S24: =S21+SUM(S23:S23) -> 1853196
C25: EBITDA Margin | H25: =MAX(IFERROR(H24/H$16,0),0) -> 0 | I25: =MAX(IFERROR(I24/I$16,0),0) -> 0 | J25: =MAX(IFERROR(J24/J$16,0),0) -> 0 | K25: =MAX(IFERROR(K24/K$16,0),0) -> 0 | L25: =MAX(IFERROR(L24/L$16,0),0) -> 0.75706309 | M25: =MAX(IFERROR(M24/M$16,0),0) -> 0.81349706 | N25: =MAX(IFERROR(N24/N$16,0),0) -> 0.80773506 | O25: =MAX(IFERROR(O24/O$16,0),0) -> 0.80928329 | ... S25: =MAX(IFERROR(S24/S$16,0),0) -> 0.79614899
C26: Interest Expense | D26: $000 | F26: =SUM(H26:S26) -> -575.96112 | H26: =H81 -> 0 | I26: =I81 -> -212.35 | J26: =J81 -> -213.88889 | K26: =K81 -> -120.55556 | L26: =L81 -> -29.166671 | M26: =M81 -> 0 | N26: =N81 -> 0 | O26: =O81 -> 0 | ... S26: =S81 -> 0
C27: Debt Drawdown / (Repayment) | D27: $000 | F27: =SUM(H27:S27) -> 0 | H27: =H82 -> 0 | I27: =I82 -> 3750 | J27: =J82 -> -1500 | K27: =K82 -> -1500 | L27: =L82 -> -750 | M27: =M82 -> 0 | N27: =N82 -> 0 | O27: =O82 -> 0 | ... S27: =S82 -> 0
C28: Historical Taxes & Interest Income | D28: $000 | F28: =SUM(H28:S28) -> 876.33736 | H28: =H83 -> 635.47403 | I28: =I83 -> 240.86333 | J28: =J83 -> 0 | K28: =K83 -> 0 | L28: =L83 -> 0 | M28: =M83 -> 0 | N28: =N83 -> 0 | O28: =O83 -> 0 | ... S28: =S83 -> 0
C29: Historical Accrual to Cash Adjustments | D29: $000 | F29: =SUM(H29:S29) -> -7225.0317 | H29: =H84 -> -1706.824 | I29: =I84 -> -5518.2077 | J29: =J84 -> 0 | K29: =K84 -> 0 | L29: =L84 -> 0 | M29: =M84 -> 0 | N29: =N84 -> 0 | O29: =O84 -> 0 | ... S29: =S84 -> 0
C30: Net Cash Flow excl Equity Financing | D30: $000 | F30: =SUM(H30:S30) -> 7998512.5 | H30: =SUM(H26:H29,H24) -> -15749.886 | I30: =SUM(I26:I29,I24) -> -16984.411 | J30: =SUM(J26:J29,J24) -> -25432.008 | K30: =SUM(K26:K29,K24) -> -14807.336 | L30: =SUM(L26:L29,L24) -> 106935.77 | M30: =SUM(M26:M29,M24) -> 381676.55 | N30: =SUM(N26:N29,N24) -> 495206.21 | O30: =SUM(O26:O29,O24) -> 821098.83 | ... S30: =SUM(S26:S29,S24) -> 1853196
C31: Historical Equity Injections | D31: $000 | F31: =SUM(H31:S31) -> 33717.499 | H31: =H87 -> 20799.974 | I31: =I87 -> 12917.525 | J31: =J87 -> 0 | K31: =K87 -> 0 | L31: =L87 -> 0 | M31: =M87 -> 0 | N31: =N87 -> 0 | O31: =O87 -> 0 | ... S31: =S87 -> 0
C32: Net Cash Flow | D32: $000 | F32: =SUM(H32:S32) -> 8032230 | H32: =SUM(H30:H31) -> 5050.0877 | I32: =SUM(I30:I31) -> -4066.8859 | J32: =SUM(J30:J31) -> -25432.008 | K32: =SUM(K30:K31) -> -14807.336 | L32: =SUM(L30:L31) -> 106935.77 | M32: =SUM(M30:M31) -> 381676.55 | N32: =SUM(N30:N31) -> 495206.21 | O32: =SUM(O30:O31) -> 821098.83 | ... S32: =SUM(S30:S31) -> 1853196
A34: Project Cadence
B36: Capex Summary
C37: Capex Cost | D37: $000/MW | H37: =IFERROR(INDEX(Inputs!$F26:$N26,MATCH('Consolidated Forecast (A)'!H$7,Inputs!$F$25:$N$25,0)),0) -> 0 | I37: =IFERROR(INDEX(Inputs!$F26:$P26,MATCH('Consolidated Forecast (A)'!I$7,Inputs!$F$25:$P$25,0)),0) -> 0 | J37: =IFERROR(INDEX(Inputs!$F26:$P26,MATCH('Consolidated Forecast (A)'!J$7,Inputs!$F$25:$P$25,0)),0) -> 0 | K37: =IFERROR(INDEX(Inputs!$F26:$P26,MATCH('Consolidated Forecast (A)'!K$7,Inputs!$F$25:$P$25,0)),0) -> 11000 | L37: =IFERROR(INDEX(Inputs!$F26:$P26,MATCH('Consolidated Forecast (A)'!L$7,Inputs!$F$25:$P$25,0)),0) -> 10000 | M37: =IFERROR(INDEX(Inputs!$F26:$P26,MATCH('Consolidated Forecast (A)'!M$7,Inputs!$F$25:$P$25,0)),0) -> 10000 | N37: =IFERROR(INDEX(Inputs!$F26:$P26,MATCH('Consolidated Forecast (A)'!N$7,Inputs!$F$25:$P$25,0)),0) -> 9000 | O37: =IFERROR(INDEX(Inputs!$F26:$P26,MATCH('Consolidated Forecast (A)'!O$7,Inputs!$F$25:$P$25,0)),0) -> 9000 | P37: =IFERROR(INDEX(Inputs!$F26:$P26,MATCH('Consolidated Forecast (A)'!P$7,Inputs!$F$25:$P$25,0)),0) -> 8500 | ... S37: =IFERROR(INDEX(Inputs!$F26:$P26,MATCH('Consolidated Forecast (A)'!S$7,Inputs!$F$25:$P$25,0)),0) -> 6300
C38: MW Reaching COD | D38: MW | F38: =SUM(H38:S38) -> 30950 | H38: =IFERROR(INDEX(Inputs!$F28:$N28,MATCH('Consolidated Forecast (A)'!H$7,Inputs!$F$25:$N$25,0)),0) -> 0 | I38: =IFERROR(INDEX(Inputs!$F28:$P28,MATCH('Consolidated Forecast (A)'!I$7,Inputs!$F$25:$P$25,0)),0) -> 0 | J38: =IFERROR(INDEX(Inputs!$F28:$P28,MATCH('Consolidated Forecast (A)'!J$7,Inputs!$F$25:$P$25,0)),0) -> 0 | K38: =IFERROR(INDEX(Inputs!$F28:$P28,MATCH('Consolidated Forecast (A)'!K$7,Inputs!$F$25:$P$25,0)),0) -> 30 | L38: =IFERROR(INDEX(Inputs!$F28:$P28,MATCH('Consolidated Forecast (A)'!L$7,Inputs!$F$25:$P$25,0)),0) -> 350 | M38: =IFERROR(INDEX(Inputs!$F28:$P28,MATCH('Consolidated Forecast (A)'!M$7,Inputs!$F$25:$P$25,0)),0) -> 1150 | N38: =IFERROR(INDEX(Inputs!$F28:$P28,MATCH('Consolidated Forecast (A)'!N$7,Inputs!$F$25:$P$25,0)),0) -> 1650 | O38: =IFERROR(INDEX(Inputs!$F28:$P28,MATCH('Consolidated Forecast (A)'!O$7,Inputs!$F$25:$P$25,0)),0) -> 2720 | P38: =IFERROR(INDEX(Inputs!$F28:$P28,MATCH('Consolidated Forecast (A)'!P$7,Inputs!$F$25:$P$25,0)),0) -> 4550 | ... S38: =IFERROR(INDEX(Inputs!$F28:$P28,MATCH('Consolidated Forecast (A)'!S$7,Inputs!$F$25:$P$25,0)),0) -> 8500
C39: MW Operational | D39: MW | H39: =IFERROR(INDEX(Inputs!$F29:$N29,MATCH('Consolidated Forecast (A)'!H$7,Inputs!$F$25:$N$25,0)),0) -> 0 | I39: =IFERROR(INDEX(Inputs!$F29:$P29,MATCH('Consolidated Forecast (A)'!I$7,Inputs!$F$25:$P$25,0)),0) -> 0 | J39: =IFERROR(INDEX(Inputs!$F29:$P29,MATCH('Consolidated Forecast (A)'!J$7,Inputs!$F$25:$P$25,0)),0) -> 0 | K39: =IFERROR(INDEX(Inputs!$F29:$P29,MATCH('Consolidated Forecast (A)'!K$7,Inputs!$F$25:$P$25,0)),0) -> 30 | L39: =IFERROR(INDEX(Inputs!$F29:$P29,MATCH('Consolidated Forecast (A)'!L$7,Inputs!$F$25:$P$25,0)),0) -> 380 | M39: =IFERROR(INDEX(Inputs!$F29:$P29,MATCH('Consolidated Forecast (A)'!M$7,Inputs!$F$25:$P$25,0)),0) -> 1530 | N39: =IFERROR(INDEX(Inputs!$F29:$P29,MATCH('Consolidated Forecast (A)'!N$7,Inputs!$F$25:$P$25,0)),0) -> 3180 | O39: =IFERROR(INDEX(Inputs!$F29:$P29,MATCH('Consolidated Forecast (A)'!O$7,Inputs!$F$25:$P$25,0)),0) -> 5900 | P39: =IFERROR(INDEX(Inputs!$F29:$P29,MATCH('Consolidated Forecast (A)'!P$7,Inputs!$F$25:$P$25,0)),0) -> 10450 | ... S39: =IFERROR(INDEX(Inputs!$F29:$P29,MATCH('Consolidated Forecast (A)'!S$7,Inputs!$F$25:$P$25,0)),0) -> 30950
A41: Projections - PnL
B43: Income
C44: EPCM Revenue | D44: $000 | E44: =Inputs!$F$36 -> 0.04 | F44: =SUM(H44:S44) -> 9535400 | H44: =H37*H38*$E$44 -> 0 | I44: =I37*I38*$E$44 -> 0 | J44: =J37*J38*$E$44 -> 0 | K44: =K37*K38*$E$44 -> 13200 | L44: =L37*L38*$E$44 -> 140000 | M44: =M37*M38*$E$44 -> 460000 | N44: =N37*N38*$E$44 -> 594000 | O44: =O37*O38*$E$44 -> 979200 | ... S44: =S37*S38*$E$44 -> 2142000
C45: Ops Management Revenue | D45: $000 | E45: =Inputs!F37 -> 6 | F45: =SUM(H45:S45) -> 541920 | H45: =$E45*H$39 -> 0 | I45: =$E45*I$39 -> 0 | J45: =$E45*J$39 -> 0 | K45: =$E45*K$39 -> 180 | L45: =$E45*L$39 -> 2280 | M45: =$E45*M$39 -> 9180 | N45: =$E45*N$39 -> 19080 | O45: =$E45*O$39 -> 35400 | ... S45: =$E45*S$39 -> 185700
C46: Revenue | D46: $000 | F46: =SUM(H46:S46) -> 10077320 | H46: =SUM(H44:H45) -> 0 | I46: =SUM(I44:I45) -> 0 | J46: =SUM(J44:J45) -> 0 | K46: =SUM(K44:K45) -> 13380 | L46: =SUM(L44:L45) -> 142280 | M46: =SUM(M44:M45) -> 469180 | N46: =SUM(N44:N45) -> 613080 | O46: =SUM(O44:O45) -> 1014600 | ... S46: =SUM(S44:S45) -> 2327700
C47: YoY Revenue Growth | H47: =IFERROR(H46/G46,0) -> 0 | I47: =IFERROR(I46/H46-1,0) -> 0 | J47: =IFERROR(J46/I46-1,0) -> 0 | K47: =IFERROR(K46/J46-1,0) -> 0 | L47: =IFERROR(L46/K46-1,0) -> 9.6337818 | M47: =IFERROR(M46/L46-1,0) -> 2.2975822 | N47: =IFERROR(N46/M46-1,0) -> 0.30670532 | O47: =IFERROR(O46/N46-1,0) -> 0.65492269 | P47: =IFERROR(P46/O46-1,0) -> 0.58653657 | ... S47: =IFERROR(S46/R46-1,0) -> 0.11123311
B49: Expenses
C50: Payroll | D50: $000 | F50: =SUM(H50:S50) -> 40597.773 | H50: =H103 -> 2703.3605 | I50: =I103 -> 5029.6521 | J50: =J103 -> 7211 | K50: =K103 -> 11143.955 | L50: =L103 -> 14509.805 | M50: 0 | N50: 0 | O50: 0 | P50: 0 | Q50: 0 | R50: 0 | S50: 0
C51: Overhead | D51: $000 | F51: =SUM(H51:S51) -> 7577.0927 | H51: =H104 -> 126.66149 | I51: =I104 -> 212.78763 | J51: =J104 -> 1587 | K51: =K104 -> 2455.0318 | L51: =L104 -> 3195.6118 | M51: 0 | N51: 0 | O51: 0 | P51: 0 | Q51: 0 | R51: 0 | S51: 0
C52: Overhead Services | D52: $000 | F52: =SUM(H52:S52) -> 9538.1391 | H52: =H116 -> 731.23766 | I52: =I116 -> 817.71146 | J52: =J116 -> 1580.5 | K52: =K116 -> 2781.2388 | L52: =L116 -> 3627.4512 | M52: 0 | N52: 0 | O52: 0 | P52: 0 | Q52: 0 | R52: 0 | S52: 0
C53: Legal Fees | D53: $000 | F53: =SUM(H53:S53) -> 7391.7249 | H53: =H121 -> 153.23498 | I53: =I121 -> 473.03436 | J53: =J121 -> 1902.2857 | K53: =K121 -> 2114.2034 | L53: =L121 -> 2748.9664 | M53: 0 | N53: 0 | O53: 0 | P53: 0 | Q53: 0 | R53: 0 | S53: 0
C54: Other Expenses | D54: $000 | F54: =SUM(H54:S54) -> 14655.144 | H54: =H130 -> 606.42004 | I54: =I130 -> 1659.7981 | J54: =J130 -> 3013 | K54: =K130 -> 4077.6488 | L54: =L130 -> 5298.2772 | M54: 0 | N54: 0 | O54: 0 | P54: 0 | Q54: 0 | R54: 0 | S54: 0
C55: Total Expenses | D55: $000 | F55: =SUM(H55:S55) -> 1982759.9 | H55: =SUM(H50:H54) -> 4320.9147 | I55: =SUM(I50:I54) -> 8192.9836 | J55: =SUM(J50:J54) -> 15293.786 | K55: =SUM(K50:K54) -> 22572.078 | L55: =SUM(L50:L54) -> 29380.111 | M55: 81800 | N55: 111600 | O55: 186600 | P55: 283400 | Q55: 357400 | R55: 417800 | S55: 464400
C57: Operating Profit | D57: $000 | F57: =SUM(H57:S57) -> 8094560.1 | H57: =H46-H55 -> -4320.9147 | I57: =I46-I55 -> -8192.9836 | J57: =J46-J55 -> -15293.786 | K57: =K46-K55 -> -9192.0783 | L57: =L46-L55 -> 112899.89 | M57: =M46-M55 -> 387380 | N57: =N46-N55 -> 501480 | O57: =O46-O55 -> 828000 | ... S57: =S46-S55 -> 1863300
C58: Operating Profit Margin | D58: % | H58: =MAX(IFERROR(H57/H46,0),0) -> 0 | I58: =MAX(IFERROR(I57/I46,0),0) -> 0 | J58: =MAX(IFERROR(J57/J46,0),0) -> 0 | K58: =MAX(IFERROR(K57/K46,0),0) -> 0 | L58: =MAX(IFERROR(L57/L46,0),0) -> 0.79350498 | M58: =MAX(IFERROR(M57/M46,0),0) -> 0.82565327 | N58: =MAX(IFERROR(N57/N46,0),0) -> 0.81796829 | O58: =MAX(IFERROR(O57/O46,0),0) -> 0.81608516 | ... S58: =MAX(IFERROR(S57/S46,0),0) -> 0.80048975
B60: Expenses
C61: R&D Expense | D61: $000 | E61: =Inputs!$F$44 -> 0.1 | F61: =SUM(H61:S61) -> 83939.773 | H61: =H140 -> 10301.761 | I61: =I140 -> 6626.7779 | J61: =J140 -> 3722 | K61: =K140 -> 3994.7021 | L61: =L140 -> 5184.9521 | M61: =L61*(1+$E61) -> 5703.4473 | N61: =M61*(1+$E61) -> 6273.792 | O61: =N61*(1+$E61) -> 6901.1712 | P61: =O61*(1+$E61) -> 7591.2883 | Q61: =P61*(1+$E61) -> 8350.4172 | R61: =Q61*(1+$E61) -> 9185.4589 | S61: =R61*(1+$E61) -> 10104.005
C63: EBITDA Excl Projects | D63: $000 | F63: =SUM(H63:S63) -> 8010620.4 | H63: =H57-H61 -> -14622.676 | I63: =I57-I61 -> -14819.762 | J63: =J57-J61 -> -19015.786 | K63: =K57-K61 -> -13186.78 | L63: =L57-L61 -> 107714.94 | M63: =M57-M61 -> 381676.55 | N63: =N57-N61 -> 495206.21 | O63: =O57-O61 -> 821098.83 | ... S63: =S57-S61 -> 1853196
C64: EBITDA Margin | D64: % | H64: =MAX(0,IFERROR(H63/H46,0)) -> 0 | I64: =MAX(0,IFERROR(I63/I46,0)) -> 0 | J64: =MAX(0,IFERROR(J63/J46,0)) -> 0 | K64: =MAX(0,IFERROR(K63/K46,0)) -> 0 | L64: =MAX(0,IFERROR(L63/L46,0)) -> 0.75706309 | M64: =MAX(0,IFERROR(M63/M46,0)) -> 0.81349706 | N64: =MAX(0,IFERROR(N63/N46,0)) -> 0.80773506 | O64: =MAX(0,IFERROR(O63/O46,0)) -> 0.80928329 | ... S64: =MAX(0,IFERROR(S63/S46,0)) -> 0.79614899
B66: XGS DevCo Asset Spend
C67: Surface Engineering* | D67: $000 | F67: =SUM(H67:S67) -> 200 | H67: =H145 -> 0 | I67: =I145 -> 0 | J67: =J145 -> 200 | K67: =K145 -> 0 | L67: =L145 -> 0 | M67: 0 | N67: 0 | O67: 0 | P67: 0 | Q67: 0 | R67: 0 | S67: 0
C68: Subsurface Engineering* | D68: $000 | F68: =SUM(H68:S68) -> 2101.7353 | H68: =H147 -> 8.7803 | I68: =I147 -> 424.955 | J68: =J147 -> 1668 | K68: =K147 -> 0 | L68: =L147 -> 0 | M68: 0 | N68: 0 | O68: 0 | P68: 0 | Q68: 0 | R68: 0 | S68: 0
C69: Early Stage Project Development (Permitting, Power Delivery)* | D69: $000 | F69: =SUM(H69:S69) -> 1781.4133 | H69: =H148 -> 47.08 | I69: =I148 -> 0 | J69: =J148 -> 1734.3333 | K69: =K148 -> 0 | L69: =L148 -> 0 | M69: 0 | N69: 0 | O69: 0 | P69: 0 | Q69: 0 | R69: 0 | S69: 0
C70: Geophysical Surveys* | D70: $000 | F70: =SUM(H70:S70) -> 300 | H70: =H146 -> 0 | I70: =I146 -> 0 | J70: =J146 -> 300 | K70: =K146 -> 0 | L70: =L146 -> 0 | M70: 0 | N70: 0 | O70: 0 | P70: 0 | Q70: 0 | R70: 0 | S70: 0
C71: Site Control* | D71: $000
C72: Total Project Expenses | D72: $000 | F72: =SUM(H72:S72) -> 4383.1486 | H72: =SUM(H67:H70) -> 55.8603 | I72: =SUM(I67:I70) -> 424.955 | J72: =SUM(J67:J70) -> 3902.3333 | K72: =SUM(K67:K70) -> 0 | L72: =SUM(L67:L70) -> 0 | M72: =SUM(M67:M70) -> 0 | N72: =SUM(N67:N70) -> 0 | O72: =SUM(O67:O70) -> 0 | ... S72: =SUM(S67:S70) -> 0
C74: EBITDA Incl Projects | D74: $000 | F74: =SUM(H74:S74) -> 8006237.2 | H74: =H63-H72 -> -14678.536 | I74: =I63-I72 -> -15244.717 | J74: =J63-J72 -> -22918.119 | K74: =K63-K72 -> -13186.78 | L74: =L63-L72 -> 107714.94 | M74: =M63-M72 -> 381676.55 | N74: =N63-N72 -> 495206.21 | O74: =O63-O72 -> 821098.83 | ... S74: =S63-S72 -> 1853196
A77: ST Forecast - Debt & Cash Accounts
B79: Net Cash Flow Projections
C80: EBITDA Incl Projects | D80: $000 | H80: =H74 -> -14678.536 | I80: =I74 -> -15244.717 | J80: =J74 -> -22918.119 | K80: =K74 -> -13186.78 | L80: =L74 -> 107714.94 | M80: =M74 -> 381676.55 | N80: =N74 -> 495206.21 | O80: =O74 -> 821098.83 | ... S80: =S74 -> 1853196
C81: Venture Debt Interest Expense | D81: $000 | H81: =H159 -> 0 | I81: =I159 -> -212.35 | J81: -213.88889 | K81: -120.55556 | L81: -29.166671 | M81: 0 | N81: 0 | O81: 0 | P81: 0 | Q81: 0 | R81: 0 | S81: 0
C82: Venture Debt Drawdown / (Repayment) | D82: $000 | H82: =SUM(H92:H93) -> 0 | I82: =SUM(I92:I93) -> 3750 | J82: =SUM(J92:J93) -> -1500 | K82: =SUM(K92:K93) -> -1500 | L82: =SUM(L92:L93) -> -750 | M82: 0 | N82: 0 | O82: 0 | P82: 0 | Q82: 0 | R82: 0 | S82: 0
C83: Historical Taxes & Interest Income | D83: $000 | H83: =SUM(H160:H161) -> 635.47403 | I83: =SUM(I160:I161) -> 240.86333 | J83: 0 | K83: 0 | L83: 0 | M83: 0 | N83: 0 | O83: 0 | P83: 0 | Q83: 0 | R83: 0 | S83: 0
C84: Historical Accrual to Cash Adjustments | D84: $000 | H84: =SUM(H167:H169,H172:H173) -> -1706.824 | I84: =SUM(I167:I169,I172:I173) -> -5518.2077 | J84: 0 | K84: 0 | L84: 0 | M84: 0 | N84: 0 | O84: 0 | P84: 0 | Q84: 0 | R84: 0 | S84: 0
C85: Net Cash Flow excl Equity Financing | D85: $000 | H85: =SUM(H80:H84) -> -15749.886 | I85: =SUM(I80:I84) -> -16984.411 | J85: =SUM(J80:J84) -> -24632.008 | K85: =SUM(K80:K84) -> -14807.336 | L85: =SUM(L80:L84) -> 106935.77 | M85: =SUM(M80:M84) -> 381676.55 | N85: =SUM(N80:N84) -> 495206.21 | O85: =SUM(O80:O84) -> 821098.83 | ... S85: =SUM(S80:S84) -> 1853196
C87: Historical Equity Injections | D87: $000 | H87: =H170 -> 20799.974 | I87: =I170 -> 12917.525 | J87: 0 | K87: 0 | L87: 0
C88: Net Cash Flow | D88: $000 | H88: =H85+H87 -> 5050.0877 | I88: =I85+I87 -> -4066.8859 | J88: =J85+J87 -> -24632.008 | K88: =K85+K87 -> -14807.336 | L88: =L85+L87 -> 106935.77 | M88: =M85+M87 -> 381676.55 | N88: =N85+N87 -> 495206.21 | O88: =O85+O87 -> 821098.83 | ... S88: =S85+S87 -> 1853196
B90: Venture Debt | E90: =Inputs!$F$59 -> 2025
C91: Opening Balance | D91: $000 | H91: =G94 -> 0 | I91: =H94 -> 0 | J91: =I94 -> 3750 | K91: =J94 -> 2250 | L91: =K94 -> 750 | M91: 0 | N91: 0 | O91: 0 | P91: 0 | Q91: 0 | R91: 0 | S91: 0
C92: Debt Drawdown | D92: $000 | E92: =Inputs!$F$58 -> 4500 | H92: =IF(H7=$E$90,$E$92,0) -> 0 | I92: =IF(I7=$E$90,$E$92,0) -> 4500 | J92: =IF(J7=$E$90,$E$92,0) -> 0 | K92: =IF(K7=$E$90,$E$92,0) -> 0 | L92: =IF(L7=$E$90,$E$92,0) -> 0 | M92: 0 | N92: 0 | O92: 0 | P92: 0 | Q92: 0 | R92: 0 | S92: 0
C93: Debt Repayment | D93: $000 | E93: =Inputs!$F$60 -> 3 | F93: =SUM(H93:S93) -> -4500 | H93: 0 | I93: -750 | J93: =-MIN(J$91,$E$92/$E$93) -> -1500 | K93: =-MIN(K$91,$E$92/$E$93) -> -1500 | L93: =-MIN(L$91,$E$92/$E$93) -> -750 | M93: 0 | N93: 0 | O93: 0 | P93: 0 | Q93: 0 | R93: 0 | S93: 0
C94: Ending Balance | D94: $000 | G94: 0 | H94: =SUM(H91:H93) -> 0 | I94: =SUM(I91:I93) -> 3750 | J94: =SUM(J91:J93) -> 2250 | K94: =SUM(K91:K93) -> 750 | L94: =SUM(L91:L93) -> 0 | M94: =SUM(M91:M93) -> 0 | N94: =SUM(N91:N93) -> 0 | O94: =SUM(O91:O93) -> 0 | ... S94: =SUM(S91:S93) -> 0
A96: Summary of Historical and ST Forecasts
B98: Headcount
C99: New Headcount (FTE) | D99: # | H99: 0 | I99: 0 | J99: =SUMIFS(INDEX(_STForecast_M_Data,MATCH('Consolidated Forecast (A)'!$C100,_STForecast_M_Labels,0),0),_STForecast_M_YearEnd,'Consolidated Forecast (A)'!J$5) -> 16 | K99: =SUMIFS(INDEX(_STForecast_M_Data,MATCH('Consolidated Forecast (A)'!$C100,_STForecast_M_Labels,0),0),_STForecast_M_YearEnd,'Consolidated Forecast (A)'!K$5) -> 16 | L99: =SUMIFS(INDEX(_STForecast_M_Data,MATCH('Consolidated Forecast (A)'!$C100,_STForecast_M_Labels,0),0),_STForecast_M_YearEnd,'Consolidated Forecast (A)'!L$5) -> 18 | U99: 0 | V99: =SUMIFS(INDEX(_STForecast_M_Data,MATCH('Consolidated Forecast (A)'!$C99,_STForecast_M_Labels,0),0),_STForecast_M_YearEnd,'Consolidated Forecast (A)'!V$5) -> 0
C100: Total Headcount (FTE) | D100: # | H100: 0 | I100: 0 | J100: =SUMIFS(INDEX(_STForecast_M_Data,MATCH('Consolidated Forecast (A)'!$C99,_STForecast_M_Labels,0),0),_STForecast_M_MonthEnd,'Consolidated Forecast (A)'!J$5) -> 44 | K100: =SUMIFS(INDEX(_STForecast_M_Data,MATCH('Consolidated Forecast (A)'!$C99,_STForecast_M_Labels,0),0),_STForecast_M_MonthEnd,'Consolidated Forecast (A)'!K$5) -> 60 | L100: =SUMIFS(INDEX(_STForecast_M_Data,MATCH('Consolidated Forecast (A)'!$C99,_STForecast_M_Labels,0),0),_STForecast_M_MonthEnd,'Consolidated Forecast (A)'!L$5) -> 78 | U100: 0 | V100: =SUMIFS(INDEX(_STForecast_M_Data,MATCH('Consolidated Forecast (A)'!$C100,_STForecast_M_Labels,0),0),_STForecast_M_YearEnd,'Consolidated Forecast (A)'!V$5) -> 0
B102: SG&A
C103: Payroll | D103: $000 | F103: =SUM(H103:S103) -> 40597.773 | H103: =SUMIFS(INDEX(_Hist_M_Data,MATCH('Consolidated Forecast (A)'!$C103,_Hist_M_Labels,0),0),_Hist_M_YearEnd,'Consolidated Forecast (A)'!H$5) -> 2703.3605 | I103: =SUMIFS(INDEX(_Hist_M_Data,MATCH('Consolidated Forecast (A)'!$C103,_Hist_M_Labels,0),0),_Hist_M_YearEnd,'Consolidated Forecast (A)'!I$5) -> 5029.6521 | J103: =SUMIFS(INDEX(_STForecast_M_Data,MATCH('Consolidated Forecast (A)'!$C103,_STForecast_M_Labels,0),0),_STForecast_M_YearEnd,'Consolidated Forecast (A)'!J$5) -> 7211 | K103: =SUMIFS(INDEX(_STForecast_M_Data,MATCH('Consolidated Forecast (A)'!$C103,_STForecast_M_Labels,0),0),_STForecast_M_YearEnd,'Consolidated Forecast (A)'!K$5) -> 11143.955 | L103: =SUMIFS(INDEX(_STForecast_M_Data,MATCH('Consolidated Forecast (A)'!$C103,_STForecast_M_Labels,0),0),_STForecast_M_YearEnd,'Consolidated Forecast (A)'!L$5) -> 14509.805 | U103: =SUMIFS(INDEX(_Hist_M_Data,MATCH('Consolidated Forecast (A)'!$C103,_Hist_M_Labels,0),0),_Hist_M_YearEnd,'Consolidated Forecast (A)'!U$5) -> 5029.6521 | V103: =SUMIFS(INDEX(_STForecast_M_Data,MATCH('Consolidated Forecast (A)'!$C103,_STForecast_M_Labels,0),0),_STForecast_M_YearEnd,'Consolidated Forecast (A)'!V$5) -> 0
C104: Overhead | D104: $000 | F104: =SUM(H104:S104) -> 7577.0927 | H104: =SUMIFS(INDEX(_Hist_M_Data,MATCH('Consolidated Forecast (A)'!$C104,_Hist_M_Labels,0),0),_Hist_M_YearEnd,'Consolidated Forecast (A)'!H$5) -> 126.66149 | I104: =SUMIFS(INDEX(_Hist_M_Data,MATCH('Consolidated Forecast (A)'!$C104,_Hist_M_Labels,0),0),_Hist_M_YearEnd,'Consolidated Forecast (A)'!I$5) -> 212.78763 | J104: =SUMIFS(INDEX(_STForecast_M_Data,MATCH('Consolidated Forecast (A)'!$C104,_STForecast_M_Labels,0),0),_STForecast_M_YearEnd,'Consolidated Forecast (A)'!J$5) -> 1587 | K104: =SUMIFS(INDEX(_STForecast_M_Data,MATCH('Consolidated Forecast (A)'!$C104,_STForecast_M_Labels,0),0),_STForecast_M_YearEnd,'Consolidated Forecast (A)'!K$5) -> 2455.0318 | L104: =SUMIFS(INDEX(_STForecast_M_Data,MATCH('Consolidated Forecast (A)'!$C104,_STForecast_M_Labels,0),0),_STForecast_M_YearEnd,'Consolidated Forecast (A)'!L$5) -> 3195.6118 | U104: =SUMIFS(INDEX(_Hist_M_Data,MATCH('Consolidated Forecast (A)'!$C104,_Hist_M_Labels,0),0),_Hist_M_YearEnd,'Consolidated Forecast (A)'!U$5) -> 212.78763 | V104: =SUMIFS(INDEX(_STForecast_M_Data,MATCH('Consolidated Forecast (A)'!$C104,_STForecast_M_Labels,0),0),_STForecast_M_YearEnd,'Consolidated Forecast (A)'!V$5) -> 0
C106: Software services | D106: $000 | F106: =SUM(H106:S106) -> 1026.633 | H106: =SUMIFS(INDEX(_Hist_M_Data,MATCH('Consolidated Forecast (A)'!$C106,_Hist_M_Labels,0),0),_Hist_M_YearEnd,'Consolidated Forecast (A)'!H$5) -> 21.80688 | I106: =SUMIFS(INDEX(_Hist_M_Data,MATCH('Consolidated Forecast (A)'!$C106,_Hist_M_Labels,0),0),_Hist_M_YearEnd,'Consolidated Forecast (A)'!I$5) -> 108.82616 | J106: =SUMIFS(INDEX(_STForecast_M_Data,MATCH('Consolidated Forecast (A)'!$C106,_STForecast_M_Labels,0),0),_STForecast_M_YearEnd,'Consolidated Forecast (A)'!J$5) -> 896 | K106: 0 | L106: 0 | U106: =SUMIFS(INDEX(_Hist_M_Data,MATCH('Consolidated Forecast (A)'!$C106,_Hist_M_Labels,0),0),_Hist_M_YearEnd,'Consolidated Forecast (A)'!U$5) -> 108.82616 | V106: =SUMIFS(INDEX(_STForecast_M_Data,MATCH('Consolidated Forecast (A)'!$C106,_STForecast_M_Labels,0),0),_STForecast_M_YearEnd,'Consolidated Forecast (A)'!V$5) -> 0
C107: Accounting Services (incl software) | D107: $000 | F107: =SUM(H107:S107) -> 183.042 | H107: =SUMIFS(INDEX(_Hist_M_Data,MATCH('Consolidated Forecast (A)'!$C107,_Hist_M_Labels,0),0),_Hist_M_YearEnd,'Consolidated Forecast (A)'!H$5) -> 0 | I107: =SUMIFS(INDEX(_Hist_M_Data,MATCH('Consolidated Forecast (A)'!$C107,_Hist_M_Labels,0),0),_Hist_M_YearEnd,'Consolidated Forecast (A)'!I$5) -> 81.042 | J107: =SUMIFS(INDEX(_STForecast_M_Data,MATCH('Consolidated Forecast (A)'!$C107,_STForecast_M_Labels,0),0),_STForecast_M_YearEnd,'Consolidated Forecast (A)'!J$5) -> 102 | K107: 0 | L107: 0
C108: PR | D108: $000 | H108: =SUMIFS(INDEX(_Hist_M_Data,MATCH('Consolidated Forecast (A)'!$C108,_Hist_M_Labels,0),0),_Hist_M_YearEnd,'Consolidated Forecast (A)'!H$5) -> 423.80519 | I108: =SUMIFS(INDEX(_Hist_M_Data,MATCH('Consolidated Forecast (A)'!$C108,_Hist_M_Labels,0),0),_Hist_M_YearEnd,'Consolidated Forecast (A)'!I$5) -> 39.05287 | J108: 0 | K108: 0 | L108: 0
C109: Audit Services | D109: $000 | F109: =SUM(H109:S109) -> 251.5119 | H109: =SUMIFS(INDEX(_Hist_M_Data,MATCH('Consolidated Forecast (A)'!$C109,_Hist_M_Labels,0),0),_Hist_M_YearEnd,'Consolidated Forecast (A)'!H$5) -> 0 | I109: =SUMIFS(INDEX(_Hist_M_Data,MATCH('Consolidated Forecast (A)'!$C109,_Hist_M_Labels,0),0),_Hist_M_YearEnd,'Consolidated Forecast (A)'!I$5) -> 169.0119 | J109: =SUMIFS(INDEX(_STForecast_M_Data,MATCH('Consolidated Forecast (A)'!$C109,_STForecast_M_Labels,0),0),_STForecast_M_YearEnd,'Consolidated Forecast (A)'!J$5) -> 82.5 | K109: 0 | L109: 0
C110: Tax Services | D110: $000 | F110: =SUM(H110:S110) -> 97.987 | H110: =SUMIFS(INDEX(_Hist_M_Data,MATCH('Consolidated Forecast (A)'!$C110,_Hist_M_Labels,0),0),_Hist_M_YearEnd,'Consolidated Forecast (A)'!H$5) -> 0 | I110: =SUMIFS(INDEX(_Hist_M_Data,MATCH('Consolidated Forecast (A)'!$C110,_Hist_M_Labels,0),0),_Hist_M_YearEnd,'Consolidated Forecast (A)'!I$5) -> 17.987 | J110: =SUMIFS(INDEX(_STForecast_M_Data,MATCH('Consolidated Forecast (A)'!$C110,_STForecast_M_Labels,0),0),_STForecast_M_YearEnd,'Consolidated Forecast (A)'!J$5) -> 80 | K110: 0 | L110: 0
C111: IT Services | D111: $000 | F111: =SUM(H111:S111) -> 225.23653 | H111: =SUMIFS(INDEX(_Hist_M_Data,MATCH('Consolidated Forecast (A)'!$C111,_Hist_M_Labels,0),0),_Hist_M_YearEnd,'Consolidated Forecast (A)'!H$5) -> 0 | I111: =SUMIFS(INDEX(_Hist_M_Data,MATCH('Consolidated Forecast (A)'!$C111,_Hist_M_Labels,0),0),_Hist_M_YearEnd,'Consolidated Forecast (A)'!I$5) -> 45.23653 | J111: =SUMIFS(INDEX(_STForecast_M_Data,MATCH('Consolidated Forecast (A)'!$C111,_STForecast_M_Labels,0),0),_STForecast_M_YearEnd,'Consolidated Forecast (A)'!J$5) -> 180 | K111: 0 | L111: 0
C112: Recruiting | D112: $000 | F112: =SUM(H112:S112) -> 240 | H112: 0 | I112: 0 | J112: =SUMIFS(INDEX(_STForecast_M_Data,MATCH('Consolidated Forecast (A)'!$C112,_STForecast_M_Labels,0),0),_STForecast_M_YearEnd,'Consolidated Forecast (A)'!J$5) -> 240 | K112: 0 | L112: 0
C113: Subject Matter experts | D113: $000 | F113: =SUM(H113:S113) -> 142 | H113: =SUMIFS(INDEX(_Hist_M_Data,MATCH('Consolidated Forecast (A)'!$C113,_Hist_M_Labels,0),0),_Hist_M_YearEnd,'Consolidated Forecast (A)'!H$5) -> 109 | I113: =SUMIFS(INDEX(_Hist_M_Data,MATCH('Consolidated Forecast (A)'!$C113,_Hist_M_Labels,0),0),_Hist_M_YearEnd,'Consolidated Forecast (A)'!I$5) -> 33 | J113: 0 | K113: 0 | L113: 0
C114: Eng services | D114: $000 | F114: =SUM(H114:S114) -> 279.51359 | H114: =SUMIFS(INDEX(_Hist_M_Data,MATCH('Consolidated Forecast (A)'!$C114,_Hist_M_Labels,0),0),_Hist_M_YearEnd,'Consolidated Forecast (A)'!H$5) -> 176.62559 | I114: =SUMIFS(INDEX(_Hist_M_Data,MATCH('Consolidated Forecast (A)'!$C114,_Hist_M_Labels,0),0),_Hist_M_YearEnd,'Consolidated Forecast (A)'!I$5) -> 102.888 | J114: 0 | K114: 0 | L114: 0 | U114: =SUMIFS(INDEX(_Hist_M_Data,MATCH('Consolidated Forecast (A)'!$C114,_Hist_M_Labels,0),0),_Hist_M_YearEnd,'Consolidated Forecast (A)'!U$5) -> 102.888 | V114: =SUMIFS(INDEX(_STForecast_M_Data,MATCH('Consolidated Forecast (A)'!$C114,_STForecast_M_Labels,0),0),_STForecast_M_YearEnd,'Consolidated Forecast (A)'!V$5) -> #N/A
C115: Other Consultants | F115: =SUM(H115:S115) -> 220.667 | H115: =SUMIFS(INDEX(_Hist_M_Data,MATCH('Consolidated Forecast (A)'!$C115,_Hist_M_Labels,0),0),_Hist_M_YearEnd,'Consolidated Forecast (A)'!H$5) -> 0 | I115: =SUMIFS(INDEX(_Hist_M_Data,MATCH('Consolidated Forecast (A)'!$C115,_Hist_M_Labels,0),0),_Hist_M_YearEnd,'Consolidated Forecast (A)'!I$5) -> 220.667 | J115: 0 | K115: 0 | L115: 0
C116: Overhead Services | D116: $000 | F116: =SUM(H116:S116) -> 9538.1391 | H116: =SUM(H106:H115) -> 731.23766 | I116: =SUM(I106:I115) -> 817.71146 | J116: =SUM(J106:J115) -> 1580.5 | K116: =SUMIFS(INDEX(_STForecast_M_Data,MATCH('Consolidated Forecast (A)'!$C116,_STForecast_M_Labels,0),0),_STForecast_M_YearEnd,'Consolidated Forecast (A)'!K$5) -> 2781.2388 | L116: =SUMIFS(INDEX(_STForecast_M_Data,MATCH('Consolidated Forecast (A)'!$C116,_STForecast_M_Labels,0),0),_STForecast_M_YearEnd,'Consolidated Forecast (A)'!L$5) -> 3627.4512 | U116: =SUM(U106:U114) -> 211.71416 | V116: =SUM(V106:V114) -> #N/A
C118: Legal Fees - Corporate | D118: $000 | F118: =SUM(H118:S118) -> 3938.34 | H118: =SUMIFS(INDEX(_Hist_M_Data,MATCH('Consolidated Forecast (A)'!$C118,_Hist_M_Labels,0),0),_Hist_M_YearEnd,'Consolidated Forecast (A)'!H$5) -> 118.74593 | I118: =SUMIFS(INDEX(_Hist_M_Data,MATCH('Consolidated Forecast (A)'!$C118,_Hist_M_Labels,0),0),_Hist_M_YearEnd,'Consolidated Forecast (A)'!I$5) -> 334.86851 | J118: =SUMIFS(INDEX(_STForecast_M_Data,MATCH('Consolidated Forecast (A)'!$C118,_STForecast_M_Labels,0),0),_STForecast_M_YearEnd,'Consolidated Forecast (A)'!J$5) -> 762.28571 | K118: =SUMIFS(INDEX(_STForecast_M_Data,MATCH('Consolidated Forecast (A)'!$C118,_STForecast_M_Labels,0),0),_STForecast_M_YearEnd,'Consolidated Forecast (A)'!K$5) -> 1182.6238 | L118: =SUMIFS(INDEX(_STForecast_M_Data,MATCH('Consolidated Forecast (A)'!$C118,_STForecast_M_Labels,0),0),_STForecast_M_YearEnd,'Consolidated Forecast (A)'!L$5) -> 1539.816 | U118: =SUMIFS(INDEX(_Hist_M_Data,MATCH('Consolidated Forecast (A)'!$C118,_Hist_M_Labels,0),0),_Hist_M_YearEnd,'Consolidated Forecast (A)'!U$5) -> 334.86851 | V118: =SUMIFS(INDEX(_STForecast_M_Data,MATCH('Consolidated Forecast (A)'!$C118,_STForecast_M_Labels,0),0),_STForecast_M_YearEnd,'Consolidated Forecast (A)'!V$5) -> 0
C119: Legal Fees - Intellectual Property | D119: $000 | F119: =SUM(H119:S119) -> 3045.1411 | H119: =SUMIFS(INDEX(_Hist_M_Data,MATCH('Consolidated Forecast (A)'!$C119,_Hist_M_Labels,0),0),_Hist_M_YearEnd,'Consolidated Forecast (A)'!H$5) -> 34.48905 | I119: =SUMIFS(INDEX(_Hist_M_Data,MATCH('Consolidated Forecast (A)'!$C119,_Hist_M_Labels,0),0),_Hist_M_YearEnd,'Consolidated Forecast (A)'!I$5) -> 29.922 | J119: =SUMIFS(INDEX(_STForecast_M_Data,MATCH('Consolidated Forecast (A)'!$C119,_STForecast_M_Labels,0),0),_STForecast_M_YearEnd,'Consolidated Forecast (A)'!J$5) -> 840 | K119: =SUMIFS(INDEX(_STForecast_M_Data,MATCH('Consolidated Forecast (A)'!$C119,_STForecast_M_Labels,0),0),_STForecast_M_YearEnd,'Consolidated Forecast (A)'!K$5) -> 931.57961 | L119: =SUMIFS(INDEX(_STForecast_M_Data,MATCH('Consolidated Forecast (A)'!$C119,_STForecast_M_Labels,0),0),_STForecast_M_YearEnd,'Consolidated Forecast (A)'!L$5) -> 1209.1504 | U119: =SUMIFS(INDEX(_Hist_M_Data,MATCH('Consolidated Forecast (A)'!$C119,_Hist_M_Labels,0),0),_Hist_M_YearEnd,'Consolidated Forecast (A)'!U$5) -> 29.922 | V119: =SUMIFS(INDEX(_STForecast_M_Data,MATCH('Consolidated Forecast (A)'!$C119,_STForecast_M_Labels,0),0),_STForecast_M_YearEnd,'Consolidated Forecast (A)'!V$5) -> 0
C120: Legal Fees - Fundraising | F120: =SUM(H120:S120) -> 408.24385 | H120: =SUMIFS(INDEX(_Hist_M_Data,MATCH('Consolidated Forecast (A)'!$C120,_Hist_M_Labels,0),0),_Hist_M_YearEnd,'Consolidated Forecast (A)'!H$5) -> 0 | I120: =SUMIFS(INDEX(_Hist_M_Data,MATCH('Consolidated Forecast (A)'!$C120,_Hist_M_Labels,0),0),_Hist_M_YearEnd,'Consolidated Forecast (A)'!I$5) -> 108.24385 | J120: =SUMIFS(INDEX(_STForecast_M_Data,MATCH('Consolidated Forecast (A)'!$C120,_STForecast_M_Labels,0),0),_STForecast_M_YearEnd,'Consolidated Forecast (A)'!J$5) -> 300 | K120: =SUMIFS(INDEX(_STForecast_M_Data,MATCH('Consolidated Forecast (A)'!$C120,_STForecast_M_Labels,0),0),_STForecast_M_YearEnd,'Consolidated Forecast (A)'!K$5) -> 0 | L120: =SUMIFS(INDEX(_STForecast_M_Data,MATCH('Consolidated Forecast (A)'!$C120,_STForecast_M_Labels,0),0),_STForecast_M_YearEnd,'Consolidated Forecast (A)'!L$5) -> 0
C121: Total Legal Fees | D121: $000 | F121: =SUM(I121:S121) -> 7238.4899 | H121: =SUM(H118:H120) -> 153.23498 | I121: =SUM(I118:I120) -> 473.03436 | J121: =SUM(J118:J120) -> 1902.2857 | K121: =SUM(K118:K120) -> 2114.2034 | L121: =SUM(L118:L120) -> 2748.9664 | U121: =SUM(U118:U119) -> 364.79051 | V121: =SUM(V118:V119) -> 0
C123: Marketing | D123: $000 | F123: =SUM(H123:S123) -> 728.08089 | H123: =SUMIFS(INDEX(_Hist_M_Data,MATCH('Consolidated Forecast (A)'!$C123,_Hist_M_Labels,0),0),_Hist_M_YearEnd,'Consolidated Forecast (A)'!H$5) -> 38.49442 | I123: =SUMIFS(INDEX(_Hist_M_Data,MATCH('Consolidated Forecast (A)'!$C123,_Hist_M_Labels,0),0),_Hist_M_YearEnd,'Consolidated Forecast (A)'!I$5) -> 178.60418 | J123: =SUMIFS(INDEX(_STForecast_M_Data,MATCH('Consolidated Forecast (A)'!$C123,_STForecast_M_Labels,0),0),_STForecast_M_YearEnd,'Consolidated Forecast (A)'!J$5) -> 144 | K123: =SUMIFS(INDEX(_STForecast_M_Data,MATCH('Consolidated Forecast (A)'!$C123,_STForecast_M_Labels,0),0),_STForecast_M_YearEnd,'Consolidated Forecast (A)'!K$5) -> 159.69936 | L123: =SUMIFS(INDEX(_STForecast_M_Data,MATCH('Consolidated Forecast (A)'!$C123,_STForecast_M_Labels,0),0),_STForecast_M_YearEnd,'Consolidated Forecast (A)'!L$5) -> 207.28293 | U123: =SUMIFS(INDEX(_Hist_M_Data,MATCH('Consolidated Forecast (A)'!$C123,_Hist_M_Labels,0),0),_Hist_M_YearEnd,'Consolidated Forecast (A)'!U$5) -> 178.60418 | V123: =SUMIFS(INDEX(_STForecast_M_Data,MATCH('Consolidated Forecast (A)'!$C123,_STForecast_M_Labels,0),0),_STForecast_M_YearEnd,'Consolidated Forecast (A)'!V$5) -> 0
C124: Government Affairs | D124: $000 | F124: =SUM(H124:S124) -> 3203.1943 | H124: =SUMIFS(INDEX(_Hist_M_Data,MATCH('Consolidated Forecast (A)'!$C124,_Hist_M_Labels,0),0),_Hist_M_YearEnd,'Consolidated Forecast (A)'!H$5) -> 114.30791 | I124: =SUMIFS(INDEX(_Hist_M_Data,MATCH('Consolidated Forecast (A)'!$C124,_Hist_M_Labels,0),0),_Hist_M_YearEnd,'Consolidated Forecast (A)'!I$5) -> 533.975 | J124: =SUMIFS(INDEX(_STForecast_M_Data,MATCH('Consolidated Forecast (A)'!$C124,_STForecast_M_Labels,0),0),_STForecast_M_YearEnd,'Consolidated Forecast (A)'!J$5) -> 720 | K124: =SUMIFS(INDEX(_STForecast_M_Data,MATCH('Consolidated Forecast (A)'!$C124,_STForecast_M_Labels,0),0),_STForecast_M_YearEnd,'Consolidated Forecast (A)'!K$5) -> 798.49681 | L124: =SUMIFS(INDEX(_STForecast_M_Data,MATCH('Consolidated Forecast (A)'!$C124,_STForecast_M_Labels,0),0),_STForecast_M_YearEnd,'Consolidated Forecast (A)'!L$5) -> 1036.4146 | U124: =SUMIFS(INDEX(_Hist_M_Data,MATCH('Consolidated Forecast (A)'!$C124,_Hist_M_Labels,0),0),_Hist_M_YearEnd,'Consolidated Forecast (A)'!U$5) -> 533.975 | V124: =SUMIFS(INDEX(_STForecast_M_Data,MATCH('Consolidated Forecast (A)'!$C124,_STForecast_M_Labels,0),0),_STForecast_M_YearEnd,'Consolidated Forecast (A)'!V$5) -> 0
C125: T&E | D125: $000 | F125: =SUM(H125:S125) -> 4196.1315 | H125: =SUMIFS(INDEX(_Hist_M_Data,MATCH('Consolidated Forecast (A)'!$C125,_Hist_M_Labels,0),0),_Hist_M_YearEnd,'Consolidated Forecast (A)'!H$5) -> 223.62705 | I125: =SUMIFS(INDEX(_Hist_M_Data,MATCH('Consolidated Forecast (A)'!$C125,_Hist_M_Labels,0),0),_Hist_M_YearEnd,'Consolidated Forecast (A)'!I$5) -> 457.301 | J125: =SUMIFS(INDEX(_STForecast_M_Data,MATCH('Consolidated Forecast (A)'!$C125,_STForecast_M_Labels,0),0),_STForecast_M_YearEnd,'Consolidated Forecast (A)'!J$5) -> 824 | K125: =SUMIFS(INDEX(_STForecast_M_Data,MATCH('Consolidated Forecast (A)'!$C125,_STForecast_M_Labels,0),0),_STForecast_M_YearEnd,'Consolidated Forecast (A)'!K$5) -> 1171.1287 | L125: =SUMIFS(INDEX(_STForecast_M_Data,MATCH('Consolidated Forecast (A)'!$C125,_STForecast_M_Labels,0),0),_STForecast_M_YearEnd,'Consolidated Forecast (A)'!L$5) -> 1520.0748 | U125: =SUMIFS(INDEX(_Hist_M_Data,MATCH('Consolidated Forecast (A)'!$C125,_Hist_M_Labels,0),0),_Hist_M_YearEnd,'Consolidated Forecast (A)'!U$5) -> 457.301 | V125: =SUMIFS(INDEX(_STForecast_M_Data,MATCH('Consolidated Forecast (A)'!$C125,_STForecast_M_Labels,0),0),_STForecast_M_YearEnd,'Consolidated Forecast (A)'!V$5) -> 0
C126: Insurance | D126: $000 | F126: =SUM(H126:S126) -> 2093.7745 | H126: =SUMIFS(INDEX(_Hist_M_Data,MATCH('Consolidated Forecast (A)'!$C126,_Hist_M_Labels,0),0),_Hist_M_YearEnd,'Consolidated Forecast (A)'!H$5) -> 158.1593 | I126: =SUMIFS(INDEX(_Hist_M_Data,MATCH('Consolidated Forecast (A)'!$C126,_Hist_M_Labels,0),0),_Hist_M_YearEnd,'Consolidated Forecast (A)'!I$5) -> 148.17715 | J126: =SUMIFS(INDEX(_STForecast_M_Data,MATCH('Consolidated Forecast (A)'!$C126,_STForecast_M_Labels,0),0),_STForecast_M_YearEnd,'Consolidated Forecast (A)'!J$5) -> 503 | K126: =SUMIFS(INDEX(_STForecast_M_Data,MATCH('Consolidated Forecast (A)'!$C126,_STForecast_M_Labels,0),0),_STForecast_M_YearEnd,'Consolidated Forecast (A)'!K$5) -> 558.94777 | L126: =SUMIFS(INDEX(_STForecast_M_Data,MATCH('Consolidated Forecast (A)'!$C126,_STForecast_M_Labels,0),0),_STForecast_M_YearEnd,'Consolidated Forecast (A)'!L$5) -> 725.49024 | U126: =SUMIFS(INDEX(_Hist_M_Data,MATCH('Consolidated Forecast (A)'!$C126,_Hist_M_Labels,0),0),_Hist_M_YearEnd,'Consolidated Forecast (A)'!U$5) -> 148.17715 | V126: =SUMIFS(INDEX(_STForecast_M_Data,MATCH('Consolidated Forecast (A)'!$C126,_STForecast_M_Labels,0),0),_STForecast_M_YearEnd,'Consolidated Forecast (A)'!V$5) -> 0
...

Sheet ST Forecast (M)
B2: XGS Enterprise Model
B3: Short Term Forecasts (Monthly)
B5: Date | E5: 46022 | G5: =E5 -> 46022 | H5: =EOMONTH(G5,1) -> 46053 | I5: =EOMONTH(H5,1) -> 46081 | J5: =EOMONTH(I5,1) -> 46112 | K5: =EOMONTH(J5,1) -> 46142 | L5: =EOMONTH(K5,1) -> 46173 | M5: =EOMONTH(L5,1) -> 46203 | N5: =EOMONTH(M5,1) -> 46234 | O5: =EOMONTH(N5,1) -> 46265 | ... AQ5: =EOMONTH(AP5,1) -> 47118
B6: YearFrac | F6: =SUM(G6:CE6) -> 2.9944444 | H6: =YEARFRAC(H5,G5) -> 0.083333333 | I6: =YEARFRAC(I5,H5) -> 0.077777778 | J6: =YEARFRAC(J5,I5) -> 0.086111111 | K6: =YEARFRAC(K5,J5) -> 0.083333333 | L6: =YEARFRAC(L5,K5) -> 0.083333333 | M6: =YEARFRAC(M5,L5) -> 0.083333333 | N6: =YEARFRAC(N5,M5) -> 0.083333333 | O6: =YEARFRAC(O5,N5) -> 0.083333333 | ... AQ6: =YEARFRAC(AQ5,AP5) -> 0.083333333
B7: Year End | H7: =DATE(YEAR(H5),12,31) -> 46387 | I7: =DATE(YEAR(I5),12,31) -> 46387 | J7: =DATE(YEAR(J5),12,31) -> 46387 | K7: =DATE(YEAR(K5),12,31) -> 46387 | L7: =DATE(YEAR(L5),12,31) -> 46387 | M7: =DATE(YEAR(M5),12,31) -> 46387 | N7: =DATE(YEAR(N5),12,31) -> 46387 | O7: =DATE(YEAR(O5),12,31) -> 46387 | ... AQ7: =DATE(YEAR(AQ5),12,31) -> 47118
A9: Expense Forecast
B11: Headcount
C12: New Headcount (FTE) | D12: # | H12: 28 | I12: 28 | J12: 29 | K12: 30 | L12: 31 | M12: 32 | N12: 34 | O12: 36 | P12: 38 | Q12: 40 | R12: 42 | S12: 44 | T12: =S12+T13 -> 46 | U12: =T12+U13 -> 48 | V12: 50 | W12: 51 | X12: 52 | Y12: 53 | Z12: 54 | AA12: 55 | AB12: 56 | AC12: 58 | AD12: 59 | AE12: 60 | AF12: 62 | AG12: 63 | AH12: 64 | AI12: 66 | AJ12: 67 | AK12: 69 | AL12: 70 | AM12: 72 | AN12: 73 | AO12: 75 | AP12: 77 | AQ12: 78
C13: Total Headcount (FTE) | D13: # | F13: =SUM(H13:AQ13) -> 50 | H13: 0 | I13: 0 | J13: 1 | K13: 1 | L13: 1 | M13: 1 | N13: 2 | O13: 2 | P13: 2 | Q13: 2 | R13: 2 | S13: 2 | T13: 2 | U13: 2 | V13: 2 | W13: 1 | X13: 1 | Y13: 1 | Z13: 1 | AA13: 1 | AB13: 1 | AC13: 2 | AD13: 1 | AE13: 1 | AF13: 2 | AG13: 1 | AH13: 1 | AI13: 2 | AJ13: 1 | AK13: 2 | AL13: 1 | AM13: 2 | AN13: 1 | AO13: 2 | AP13: 2 | AQ13: 1
B15: SG&A
C16: Payroll | D16: $000 | F16: =SUM(H16:AQ16) -> 32864.76 | H16: 490 | I16: 490 | J16: 508 | K16: 525 | L16: 543 | M16: 560 | N16: 595 | O16: 630 | P16: 665 | Q16: 700 | R16: 735 | S16: 770 | T16: 805 | U16: 840 | V16: =U16*(1+Inputs!$F$40)^V$6 -> 859.19368 | W16: =V16*(1+Inputs!$F$40)^W$6 -> 878.18569 | X16: =W16*(1+Inputs!$F$40)^X$6 -> 897.5975 | Y16: =X16*(1+Inputs!$F$40)^Y$6 -> 917.4384 | Z16: =Y16*(1+Inputs!$F$40)^Z$6 -> 937.71787 | AA16: =Z16*(1+Inputs!$F$40)^AA$6 -> 958.44561 | AB16: =AA16*(1+Inputs!$F$40)^AB$6 -> 979.63152 | AC16: =AB16*(1+Inputs!$F$40)^AC$6 -> 1001.2857 | ... AQ16: =AP16*(1+Inputs!$F$40)^AQ$6 -> 1359.8529
C17: Overhead | D17: $000 | F17: =SUM(H17:AQ17) -> 7237.6436 | H17: 108 | I17: 108 | J17: 112 | K17: 116 | L17: 119 | M17: 123 | N17: 131 | O17: 139 | P17: 146 | Q17: 154 | R17: 162 | S17: 169 | T17: 178 | U17: 185 | V17: =U17*(1+Inputs!$F$40)^V$6 -> 189.22718 | W17: =V17*(1+Inputs!$F$40)^W$6 -> 193.40994 | X17: =W17*(1+Inputs!$F$40)^X$6 -> 197.68516 | Y17: =X17*(1+Inputs!$F$40)^Y$6 -> 202.05489 | Z17: =Y17*(1+Inputs!$F$40)^Z$6 -> 206.5212 | AA17: =Z17*(1+Inputs!$F$40)^AA$6 -> 211.08624 | AB17: =AA17*(1+Inputs!$F$40)^AB$6 -> 215.75218 | AC17: =AB17*(1+Inputs!$F$40)^AC$6 -> 220.52126 | ... AQ17: =AP17*(1+Inputs!$F$40)^AQ$6 -> 299.49142
C19: Software services | D19: $000 | F19: =SUM(H19:AQ19) -> 1096 | H19: 62 | I19: 62 | J19: 64 | K19: 66 | L19: 68 | M19: 70 | N19: 74 | O19: 78 | P19: 82 | Q19: 86 | R19: 90 | S19: 94 | T19: 98 | U19: 102 | V19: 0 | W19: 0 | X19: 0 | Y19: 0 | Z19: 0 | AA19: 0 | AB19: 0 | AC19: 0 | AD19: 0 | AE19: 0 | AF19: 0 | AG19: 0 | AH19: 0 | AI19: 0 | AJ19: 0 | AK19: 0 | AL19: 0 | AM19: 0 | AN19: 0 | AO19: 0 | AP19: 0 | AQ19: 0
C20: Accounting Services (incl software) | D20: $000 | F20: =SUM(H20:AQ20) -> 112 | H20: 6 | I20: 6 | J20: 6 | K20: 15 | L20: 6 | M20: 26 | N20: 10 | O20: 1 | P20: 6 | Q20: 10 | R20: 5 | S20: 5 | T20: 5 | U20: 5 | V20: 0 | W20: 0 | X20: 0 | Y20: 0 | Z20: 0 | AA20: 0 | AB20: 0 | AC20: 0 | AD20: 0 | AE20: 0 | AF20: 0 | AG20: 0 | AH20: 0 | AI20: 0 | AJ20: 0 | AK20: 0 | AL20: 0 | AM20: 0 | AN20: 0 | AO20: 0 | AP20: 0 | AQ20: 0
C21: Audit Services | D21: $000 | F21: =SUM(H21:AQ21) -> 122.5 | H21: 7 | I21: 12.5 | J21: 12.5 | K21: 12.5 | L21: 15.5 | M21: 15.5 | N21: 0 | O21: 0 | P21: 0 | Q21: 0 | R21: 0 | S21: 7 | T21: 20 | U21: 20 | V21: 0 | W21: 0 | X21: 0 | Y21: 0 | Z21: 0 | AA21: 0 | AB21: 0 | AC21: 0 | AD21: 0 | AE21: 0 | AF21: 0 | AG21: 0 | AH21: 0 | AI21: 0 | AJ21: 0 | AK21: 0 | AL21: 0 | AM21: 0 | AN21: 0 | AO21: 0 | AP21: 0 | AQ21: 0
C22: Tax Services | D22: $000 | F22: =SUM(H22:AQ22) -> 102.5 | H22: 0 | I22: 7.5 | J22: 12 | K22: 0 | L22: 7.5 | M22: 12 | N22: 0 | O22: 15 | P22: 0 | Q22: 13 | R22: 13 | S22: 0 | T22: 7.5 | U22: 15 | V22: 0 | W22: 0 | X22: 0 | Y22: 0 | Z22: 0 | AA22: 0 | AB22: 0 | AC22: 0 | AD22: 0 | AE22: 0 | AF22: 0 | AG22: 0 | AH22: 0 | AI22: 0 | AJ22: 0 | AK22: 0 | AL22: 0 | AM22: 0 | AN22: 0 | AO22: 0 | AP22: 0 | AQ22: 0
C23: IT Services | D23: $000 | F23: =SUM(H23:AQ23) -> 234 | H23: 10 | I23: 10 | J23: 10 | K23: 11 | L23: 12 | M23: 13 | N23: 14 | O23: 16 | P23: 18 | Q23: 20 | R23: 22 | S23: 24 | T23: 26 | U23: 28 | V23: 0 | W23: 0 | X23: 0 | Y23: 0 | Z23: 0 | AA23: 0 | AB23: 0 | AC23: 0 | AD23: 0 | AE23: 0 | AF23: 0 | AG23: 0 | AH23: 0 | AI23: 0 | AJ23: 0 | AK23: 0 | AL23: 0 | AM23: 0 | AN23: 0 | AO23: 0 | AP23: 0 | AQ23: 0
C24: Recruiting | D24: $000 | F24: =SUM(H24:AQ24) -> 320 | H24: 0 | I24: 0 | J24: 0 | K24: 0 | L24: 0 | M24: 0 | N24: 40 | O24: 40 | P24: 40 | Q24: 40 | R24: 40 | S24: 40 | T24: 40 | U24: 40 | V24: 0 | W24: 0 | X24: 0 | Y24: 0 | Z24: 0 | AA24: 0 | AB24: 0 | AC24: 0 | AD24: 0 | AE24: 0 | AF24: 0 | AG24: 0 | AH24: 0 | AI24: 0 | AJ24: 0 | AK24: 0 | AL24: 0 | AM24: 0 | AN24: 0 | AO24: 0 | AP24: 0 | AQ24: 0
C25: Overhead Services | D25: $000 | F25: =SUM(H25:AQ25) -> 7989.19 | H25: =SUM(H19:H24) -> 85 | I25: =SUM(I19:I24) -> 98 | J25: =SUM(J19:J24) -> 104.5 | K25: =SUM(K19:K24) -> 104.5 | L25: =SUM(L19:L24) -> 109 | M25: =SUM(M19:M24) -> 136.5 | N25: =SUM(N19:N24) -> 138 | O25: =SUM(O19:O24) -> 150 | ... U25: =SUM(U19:U24) -> 210 | V25: =U25*(1+Inputs!$F$41)^V$6 -> 214.79842 | W25: =V25*(1+Inputs!$F$41)^W$6 -> 219.54642 | X25: =W25*(1+Inputs!$F$41)^X$6 -> 224.39937 | Y25: =X25*(1+Inputs!$F$41)^Y$6 -> 229.3596 | Z25: =Y25*(1+Inputs!$F$41)^Z$6 -> 234.42947 | AA25: =Z25*(1+Inputs!$F$41)^AA$6 -> 239.6114 | AB25: =AA25*(1+Inputs!$F$41)^AB$6 -> 244.90788 | AC25: =AB25*(1+Inputs!$F$41)^AC$6 -> 250.32143 | ... AQ25: =AP25*(1+Inputs!$F$41)^AQ$6 -> 339.96323
C27: Legal Fees - Corporate | D27: $000 | F27: =SUM(H27:AQ27) -> 3484.7256 | H27: 51 | I27: 52 | J27: 52 | K27: 55.714286 | L27: 57.571429 | M27: 59.428571 | N27: 63.142857 | O27: 66.857143 | P27: 70.571429 | Q27: 74.285714 | R27: 78 | S27: 81.714286 | T27: 85.428571 | U27: 89.142857 | V27: =U27*(1+Inputs!$F$41)^V$6 -> 91.179738 | W27: =V27*(1+Inputs!$F$41)^W$6 -> 93.195216 | X27: =W27*(1+Inputs!$F$41)^X$6 -> 95.255245 | Y27: =X27*(1+Inputs!$F$41)^Y$6 -> 97.36081 | Z27: =Y27*(1+Inputs!$F$41)^Z$6 -> 99.512917 | AA27: =Z27*(1+Inputs!$F$41)^AA$6 -> 101.7126 | AB27: =AA27*(1+Inputs!$F$41)^AB$6 -> 103.9609 | AC27: =AB27*(1+Inputs!$F$41)^AC$6 -> 106.25889 | ... AQ27: =AP27*(1+Inputs!$F$41)^AQ$6 -> 144.31092
C28: Legal Fees - Intellectual Property | D28: $000 | F28: =SUM(H28:AQ28) -> 2980.73 | H28: 70 | I28: 70 | J28: 70 | K28: 70 | L28: 70 | M28: 70 | N28: 70 | O28: 70 | P28: 70 | Q28: 70 | R28: 70 | S28: 70 | T28: 70 | U28: 70 | V28: =U28*(1+Inputs!$F$41)^V$6 -> 71.599473 | W28: =V28*(1+Inputs!$F$41)^W$6 -> 73.182141 | X28: =W28*(1+Inputs!$F$41)^X$6 -> 74.799792 | Y28: =X28*(1+Inputs!$F$41)^Y$6 -> 76.4532 | Z28: =Y28*(1+Inputs!$F$41)^Z$6 -> 78.143156 | AA28: =Z28*(1+Inputs!$F$41)^AA$6 -> 79.870467 | AB28: =AA28*(1+Inputs!$F$41)^AB$6 -> 81.63596 | AC28: =AB28*(1+Inputs!$F$41)^AC$6 -> 83.440478 | ... AQ28: =AP28*(1+Inputs!$F$41)^AQ$6 -> 113.32108
C29: Legal Fees - Fundraising | D29: $000 | F29: =SUM(H29:AQ29) -> 300 | H29: 0 | I29: 0 | J29: 300 | K29: 0 | L29: 0 | M29: 0 | N29: 0 | O29: 0 | P29: 0 | Q29: 0 | R29: 0 | S29: 0 | T29: =U29 -> 0 | U29: 0 | V29: 0 | W29: 0 | X29: 0 | Y29: 0 | Z29: 0 | AA29: 0 | AB29: 0 | AC29: 0 | AD29: 0 | AE29: 0 | AF29: 0 | AG29: 0 | AH29: 0 | AI29: 0 | AJ29: 0 | AK29: 0 | AL29: 0 | AM29: 0 | AN29: 0 | AO29: 0 | AP29: 0 | AQ29: 0
C30: Total Legal Fees | D30: $000 | F30: =SUM(F27:F28) -> 6465.4556 | H30: =SUM(H27:H29) -> 121 | I30: =SUM(I27:I29) -> 122 | J30: =SUM(J27:J29) -> 422 | K30: =SUM(K27:K29) -> 125.71429 | L30: =SUM(L27:L29) -> 127.57143 | M30: =SUM(M27:M29) -> 129.42857 | N30: =SUM(N27:N29) -> 133.14286 | O30: =SUM(O27:O29) -> 136.85714 | ... AQ30: =SUM(AQ27:AQ29) -> 257.632
C32: Marketing | D32: $000 | F32: =SUM(H32:AQ32) -> 510.98229 | H32: 12 | I32: 12 | J32: 12 | K32: 12 | L32: 12 | M32: 12 | N32: 12 | O32: 12 | P32: 12 | Q32: 12 | R32: 12 | S32: 12 | T32: 12 | U32: 12 | V32: =U32*(1+Inputs!$F$41)^V$6 -> 12.274195 | W32: =V32*(1+Inputs!$F$41)^W$6 -> 12.54551 | X32: =W32*(1+Inputs!$F$41)^X$6 -> 12.822821 | Y32: =X32*(1+Inputs!$F$41)^Y$6 -> 13.106263 | Z32: =Y32*(1+Inputs!$F$41)^Z$6 -> 13.39597 | AA32: =Z32*(1+Inputs!$F$41)^AA$6 -> 13.69208 | AB32: =AA32*(1+Inputs!$F$41)^AB$6 -> 13.994736 | AC32: =AB32*(1+Inputs!$F$41)^AC$6 -> 14.304082 | ... AQ32: =AP32*(1+Inputs!$F$41)^AQ$6 -> 19.42647
C33: Government Affairs | D33: $000 | F33: =SUM(H33:AQ33) -> 2554.9114 | H33: 60 | I33: 60 | J33: 60 | K33: 60 | L33: 60 | M33: 60 | N33: 60 | O33: 60 | P33: 60 | Q33: 60 | R33: 60 | S33: 60 | T33: 60 | U33: 60 | V33: =U33*(1+Inputs!$F$41)^V$6 -> 61.370977 | W33: =V33*(1+Inputs!$F$41)^W$6 -> 62.727549 | X33: =W33*(1+Inputs!$F$41)^X$6 -> 64.114107 | Y33: =X33*(1+Inputs!$F$41)^Y$6 -> 65.531314 | Z33: =Y33*(1+Inputs!$F$41)^Z$6 -> 66.979848 | AA33: =Z33*(1+Inputs!$F$41)^AA$6 -> 68.460401 | AB33: =AA33*(1+Inputs!$F$41)^AB$6 -> 69.97368 | AC33: =AB33*(1+Inputs!$F$41)^AC$6 -> 71.52041 | ... AQ33: =AP33*(1+Inputs!$F$41)^AQ$6 -> 97.132352
C34: T&E | D34: $000 | F34: =SUM(H34:AQ34) -> 3515.2034 | H34: 56 | I34: 56 | J34: 58 | K34: 60 | L34: 62 | M34: 64 | N34: 68 | O34: 72 | P34: 76 | Q34: 80 | R34: 84 | S34: 88 | T34: 88 | U34: 88 | V34: =U34*(1+Inputs!$F$41)^V$6 -> 90.010767 | W34: =V34*(1+Inputs!$F$41)^W$6 -> 92.000405 | X34: =W34*(1+Inputs!$F$41)^X$6 -> 94.034024 | Y34: =X34*(1+Inputs!$F$41)^Y$6 -> 96.112594 | Z34: =Y34*(1+Inputs!$F$41)^Z$6 -> 98.23711 | AA34: =Z34*(1+Inputs!$F$41)^AA$6 -> 100.40859 | AB34: =AA34*(1+Inputs!$F$41)^AB$6 -> 102.62806 | AC34: =AB34*(1+Inputs!$F$41)^AC$6 -> 104.8966 | ... AQ34: =AP34*(1+Inputs!$F$41)^AQ$6 -> 142.46078
C35: Insurance | D35: $000 | F35: =SUM(H35:AQ35) -> 1787.438 | H35: 41 | I35: 42 | J35: 42 | K35: 42 | L35: 42 | M35: 42 | N35: 42 | O35: 42 | P35: 42 | Q35: 42 | R35: 42 | S35: 42 | T35: 42 | U35: 42 | V35: =U35*(1+Inputs!$F$41)^V$6 -> 42.959684 | W35: =V35*(1+Inputs!$F$41)^W$6 -> 43.909284 | X35: =W35*(1+Inputs!$F$41)^X$6 -> 44.879875 | Y35: =X35*(1+Inputs!$F$41)^Y$6 -> 45.87192 | Z35: =Y35*(1+Inputs!$F$41)^Z$6 -> 46.885893 | AA35: =Z35*(1+Inputs!$F$41)^AA$6 -> 47.92228 | AB35: =AA35*(1+Inputs!$F$41)^AB$6 -> 48.981576 | AC35: =AB35*(1+Inputs!$F$41)^AC$6 -> 50.064287 | ... AQ35: =AP35*(1+Inputs!$F$41)^AQ$6 -> 67.992646
C36: Office | D36: $000 | F36: =SUM(H36:AQ36) -> 4020.3909 | H36: 41 | I36: 46 | J36: 51 | K36: 56 | L36: 61 | M36: 66 | N36: 71 | O36: 76 | P36: 81 | Q36: 86 | R36: 91 | S36: 96 | T36: 100.36364 | U36: 104.72727 | V36: =U36*(1+Inputs!$F$41)^V$6 -> 107.12025 | W36: =V36*(1+Inputs!$F$41)^W$6 -> 109.48809 | X36: =W36*(1+Inputs!$F$41)^X$6 -> 111.90826 | Y36: =X36*(1+Inputs!$F$41)^Y$6 -> 114.38193 | Z36: =Y36*(1+Inputs!$F$41)^Z$6 -> 116.91028 | AA36: =Z36*(1+Inputs!$F$41)^AA$6 -> 119.49452 | AB36: =AA36*(1+Inputs!$F$41)^AB$6 -> 122.13588 | AC36: =AB36*(1+Inputs!$F$41)^AC$6 -> 124.83562 | ... AQ36: =AP36*(1+Inputs!$F$41)^AQ$6 -> 169.54011
C37: Total Other Expenses | D37: $000 | F37: =SUM(H37:AQ37) -> 12388.926 | H37: =SUM(H32:H36) -> 210 | I37: =SUM(I32:I36) -> 216 | J37: =SUM(J32:J36) -> 223 | K37: =SUM(K32:K36) -> 230 | L37: =SUM(L32:L36) -> 237 | M37: =SUM(M32:M36) -> 244 | N37: =SUM(N32:N36) -> 253 | O37: =SUM(O32:O36) -> 262 | ... AQ37: =SUM(AQ32:AQ36) -> 496.55236
C39: Operating Expenses | D39: $000 | F39: =SUM(H39:AQ39) -> 67245.975 | H39: =SUM(H16:H17,H25,H30,H37) -> 1014 | I39: =SUM(I16:I17,I25,I30,I37) -> 1034 | J39: =SUM(J16:J17,J25,J30,J37) -> 1369.5 | K39: =SUM(K16:K17,K25,K30,K37) -> 1101.2143 | L39: =SUM(L16:L17,L25,L30,L37) -> 1135.5714 | M39: =SUM(M16:M17,M25,M30,M37) -> 1192.9286 | N39: =SUM(N16:N17,N25,N30,N37) -> 1250.1429 | O39: =SUM(O16:O17,O25,O30,O37) -> 1317.8571 | ... AQ39: =SUM(AQ16:AQ17,AQ25,AQ30,AQ37) -> 2753.4919
B41: R&D
C42: Cement placement hardware | D42: $000 | F42: =SUM(H42:AQ42) -> 168 | H42: 12 | I42: 12 | J42: 12 | K42: 12 | L42: 12 | M42: 12 | N42: 12 | O42: 12 | P42: 12 | Q42: 12 | R42: 12 | S42: 12 | T42: =U42 -> 12 | U42: 12 | V42: 0 | W42: 0 | X42: 0 | Y42: 0 | Z42: 0 | AA42: 0 | AB42: 0 | AC42: 0 | AD42: 0 | AE42: 0 | AF42: 0 | AG42: 0 | AH42: 0 | AI42: 0 | AJ42: 0 | AK42: 0 | AL42: 0 | AM42: 0 | AN42: 0 | AO42: 0 | AP42: 0 | AQ42: 0
C43: LCZ and sheath cements | D43: $000 | F43: =SUM(H43:AQ43) -> 1633.3333 | H43: 116.66667 | I43: 116.66667 | J43: 116.66667 | K43: 116.66667 | L43: 116.66667 | M43: 116.66667 | N43: 116.66667 | O43: 116.66667 | P43: 116.66667 | Q43: 116.66667 | R43: 116.66667 | S43: 116.66667 | T43: =U43 -> 116.66667 | U43: 116.66667 | V43: 0 | W43: 0 | X43: 0 | Y43: 0 | Z43: 0 | AA43: 0 | AB43: 0 | AC43: 0 | AD43: 0 | AE43: 0 | AF43: 0 | AG43: 0 | AH43: 0 | AI43: 0 | AJ43: 0 | AK43: 0 | AL43: 0 | AM43: 0 | AN43: 0 | AO43: 0 | AP43: 0 | AQ43: 0
C44: VIT & well design | D44: $000 | F44: =SUM(H44:AQ44) -> 280 | H44: 20 | I44: 20 | J44: 20 | K44: 20 | L44: 20 | M44: 20 | N44: 20 | O44: 20 | P44: 20 | Q44: 20 | R44: 20 | S44: 20 | T44: =U44 -> 20 | U44: 20 | V44: 0 | W44: 0 | X44: 0 | Y44: 0 | Z44: 0 | AA44: 0 | AB44: 0 | AC44: 0 | AD44: 0 | AE44: 0 | AF44: 0 | AG44: 0 | AH44: 0 | AI44: 0 | AJ44: 0 | AK44: 0 | AL44: 0 | AM44: 0 | AN44: 0 | AO44: 0 | AP44: 0 | AQ44: 0
C45: Higher temperature drilling | D45: $000 | F45: =SUM(H45:AQ45) -> 294 | H45: 21 | I45: 21 | J45: 21 | K45: 21 | L45: 21 | M45: 21 | N45: 21 | O45: 21 | P45: 21 | Q45: 21 | R45: 21 | S45: 21 | T45: 21 | U45: 21 | V45: 0 | W45: 0 | X45: 0 | Y45: 0 | Z45: 0 | AA45: 0 | AB45: 0 | AC45: 0 | AD45: 0 | AE45: 0 | AF45: 0 | AG45: 0 | AH45: 0 | AI45: 0 | AJ45: 0 | AK45: 0 | AL45: 0 | AM45: 0 | AN45: 0 | AO45: 0 | AP45: 0 | AQ45: 0
C46: Sensors & measurement | D46: $000 | F46: =SUM(H46:AQ46) -> 294 | H46: 21 | I46: 21 | J46: 21 | K46: 21 | L46: 21 | M46: 21 | N46: 21 | O46: 21 | P46: 21 | Q46: 21 | R46: 21 | S46: 21 | T46: 21 | U46: 21 | V46: 0 | W46: 0 | X46: 0 | Y46: 0 | Z46: 0 | AA46: 0 | AB46: 0 | AC46: 0 | AD46: 0 | AE46: 0 | AF46: 0 | AG46: 0 | AH46: 0 | AI46: 0 | AJ46: 0 | AK46: 0 | AL46: 0 | AM46: 0 | AN46: 0 | AO46: 0 | AP46: 0 | AQ46: 0
C47: Perforation sealing | D47: $000 | F47: =SUM(H47:AQ47) -> 308 | H47: 22 | I47: 22 | J47: 22 | K47: 22 | L47: 22 | M47: 22 | N47: 22 | O47: 22 | P47: 22 | Q47: 22 | R47: 22 | S47: 22 | T47: 22 | U47: 22 | V47: 0 | W47: 0 | X47: 0 | Y47: 0 | Z47: 0 | AA47: 0 | AB47: 0 | AC47: 0 | AD47: 0 | AE47: 0 | AF47: 0 | AG47: 0 | AH47: 0 | AI47: 0 | AJ47: 0 | AK47: 0 | AL47: 0 | AM47: 0 | AN47: 0 | AO47: 0 | AP47: 0 | AQ47: 0
C48: On-site testing cells | D48: $000 | F48: =SUM(H48:AQ48) -> 116.66667 | H48: 8.3333333 | I48: 8.3333333 | J48: 8.3333333 | K48: 8.3333333 | L48: 8.3333333 | M48: 8.3333333 | N48: 8.3333333 | O48: 8.3333333 | P48: 8.3333333 | Q48: 8.3333333 | R48: 8.3333333 | S48: 8.3333333 | T48: =U48 -> 8.3333333 | U48: 8.3333333 | V48: 0 | W48: 0 | X48: 0 | Y48: 0 | Z48: 0 | AA48: 0 | AB48: 0 | AC48: 0 | AD48: 0 | AE48: 0 | AF48: 0 | AG48: 0 | AH48: 0 | AI48: 0 | AJ48: 0 | AK48: 0 | AL48: 0 | AM48: 0 | AN48: 0 | AO48: 0 | AP48: 0 | AQ48: 0
C49: Heat flow modeling software | D49: $000 | F49: =SUM(H49:AQ49) -> 840 | H49: 60 | I49: 60 | J49: 60 | K49: 60 | L49: 60 | M49: 60 | N49: 60 | O49: 60 | P49: 60 | Q49: 60 | R49: 60 | S49: 60 | T49: =U49 -> 60 | U49: 60 | V49: 0 | W49: 0 | X49: 0 | Y49: 0 | Z49: 0 | AA49: 0 | AB49: 0 | AC49: 0 | AD49: 0 | AE49: 0 | AF49: 0 | AG49: 0 | AH49: 0 | AI49: 0 | AJ49: 0 | AK49: 0 | AL49: 0 | AM49: 0 | AN49: 0 | AO49: 0 | AP49: 0 | AQ49: 0
C50: Drilling management software | D50: $000 | F50: =SUM(H50:AQ50) -> 233.33333 | H50: 16.666667 | I50: 16.666667 | J50: 16.666667 | K50: 16.666667 | L50: 16.666667 | M50: 16.666667 | N50: 16.666667 | O50: 16.666667 | P50: 16.666667 | Q50: 16.666667 | R50: 16.666667 | S50: 16.666667 | T50: =U50 -> 16.666667 | U50: 16.666667 | V50: 0 | W50: 0 | X50: 0 | Y50: 0 | Z50: 0 | AA50: 0 | AB50: 0 | AC50: 0 | AD50: 0 | AE50: 0 | AF50: 0 | AG50: 0 | AH50: 0 | AI50: 0 | AJ50: 0 | AK50: 0 | AL50: 0 | AM50: 0 | AN50: 0 | AO50: 0 | AP50: 0 | AQ50: 0
C51: Materials database | D51: $000 | F51: =SUM(H51:AQ51) -> 120 | H51: 20 | I51: 20 | J51: 20 | K51: 20 | L51: 20 | M51: 20 | N51: 0 | O51: 0 | P51: 0 | Q51: 0 | R51: 0 | S51: 0 | T51: =U51 -> 0 | U51: 0 | V51: 0 | W51: 0 | X51: 0 | Y51: 0 | Z51: 0 | AA51: 0 | AB51: 0 | AC51: 0 | AD51: 0 | AE51: 0 | AF51: 0 | AG51: 0 | AH51: 0 | AI51: 0 | AJ51: 0 | AK51: 0 | AL51: 0 | AM51: 0 | AN51: 0 | AO51: 0 | AP51: 0 | AQ51: 0
C52: Other (Advisors) | D52: $000 | F52: =SUM(H52:AQ52) -> 35 | H52: 2.5 | I52: 2.5 | J52: 2.5 | K52: 2.5 | L52: 2.5 | M52: 2.5 | N52: 2.5 | O52: 2.5 | P52: 2.5 | Q52: 2.5 | R52: 2.5 | S52: 2.5 | T52: =U52 -> 2.5 | U52: 2.5 | V52: 0 | W52: 0 | X52: 0 | Y52: 0 | Z52: 0 | AA52: 0 | AB52: 0 | AC52: 0 | AD52: 0 | AE52: 0 | AF52: 0 | AG52: 0 | AH52: 0 | AI52: 0 | AJ52: 0 | AK52: 0 | AL52: 0 | AM52: 0 | AN52: 0 | AO52: 0 | AP52: 0 | AQ52: 0
C53: R&D | D53: $000 | F53: =SUM(H53:AQ53) -> 12901.654 | H53: =SUM(H42:H52) -> 320.16667 | I53: =SUM(I42:I52) -> 320.16667 | J53: =SUM(J42:J52) -> 320.16667 | K53: =SUM(K42:K52) -> 320.16667 | L53: =SUM(L42:L52) -> 320.16667 | M53: =SUM(M42:M52) -> 320.16667 | N53: =SUM(N42:N52) -> 300.16667 | O53: =SUM(O42:O52) -> 300.16667 | ... U53: =SUM(U42:U52) -> 300.16667 | V53: =AVERAGE(P53:U53)*(1+Inputs!$F$41)^V$6 -> 307.02536 | W53: =V53*(1+Inputs!$F$41)^W$6 -> 313.81199 | X53: =W53*(1+Inputs!$F$41)^X$6 -> 320.74863 | Y53: =X53*(1+Inputs!$F$41)^Y$6 -> 327.8386 | Z53: =Y53*(1+Inputs!$F$41)^Z$6 -> 335.08529 | AA53: =Z53*(1+Inputs!$F$41)^AA$6 -> 342.49217 | AB53: =AA53*(1+Inputs!$F$41)^AB$6 -> 350.06277 | AC53: =AB53*(1+Inputs!$F$41)^AC$6 -> 357.80072 | AD53: =AC53*(1+Inputs!$F$41)^AD$6 -> 365.70971 | ... AQ53: =AP53*(1+Inputs!$F$41)^AQ$6 -> 485.93157
C55: Operating Expenses + R&D | D55: $000 | F55: =SUM(H55:AQ55) -> 80147.63 | H55: =H39+H53 -> 1334.1667 | I55: =I39+I53 -> 1354.1667 | J55: =J39+J53 -> 1689.6667 | K55: =K39+K53 -> 1421.381 | L55: =L39+L53 -> 1455.7381 | M55: =M39+M53 -> 1513.0952 | N55: =N39+N53 -> 1550.3095 | O55: =O39+O53 -> 1618.0238 | ... AQ55: =AQ39+AQ53 -> 3239.4235
B57: XGS DevCo Asset Spend
C58: Surface Engineering* | D58: $000 | F58: =SUM(H58:AQ58) -> 200 | H58: 0 | I58: 0 | J58: 50 | K58: 50 | L58: 50 | M58: 50 | N58: 0 | O58: 0 | P58: 0 | Q58: 0 | R58: 0 | S58: 0 | T58: 0 | U58: 0 | V58: 0 | W58: 0 | X58: 0 | Y58: 0 | Z58: 0 | AA58: 0 | AB58: 0 | AC58: 0 | AD58: 0 | AE58: 0 | AF58: 0 | AG58: 0 | AH58: 0 | AI58: 0 | AJ58: 0 | AK58: 0 | AL58: 0 | AM58: 0 | AN58: 0 | AO58: 0 | AP58: 0 | AQ58: 0
C59: Subsurface Engineering* | D59: $000 | F59: =SUM(H59:AQ59) -> 300 | H59: 0 | I59: 0 | J59: 75 | K59: 75 | L59: 75 | M59: 75 | N59: 0 | O59: 0 | P59: 0 | Q59: 0 | R59: 0 | S59: 0 | T59: 0 | U59: 0 | V59: 0 | W59: 0 | X59: 0 | Y59: 0 | Z59: 0 | AA59: 0 | AB59: 0 | AC59: 0 | AD59: 0 | AE59: 0 | AF59: 0 | AG59: 0 | AH59: 0 | AI59: 0 | AJ59: 0 | AK59: 0 | AL59: 0 | AM59: 0 | AN59: 0 | AO59: 0 | AP59: 0 | AQ59: 0
C60: Early Stage Project Development (Permitting, Power Delivery)* | D60: $000 | F60: =SUM(H60:AQ60) -> 1668 | H60: 0 | I60: 0 | J60: 417 | K60: 417 | L60: 417 | M60: 417 | N60: 0 | O60: 0 | P60: 0 | Q60: 0 | R60: 0 | S60: 0 | T60: 0 | U60: 0 | V60: 0 | W60: 0 | X60: 0 | Y60: 0 | Z60: 0 | AA60: 0 | AB60: 0 | AC60: 0 | AD60: 0 | AE60: 0 | AF60: 0 | AG60: 0 | AH60: 0 | AI60: 0 | AJ60: 0 | AK60: 0 | AL60: 0 | AM60: 0 | AN60: 0 | AO60: 0 | AP60: 0 | AQ60: 0
C61: Geophysical Surveys* | D61: $000 | F61: =SUM(H61:AQ61) -> 1734.3333 | H61: 0 | I61: 0 | J61: 433.58333 | K61: 433.58333 | L61: 433.58333 | M61: 433.58333 | N61: 0 | O61: 0 | P61: 0 | Q61: 0 | R61: 0 | S61: 0 | T61: 0 | U61: 0 | V61: 0 | W61: 0 | X61: 0 | Y61: 0 | Z61: 0 | AA61: 0 | AB61: 0 | AC61: 0 | AD61: 0 | AE61: 0 | AF61: 0 | AG61: 0 | AH61: 0 | AI61: 0 | AJ61: 0 | AK61: 0 | AL61: 0 | AM61: 0 | AN61: 0 | AO61: 0 | AP61: 0 | AQ61: 0
C62: Site Control* | D62: $000 | F62: =SUM(H62:AQ62) -> 800 | H62: 0 | I62: 0 | J62: 200 | K62: 200 | L62: 200 | M62: 200 | N62: 0 | O62: 0 | P62: 0 | Q62: 0 | R62: 0 | S62: 0 | T62: 0 | U62: 0 | V62: 0 | W62: 0 | X62: 0 | Y62: 0 | Z62: 0 | AA62: 0 | AB62: 0 | AC62: 0 | AD62: 0 | AE62: 0 | AF62: 0 | AG62: 0 | AH62: 0 | AI62: 0 | AJ62: 0 | AK62: 0 | AL62: 0 | AM62: 0 | AN62: 0 | AO62: 0 | AP62: 0 | AQ62: 0
C63: Total Project Expenses | D63: $000 | F63: =SUM(H63:AQ63) -> 4902.3333 | H63: 100 | I63: 100 | J63: =SUM(J58:J62) -> 1175.5833 | K63: =SUM(K58:K62) -> 1175.5833 | L63: =SUM(L58:L62) -> 1175.5833 | M63: =SUM(M58:M62) -> 1175.5833 | N63: =SUM(N58:N62) -> 0 | O63: =SUM(O58:O62) -> 0 | P63: =SUM(P58:P62) -> 0 | Q63: =SUM(Q58:Q62) -> 0 | ... AQ63: =SUM(AQ58:AQ62) -> 0
C65: Total Operating, R&D, and Project Expenses | D65: $000 | F65: =SUM(H65:AQ65) -> 85049.963 | H65: =H55+H63 -> 1434.1667 | I65: =I55+I63 -> 1454.1667 | J65: =J55+J63 -> 2865.25 | K65: =K55+K63 -> 2596.9643 | L65: =L55+L63 -> 2631.3214 | M65: =M55+M63 -> 2688.6786 | N65: =N55+N63 -> 1550.3095 | O65: =O55+O63 -> 1618.0238 | ... AQ65: =AQ55+AQ63 -> 3239.4235

Sheet Historical PnL (M)
B2: XGS Enterprise Model
B3: Historical PnL (Monthly)
B5: Date | E5: =Inputs!$F$7 -> 45322 | G5: =EOMONTH(E5,-1) -> 45291 | H5: =EOMONTH(G5,1) -> 45322 | I5: =EOMONTH(H5,1) -> 45351 | J5: =EOMONTH(I5,1) -> 45382 | K5: =EOMONTH(J5,1) -> 45412 | L5: =EOMONTH(K5,1) -> 45443 | M5: =EOMONTH(L5,1) -> 45473 | N5: =EOMONTH(M5,1) -> 45504 | O5: =EOMONTH(N5,1) -> 45535 | ... AE5: =EOMONTH(AD5,1) -> 46022
B6: YearFrac | F6: =SUM(G6:BS6) -> 1.9972222 | H6: =YEARFRAC(H5,G5) -> 0.083333333 | I6: =YEARFRAC(I5,H5) -> 0.080555556 | J6: =YEARFRAC(J5,I5) -> 0.086111111 | K6: =YEARFRAC(K5,J5) -> 0.083333333 | L6: =YEARFRAC(L5,K5) -> 0.083333333 | M6: =YEARFRAC(M5,L5) -> 0.083333333 | N6: =YEARFRAC(N5,M5) -> 0.083333333 | O6: =YEARFRAC(O5,N5) -> 0.083333333 | ... AE6: =YEARFRAC(AE5,AD5) -> 0.083333333
B7: Year End | H7: =DATE(YEAR(H5),12,31) -> 45657 | I7: =DATE(YEAR(I5),12,31) -> 45657 | J7: =DATE(YEAR(J5),12,31) -> 45657 | K7: =DATE(YEAR(K5),12,31) -> 45657 | L7: =DATE(YEAR(L5),12,31) -> 45657 | M7: =DATE(YEAR(M5),12,31) -> 45657 | N7: =DATE(YEAR(N5),12,31) -> 45657 | O7: =DATE(YEAR(O5),12,31) -> 45657 | ... AE7: =DATE(YEAR(AE5),12,31) -> 46022
A9: Operating Profit
B11: Revenue | E11: SOURCE
C12: Revenue | D12: $000 | E12: I/S | F12: =SUM(H12:AE12) -> 0 | H12: =INDEX(_HistIS_M_Data,MATCH($C12,_HistIS_M_Labels,0),MATCH(H$5,_HistIS_M_MonthEnd,0))/1000 -> 0 | I12: =INDEX(_HistIS_M_Data,MATCH($C12,_HistIS_M_Labels,0),MATCH(I$5,_HistIS_M_MonthEnd,0)) -> 0 | J12: =INDEX(_HistIS_M_Data,MATCH($C12,_HistIS_M_Labels,0),MATCH(J$5,_HistIS_M_MonthEnd,0)) -> 0 | K12: =INDEX(_HistIS_M_Data,MATCH($C12,_HistIS_M_Labels,0),MATCH(K$5,_HistIS_M_MonthEnd,0)) -> 0 | L12: =INDEX(_HistIS_M_Data,MATCH($C12,_HistIS_M_Labels,0),MATCH(L$5,_HistIS_M_MonthEnd,0)) -> 0 | M12: =INDEX(_HistIS_M_Data,MATCH($C12,_HistIS_M_Labels,0),MATCH(M$5,_HistIS_M_MonthEnd,0)) -> 0 | N12: =INDEX(_HistIS_M_Data,MATCH($C12,_HistIS_M_Labels,0),MATCH(N$5,_HistIS_M_MonthEnd,0)) -> 0 | O12: =INDEX(_HistIS_M_Data,MATCH($C12,_HistIS_M_Labels,0),MATCH(O$5,_HistIS_M_MonthEnd,0)) -> 0 | P12: =INDEX(_HistIS_M_Data,MATCH($C12,_HistIS_M_Labels,0),MATCH(P$5,_HistIS_M_MonthEnd,0)) -> 0 | ... AE12: =INDEX(_HistIS_M_Data,MATCH($C12,_HistIS_M_Labels,0),MATCH(AE$5,_HistIS_M_MonthEnd,0)) -> 0
B14: SG&A
C15: New Headcount (FTE)
C16: Total Headcount (FTE)
C18: Payroll | D18: $000 | E18: I/S | F18: =SUM(H18:AE18) -> 7733.0126 | H18: =SUMIFS(INDEX(_HistIS_M_Data,0,MATCH(H$5,_HistIS_M_MonthEnd,0)),_HistIS_M_Labels,$C18)/1000 -> 267.3705 | I18: =SUMIFS(INDEX(_HistIS_M_Data,0,MATCH(I$5,_HistIS_M_MonthEnd,0)),_HistIS_M_Labels,$C18)/1000 -> 294.41314 | J18: =SUMIFS(INDEX(_HistIS_M_Data,0,MATCH(J$5,_HistIS_M_MonthEnd,0)),_HistIS_M_Labels,$C18)/1000 -> 160.39341 | K18: =SUMIFS(INDEX(_HistIS_M_Data,0,MATCH(K$5,_HistIS_M_MonthEnd,0)),_HistIS_M_Labels,$C18)/1000 -> 143.95634 | L18: =SUMIFS(INDEX(_HistIS_M_Data,0,MATCH(L$5,_HistIS_M_MonthEnd,0)),_HistIS_M_Labels,$C18)/1000 -> 261.99758 | M18: =SUMIFS(INDEX(_HistIS_M_Data,0,MATCH(M$5,_HistIS_M_MonthEnd,0)),_HistIS_M_Labels,$C18)/1000 -> 151.31328 | N18: =SUMIFS(INDEX(_HistIS_M_Data,0,MATCH(N$5,_HistIS_M_MonthEnd,0)),_HistIS_M_Labels,$C18)/1000 -> 217.7044 | O18: =SUMIFS(INDEX(_HistIS_M_Data,0,MATCH(O$5,_HistIS_M_MonthEnd,0)),_HistIS_M_Labels,$C18)/1000 -> 204.98362 | ... AE18: =SUMIFS(INDEX(_HistIS_M_Data,0,MATCH(AE$5,_HistIS_M_MonthEnd,0)),_HistIS_M_Labels,$C18)/1000 -> 511.714
C19: Overhead | D19: $000 | E19: I/S | F19: =SUM(H19:AE19) -> 339.44912 | H19: =SUMIFS(INDEX(_HistIS_M_Data,0,MATCH(H$5,_HistIS_M_MonthEnd,0)),_HistIS_M_Labels,$C19)/1000 -> 14.491 | I19: =SUMIFS(INDEX(_HistIS_M_Data,0,MATCH(I$5,_HistIS_M_MonthEnd,0)),_HistIS_M_Labels,$C19)/1000 -> 12.28007 | J19: =SUMIFS(INDEX(_HistIS_M_Data,0,MATCH(J$5,_HistIS_M_MonthEnd,0)),_HistIS_M_Labels,$C19)/1000 -> 11.73929 | K19: =SUMIFS(INDEX(_HistIS_M_Data,0,MATCH(K$5,_HistIS_M_MonthEnd,0)),_HistIS_M_Labels,$C19)/1000 -> 6.56512 | L19: =SUMIFS(INDEX(_HistIS_M_Data,0,MATCH(L$5,_HistIS_M_MonthEnd,0)),_HistIS_M_Labels,$C19)/1000 -> 9.13051 | M19: =SUMIFS(INDEX(_HistIS_M_Data,0,MATCH(M$5,_HistIS_M_MonthEnd,0)),_HistIS_M_Labels,$C19)/1000 -> 9.71567 | N19: =SUMIFS(INDEX(_HistIS_M_Data,0,MATCH(N$5,_HistIS_M_MonthEnd,0)),_HistIS_M_Labels,$C19)/1000 -> 11.31257 | O19: =SUMIFS(INDEX(_HistIS_M_Data,0,MATCH(O$5,_HistIS_M_MonthEnd,0)),_HistIS_M_Labels,$C19)/1000 -> 14.88367 | ... AE19: =SUMIFS(INDEX(_HistIS_M_Data,0,MATCH(AE$5,_HistIS_M_MonthEnd,0)),_HistIS_M_Labels,$C19)/1000 -> 25.067
C21: Subject Matter experts | D21: $000 | E21: I/S | F21: =SUM(H21:AE21) -> 142 | H21: =SUMIFS(INDEX(_HistIS_M_Data,0,MATCH(H$5,_HistIS_M_MonthEnd,0)),_HistIS_M_Labels,$C21)/1000 -> 20 | I21: =SUMIFS(INDEX(_HistIS_M_Data,0,MATCH(I$5,_HistIS_M_MonthEnd,0)),_HistIS_M_Labels,$C21)/1000 -> 20 | J21: =SUMIFS(INDEX(_HistIS_M_Data,0,MATCH(J$5,_HistIS_M_MonthEnd,0)),_HistIS_M_Labels,$C21)/1000 -> 20 | K21: =SUMIFS(INDEX(_HistIS_M_Data,0,MATCH(K$5,_HistIS_M_MonthEnd,0)),_HistIS_M_Labels,$C21)/1000 -> 20 | L21: =SUMIFS(INDEX(_HistIS_M_Data,0,MATCH(L$5,_HistIS_M_MonthEnd,0)),_HistIS_M_Labels,$C21)/1000 -> 20 | M21: =SUMIFS(INDEX(_HistIS_M_Data,0,MATCH(M$5,_HistIS_M_MonthEnd,0)),_HistIS_M_Labels,$C21)/1000 -> 9 | N21: =SUMIFS(INDEX(_HistIS_M_Data,0,MATCH(N$5,_HistIS_M_MonthEnd,0)),_HistIS_M_Labels,$C21)/1000 -> 0 | O21: =SUMIFS(INDEX(_HistIS_M_Data,0,MATCH(O$5,_HistIS_M_MonthEnd,0)),_HistIS_M_Labels,$C21)/1000 -> 0 | ... AE21: =SUMIFS(INDEX(_HistIS_M_Data,0,MATCH(AE$5,_HistIS_M_MonthEnd,0)),_HistIS_M_Labels,$C21)/1000 -> 0
C22: Eng services | D22: $000 | E22: I/S | F22: =SUM(H22:AE22) -> 279.51359 | H22: =SUMIFS(INDEX(_HistIS_M_Data,0,MATCH(H$5,_HistIS_M_MonthEnd,0)),_HistIS_M_Labels,$C22)/1000 -> 6.825 | I22: =SUMIFS(INDEX(_HistIS_M_Data,0,MATCH(I$5,_HistIS_M_MonthEnd,0)),_HistIS_M_Labels,$C22)/1000 -> 6.9375 | J22: =SUMIFS(INDEX(_HistIS_M_Data,0,MATCH(J$5,_HistIS_M_MonthEnd,0)),_HistIS_M_Labels,$C22)/1000 -> 10.5 | K22: =SUMIFS(INDEX(_HistIS_M_Data,0,MATCH(K$5,_HistIS_M_MonthEnd,0)),_HistIS_M_Labels,$C22)/1000 -> 31.80059 | L22: =SUMIFS(INDEX(_HistIS_M_Data,0,MATCH(L$5,_HistIS_M_MonthEnd,0)),_HistIS_M_Labels,$C22)/1000 -> 43.6375 | M22: =SUMIFS(INDEX(_HistIS_M_Data,0,MATCH(M$5,_HistIS_M_MonthEnd,0)),_HistIS_M_Labels,$C22)/1000 -> 0 | N22: =SUMIFS(INDEX(_HistIS_M_Data,0,MATCH(N$5,_HistIS_M_MonthEnd,0)),_HistIS_M_Labels,$C22)/1000 -> 7 | O22: =SUMIFS(INDEX(_HistIS_M_Data,0,MATCH(O$5,_HistIS_M_MonthEnd,0)),_HistIS_M_Labels,$C22)/1000 -> 31.575 | ... AE22: =SUMIFS(INDEX(_HistIS_M_Data,0,MATCH(AE$5,_HistIS_M_MonthEnd,0)),_HistIS_M_Labels,$C22)/1000 -> 0
C23: Software services | D23: $000 | E23: I/S | F23: =SUM(H23:AE23) -> 130.63304 | H23: =SUMIFS(INDEX(_HistIS_M_Data,0,MATCH(H$5,_HistIS_M_MonthEnd,0)),_HistIS_M_Labels,$C23)/1000 -> 0 | I23: =SUMIFS(INDEX(_HistIS_M_Data,0,MATCH(I$5,_HistIS_M_MonthEnd,0)),_HistIS_M_Labels,$C23)/1000 -> 0 | J23: =SUMIFS(INDEX(_HistIS_M_Data,0,MATCH(J$5,_HistIS_M_MonthEnd,0)),_HistIS_M_Labels,$C23)/1000 -> 0 | K23: =SUMIFS(INDEX(_HistIS_M_Data,0,MATCH(K$5,_HistIS_M_MonthEnd,0)),_HistIS_M_Labels,$C23)/1000 -> 0 | L23: =SUMIFS(INDEX(_HistIS_M_Data,0,MATCH(L$5,_HistIS_M_MonthEnd,0)),_HistIS_M_Labels,$C23)/1000 -> 1.34 | M23: =SUMIFS(INDEX(_HistIS_M_Data,0,MATCH(M$5,_HistIS_M_MonthEnd,0)),_HistIS_M_Labels,$C23)/1000 -> 0 | N23: =SUMIFS(INDEX(_HistIS_M_Data,0,MATCH(N$5,_HistIS_M_MonthEnd,0)),_HistIS_M_Labels,$C23)/1000 -> 0 | O23: =SUMIFS(INDEX(_HistIS_M_Data,0,MATCH(O$5,_HistIS_M_MonthEnd,0)),_HistIS_M_Labels,$C23)/1000 -> 0 | ... AE23: =SUMIFS(INDEX(_HistIS_M_Data,0,MATCH(AE$5,_HistIS_M_MonthEnd,0)),_HistIS_M_Labels,$C23)/1000 -> 0
C24: Accounting Services (incl software) | D24: $000 | E24: I/S | F24: =SUM(H24:AE24) -> 81.042 | H24: =SUMIFS(INDEX(_HistIS_M_Data,0,MATCH(H$5,_HistIS_M_MonthEnd,0)),_HistIS_M_Labels,$C24)/1000 -> 0 | I24: =SUMIFS(INDEX(_HistIS_M_Data,0,MATCH(I$5,_HistIS_M_MonthEnd,0)),_HistIS_M_Labels,$C24)/1000 -> 0 | J24: =SUMIFS(INDEX(_HistIS_M_Data,0,MATCH(J$5,_HistIS_M_MonthEnd,0)),_HistIS_M_Labels,$C24)/1000 -> 0 | K24: =SUMIFS(INDEX(_HistIS_M_Data,0,MATCH(K$5,_HistIS_M_MonthEnd,0)),_HistIS_M_Labels,$C24)/1000 -> 0 | L24: =SUMIFS(INDEX(_HistIS_M_Data,0,MATCH(L$5,_HistIS_M_MonthEnd,0)),_HistIS_M_Labels,$C24)/1000 -> 0 | M24: =SUMIFS(INDEX(_HistIS_M_Data,0,MATCH(M$5,_HistIS_M_MonthEnd,0)),_HistIS_M_Labels,$C24)/1000 -> 0 | N24: =SUMIFS(INDEX(_HistIS_M_Data,0,MATCH(N$5,_HistIS_M_MonthEnd,0)),_HistIS_M_Labels,$C24)/1000 -> 0 | O24: =SUMIFS(INDEX(_HistIS_M_Data,0,MATCH(O$5,_HistIS_M_MonthEnd,0)),_HistIS_M_Labels,$C24)/1000 -> 0 | ... AE24: =SUMIFS(INDEX(_HistIS_M_Data,0,MATCH(AE$5,_HistIS_M_MonthEnd,0)),_HistIS_M_Labels,$C24)/1000 -> 15.6
C25: PR | D25: $000 | E25: I/S | F25: =SUM(H25:AE25) -> 462.85806 | H25: =SUMIFS(INDEX(_HistIS_M_Data,0,MATCH(H$5,_HistIS_M_MonthEnd,0)),_HistIS_M_Labels,$C25)/1000 -> 7.91796 | I25: =SUMIFS(INDEX(_HistIS_M_Data,0,MATCH(I$5,_HistIS_M_MonthEnd,0)),_HistIS_M_Labels,$C25)/1000 -> 27.08748 | J25: =SUMIFS(INDEX(_HistIS_M_Data,0,MATCH(J$5,_HistIS_M_MonthEnd,0)),_HistIS_M_Labels,$C25)/1000 -> 26.7164 | K25: =SUMIFS(INDEX(_HistIS_M_Data,0,MATCH(K$5,_HistIS_M_MonthEnd,0)),_HistIS_M_Labels,$C25)/1000 -> 80.72572 | L25: =SUMIFS(INDEX(_HistIS_M_Data,0,MATCH(L$5,_HistIS_M_MonthEnd,0)),_HistIS_M_Labels,$C25)/1000 -> 32.70528 | M25: =SUMIFS(INDEX(_HistIS_M_Data,0,MATCH(M$5,_HistIS_M_MonthEnd,0)),_HistIS_M_Labels,$C25)/1000 -> 38.58767 | N25: =SUMIFS(INDEX(_HistIS_M_Data,0,MATCH(N$5,_HistIS_M_MonthEnd,0)),_HistIS_M_Labels,$C25)/1000 -> 44.9655 | O25: =SUMIFS(INDEX(_HistIS_M_Data,0,MATCH(O$5,_HistIS_M_MonthEnd,0)),_HistIS_M_Labels,$C25)/1000 -> 18.99777 | ... AE25: =SUMIFS(INDEX(_HistIS_M_Data,0,MATCH(AE$5,_HistIS_M_MonthEnd,0)),_HistIS_M_Labels,$C25)/1000 -> 0
C26: Audit Services | D26: $000 | E26: I/S | F26: =SUM(H26:AE26) -> 169.0119 | H26: =SUMIFS(INDEX(_HistIS_M_Data,0,MATCH(H$5,_HistIS_M_MonthEnd,0)),_HistIS_M_Labels,$C26)/1000 -> 0 | I26: =SUMIFS(INDEX(_HistIS_M_Data,0,MATCH(I$5,_HistIS_M_MonthEnd,0)),_HistIS_M_Labels,$C26)/1000 -> 0 | J26: =SUMIFS(INDEX(_HistIS_M_Data,0,MATCH(J$5,_HistIS_M_MonthEnd,0)),_HistIS_M_Labels,$C26)/1000 -> 0 | K26: =SUMIFS(INDEX(_HistIS_M_Data,0,MATCH(K$5,_HistIS_M_MonthEnd,0)),_HistIS_M_Labels,$C26)/1000 -> 0 | L26: =SUMIFS(INDEX(_HistIS_M_Data,0,MATCH(L$5,_HistIS_M_MonthEnd,0)),_HistIS_M_Labels,$C26)/1000 -> 0 | M26: =SUMIFS(INDEX(_HistIS_M_Data,0,MATCH(M$5,_HistIS_M_MonthEnd,0)),_HistIS_M_Labels,$C26)/1000 -> 0 | N26: =SUMIFS(INDEX(_HistIS_M_Data,0,MATCH(N$5,_HistIS_M_MonthEnd,0)),_HistIS_M_Labels,$C26)/1000 -> 0 | O26: =SUMIFS(INDEX(_HistIS_M_Data,0,MATCH(O$5,_HistIS_M_MonthEnd,0)),_HistIS_M_Labels,$C26)/1000 -> 0 | ... AE26: =SUMIFS(INDEX(_HistIS_M_Data,0,MATCH(AE$5,_HistIS_M_MonthEnd,0)),_HistIS_M_Labels,$C26)/1000 -> 0.036
C27: Tax Services | D27: $000 | E27: I/S | F27: =SUM(H27:AE27) -> 17.987 | H27: =SUMIFS(INDEX(_HistIS_M_Data,0,MATCH(H$5,_HistIS_M_MonthEnd,0)),_HistIS_M_Labels,$C27)/1000 -> 0 | I27: =SUMIFS(INDEX(_HistIS_M_Data,0,MATCH(I$5,_HistIS_M_MonthEnd,0)),_HistIS_M_Labels,$C27)/1000 -> 0 | J27: =SUMIFS(INDEX(_HistIS_M_Data,0,MATCH(J$5,_HistIS_M_MonthEnd,0)),_HistIS_M_Labels,$C27)/1000 -> 0 | K27: =SUMIFS(INDEX(_HistIS_M_Data,0,MATCH(K$5,_HistIS_M_MonthEnd,0)),_HistIS_M_Labels,$C27)/1000 -> 0 | L27: =SUMIFS(INDEX(_HistIS_M_Data,0,MATCH(L$5,_HistIS_M_MonthEnd,0)),_HistIS_M_Labels,$C27)/1000 -> 0 | M27: =SUMIFS(INDEX(_HistIS_M_Data,0,MATCH(M$5,_HistIS_M_MonthEnd,0)),_HistIS_M_Labels,$C27)/1000 -> 0 | N27: =SUMIFS(INDEX(_HistIS_M_Data,0,MATCH(N$5,_HistIS_M_MonthEnd,0)),_HistIS_M_Labels,$C27)/1000 -> 0 | O27: =SUMIFS(INDEX(_HistIS_M_Data,0,MATCH(O$5,_HistIS_M_MonthEnd,0)),_HistIS_M_Labels,$C27)/1000 -> 0 | ... AE27: =SUMIFS(INDEX(_HistIS_M_Data,0,MATCH(AE$5,_HistIS_M_MonthEnd,0)),_HistIS_M_Labels,$C27)/1000 -> 0
C28: IT Services | D28: $000 | E28: I/S | F28: =SUM(H28:AE28) -> 45.23653 | H28: =SUMIFS(INDEX(_HistIS_M_Data,0,MATCH(H$5,_HistIS_M_MonthEnd,0)),_HistIS_M_Labels,$C28)/1000 -> 0 | I28: =SUMIFS(INDEX(_HistIS_M_Data,0,MATCH(I$5,_HistIS_M_MonthEnd,0)),_HistIS_M_Labels,$C28)/1000 -> 0 | J28: =SUMIFS(INDEX(_HistIS_M_Data,0,MATCH(J$5,_HistIS_M_MonthEnd,0)),_HistIS_M_Labels,$C28)/1000 -> 0 | K28: =SUMIFS(INDEX(_HistIS_M_Data,0,MATCH(K$5,_HistIS_M_MonthEnd,0)),_HistIS_M_Labels,$C28)/1000 -> 0 | L28: =SUMIFS(INDEX(_HistIS_M_Data,0,MATCH(L$5,_HistIS_M_MonthEnd,0)),_HistIS_M_Labels,$C28)/1000 -> 0 | M28: =SUMIFS(INDEX(_HistIS_M_Data,0,MATCH(M$5,_HistIS_M_MonthEnd,0)),_HistIS_M_Labels,$C28)/1000 -> 0 | N28: =SUMIFS(INDEX(_HistIS_M_Data,0,MATCH(N$5,_HistIS_M_MonthEnd,0)),_HistIS_M_Labels,$C28)/1000 -> 0 | O28: =SUMIFS(INDEX(_HistIS_M_Data,0,MATCH(O$5,_HistIS_M_MonthEnd,0)),_HistIS_M_Labels,$C28)/1000 -> 0 | ... AE28: =SUMIFS(INDEX(_HistIS_M_Data,0,MATCH(AE$5,_HistIS_M_MonthEnd,0)),_HistIS_M_Labels,$C28)/1000 -> 3.906
C29: Other Consultants | D29: $000 | E29: I/S | F29: =SUM(H29:AE29) -> 220.667 | H29: =SUMIFS(INDEX(_HistIS_M_Data,0,MATCH(H$5,_HistIS_M_MonthEnd,0)),_HistIS_M_Labels,$C29)/1000 -> 0 | I29: =SUMIFS(INDEX(_HistIS_M_Data,0,MATCH(I$5,_HistIS_M_MonthEnd,0)),_HistIS_M_Labels,$C29)/1000 -> 0 | J29: =SUMIFS(INDEX(_HistIS_M_Data,0,MATCH(J$5,_HistIS_M_MonthEnd,0)),_HistIS_M_Labels,$C29)/1000 -> 0 | K29: =SUMIFS(INDEX(_HistIS_M_Data,0,MATCH(K$5,_HistIS_M_MonthEnd,0)),_HistIS_M_Labels,$C29)/1000 -> 0 | L29: =SUMIFS(INDEX(_HistIS_M_Data,0,MATCH(L$5,_HistIS_M_MonthEnd,0)),_HistIS_M_Labels,$C29)/1000 -> 0 | M29: =SUMIFS(INDEX(_HistIS_M_Data,0,MATCH(M$5,_HistIS_M_MonthEnd,0)),_HistIS_M_Labels,$C29)/1000 -> 0 | N29: =SUMIFS(INDEX(_HistIS_M_Data,0,MATCH(N$5,_HistIS_M_MonthEnd,0)),_HistIS_M_Labels,$C29)/1000 -> 0 | O29: =SUMIFS(INDEX(_HistIS_M_Data,0,MATCH(O$5,_HistIS_M_MonthEnd,0)),_HistIS_M_Labels,$C29)/1000 -> 0 | ... AE29: =SUMIFS(INDEX(_HistIS_M_Data,0,MATCH(AE$5,_HistIS_M_MonthEnd,0)),_HistIS_M_Labels,$C29)/1000 -> 0
C30: Overhead Services | D30: $000 | F30: =SUM(H30:AE30) -> 1548.9491 | H30: =SUM(H21:H29) -> 34.74296 | I30: =SUM(I21:I29) -> 54.02498 | J30: =SUM(J21:J29) -> 57.2164 | K30: =SUM(K21:K29) -> 132.52631 | L30: =SUM(L21:L29) -> 97.68278 | M30: =SUM(M21:M29) -> 47.58767 | N30: =SUM(N21:N29) -> 51.9655 | O30: =SUM(O21:O29) -> 50.57277 | ... AE30: =SUM(AE21:AE29) -> 19.542
C32: Legal Fees - Corporate | D32: $000 | E32: I/S | F32: =SUM(H32:AE32) -> 453.61444 | H32: =SUMIFS(INDEX(_HistIS_M_Data,0,MATCH(H$5,_HistIS_M_MonthEnd,0)),_HistIS_M_Labels,$C32)/1000 -> 0.3785 | I32: =SUMIFS(INDEX(_HistIS_M_Data,0,MATCH(I$5,_HistIS_M_MonthEnd,0)),_HistIS_M_Labels,$C32)/1000 -> 14.918 | J32: =SUMIFS(INDEX(_HistIS_M_Data,0,MATCH(J$5,_HistIS_M_MonthEnd,0)),_HistIS_M_Labels,$C32)/1000 -> 2.61 | K32: =SUMIFS(INDEX(_HistIS_M_Data,0,MATCH(K$5,_HistIS_M_MonthEnd,0)),_HistIS_M_Labels,$C32)/1000 -> 13.077 | L32: =SUMIFS(INDEX(_HistIS_M_Data,0,MATCH(L$5,_HistIS_M_MonthEnd,0)),_HistIS_M_Labels,$C32)/1000 -> 21.4765 | M32: =SUMIFS(INDEX(_HistIS_M_Data,0,MATCH(M$5,_HistIS_M_MonthEnd,0)),_HistIS_M_Labels,$C32)/1000 -> 6.267 | N32: =SUMIFS(INDEX(_HistIS_M_Data,0,MATCH(N$5,_HistIS_M_MonthEnd,0)),_HistIS_M_Labels,$C32)/1000 -> 3.27045 | O32: =SUMIFS(INDEX(_HistIS_M_Data,0,MATCH(O$5,_HistIS_M_MonthEnd,0)),_HistIS_M_Labels,$C32)/1000 -> 8.297 | ... AE32: =SUMIFS(INDEX(_HistIS_M_Data,0,MATCH(AE$5,_HistIS_M_MonthEnd,0)),_HistIS_M_Labels,$C32)/1000 -> 41.716
C33: Legal Fees - Intellectual Property | D33: $000 | E33: I/S | F33: =SUM(H33:AE33) -> 64.41105 | H33: =SUMIFS(INDEX(_HistIS_M_Data,0,MATCH(H$5,_HistIS_M_MonthEnd,0)),_HistIS_M_Labels,$C33)/1000 -> 0.00013 | I33: =SUMIFS(INDEX(_HistIS_M_Data,0,MATCH(I$5,_HistIS_M_MonthEnd,0)),_HistIS_M_Labels,$C33)/1000 -> 2.275 | J33: =SUMIFS(INDEX(_HistIS_M_Data,0,MATCH(J$5,_HistIS_M_MonthEnd,0)),_HistIS_M_Labels,$C33)/1000 -> 2.17995 | K33: =SUMIFS(INDEX(_HistIS_M_Data,0,MATCH(K$5,_HistIS_M_MonthEnd,0)),_HistIS_M_Labels,$C33)/1000 -> -26.07398 | L33: =SUMIFS(INDEX(_HistIS_M_Data,0,MATCH(L$5,_HistIS_M_MonthEnd,0)),_HistIS_M_Labels,$C33)/1000 -> 40.67618 | M33: =SUMIFS(INDEX(_HistIS_M_Data,0,MATCH(M$5,_HistIS_M_MonthEnd,0)),_HistIS_M_Labels,$C33)/1000 -> 0 | N33: =SUMIFS(INDEX(_HistIS_M_Data,0,MATCH(N$5,_HistIS_M_MonthEnd,0)),_HistIS_M_Labels,$C33)/1000 -> 2.9 | O33: =SUMIFS(INDEX(_HistIS_M_Data,0,MATCH(O$5,_HistIS_M_MonthEnd,0)),_HistIS_M_Labels,$C33)/1000 -> 2.83227 | ... AE33: =SUMIFS(INDEX(_HistIS_M_Data,0,MATCH(AE$5,_HistIS_M_MonthEnd,0)),_HistIS_M_Labels,$C33)/1000 -> 0
C34: Legal Fees - Fundraising | D34: $000 | E34: I/S | F34: =SUM(H34:AE34) -> 108.24385 | H34: =SUMIFS(INDEX(_HistIS_M_Data,0,MATCH(H$5,_HistIS_M_MonthEnd,0)),_HistIS_M_Labels,$C34)/1000 -> 0 | I34: =SUMIFS(INDEX(_HistIS_M_Data,0,MATCH(I$5,_HistIS_M_MonthEnd,0)),_HistIS_M_Labels,$C34)/1000 -> 0 | J34: =SUMIFS(INDEX(_HistIS_M_Data,0,MATCH(J$5,_HistIS_M_MonthEnd,0)),_HistIS_M_Labels,$C34)/1000 -> 0 | K34: =SUMIFS(INDEX(_HistIS_M_Data,0,MATCH(K$5,_HistIS_M_MonthEnd,0)),_HistIS_M_Labels,$C34)/1000 -> 0 | L34: =SUMIFS(INDEX(_HistIS_M_Data,0,MATCH(L$5,_HistIS_M_MonthEnd,0)),_HistIS_M_Labels,$C34)/1000 -> 0 | M34: =SUMIFS(INDEX(_HistIS_M_Data,0,MATCH(M$5,_HistIS_M_MonthEnd,0)),_HistIS_M_Labels,$C34)/1000 -> 0 | N34: =SUMIFS(INDEX(_HistIS_M_Data,0,MATCH(N$5,_HistIS_M_MonthEnd,0)),_HistIS_M_Labels,$C34)/1000 -> 0 | O34: =SUMIFS(INDEX(_HistIS_M_Data,0,MATCH(O$5,_HistIS_M_MonthEnd,0)),_HistIS_M_Labels,$C34)/1000 -> 0 | ... AE34: =SUMIFS(INDEX(_HistIS_M_Data,0,MATCH(AE$5,_HistIS_M_MonthEnd,0)),_HistIS_M_Labels,$C34)/1000 -> 5.122
C35: Total Legal Fees | D35: $000 | F35: =SUM(H35:AE35) -> 626.26934 | H35: =SUM(H32:H34) -> 0.37863 | I35: =SUM(I32:I34) -> 17.193 | J35: =SUM(J32:J34) -> 4.78995 | K35: =SUM(K32:K34) -> -12.99698 | L35: =SUM(L32:L34) -> 62.15268 | M35: =SUM(M32:M34) -> 6.267 | N35: =SUM(N32:N34) -> 6.17045 | O35: =SUM(O32:O34) -> 11.12927 | ... AE35: =SUM(AE32:AE34) -> 46.838
C37: Marketing | D37: $000 | E37: I/S | F37: =SUM(H37:AE37) -> 217.0986 | H37: =SUMIFS(INDEX(_HistIS_M_Data,0,MATCH(H$5,_HistIS_M_MonthEnd,0)),_HistIS_M_Labels,$C37)/1000 -> 0 | I37: =SUMIFS(INDEX(_HistIS_M_Data,0,MATCH(I$5,_HistIS_M_MonthEnd,0)),_HistIS_M_Labels,$C37)/1000 -> 3.84 | J37: =SUMIFS(INDEX(_HistIS_M_Data,0,MATCH(J$5,_HistIS_M_MonthEnd,0)),_HistIS_M_Labels,$C37)/1000 -> 0 | K37: =SUMIFS(INDEX(_HistIS_M_Data,0,MATCH(K$5,_HistIS_M_MonthEnd,0)),_HistIS_M_Labels,$C37)/1000 -> 6.13015 | L37: =SUMIFS(INDEX(_HistIS_M_Data,0,MATCH(L$5,_HistIS_M_MonthEnd,0)),_HistIS_M_Labels,$C37)/1000 -> 0.925 | M37: =SUMIFS(INDEX(_HistIS_M_Data,0,MATCH(M$5,_HistIS_M_MonthEnd,0)),_HistIS_M_Labels,$C37)/1000 -> 1.72456 | N37: =SUMIFS(INDEX(_HistIS_M_Data,0,MATCH(N$5,_HistIS_M_MonthEnd,0)),_HistIS_M_Labels,$C37)/1000 -> 3.125 | O37: =SUMIFS(INDEX(_HistIS_M_Data,0,MATCH(O$5,_HistIS_M_MonthEnd,0)),_HistIS_M_Labels,$C37)/1000 -> 3.006 | ... AE37: =SUMIFS(INDEX(_HistIS_M_Data,0,MATCH(AE$5,_HistIS_M_MonthEnd,0)),_HistIS_M_Labels,$C37)/1000 -> 14.263
C38: Government Affairs | D38: $000 | E38: I/S | F38: =SUM(H38:AE38) -> 648.28291 | H38: =SUMIFS(INDEX(_HistIS_M_Data,0,MATCH(H$5,_HistIS_M_MonthEnd,0)),_HistIS_M_Labels,$C38)/1000 -> 0 | I38: =SUMIFS(INDEX(_HistIS_M_Data,0,MATCH(I$5,_HistIS_M_MonthEnd,0)),_HistIS_M_Labels,$C38)/1000 -> 0 | J38: =SUMIFS(INDEX(_HistIS_M_Data,0,MATCH(J$5,_HistIS_M_MonthEnd,0)),_HistIS_M_Labels,$C38)/1000 -> 0 | K38: =SUMIFS(INDEX(_HistIS_M_Data,0,MATCH(K$5,_HistIS_M_MonthEnd,0)),_HistIS_M_Labels,$C38)/1000 -> 0 | L38: =SUMIFS(INDEX(_HistIS_M_Data,0,MATCH(L$5,_HistIS_M_MonthEnd,0)),_HistIS_M_Labels,$C38)/1000 -> 0 | M38: =SUMIFS(INDEX(_HistIS_M_Data,0,MATCH(M$5,_HistIS_M_MonthEnd,0)),_HistIS_M_Labels,$C38)/1000 -> 0 | N38: =SUMIFS(INDEX(_HistIS_M_Data,0,MATCH(N$5,_HistIS_M_MonthEnd,0)),_HistIS_M_Labels,$C38)/1000 -> 5 | O38: =SUMIFS(INDEX(_HistIS_M_Data,0,MATCH(O$5,_HistIS_M_MonthEnd,0)),_HistIS_M_Labels,$C38)/1000 -> 2.29166 | ... AE38: =SUMIFS(INDEX(_HistIS_M_Data,0,MATCH(AE$5,_HistIS_M_MonthEnd,0)),_HistIS_M_Labels,$C38)/1000 -> 95
C39: T&E | D39: $000 | E39: I/S | F39: =SUM(H39:AE39) -> 680.92805 | H39: =SUMIFS(INDEX(_HistIS_M_Data,0,MATCH(H$5,_HistIS_M_MonthEnd,0)),_HistIS_M_Labels,$C39)/1000 -> 16.10633 | I39: =SUMIFS(INDEX(_HistIS_M_Data,0,MATCH(I$5,_HistIS_M_MonthEnd,0)),_HistIS_M_Labels,$C39)/1000 -> 18.83156 | J39: =SUMIFS(INDEX(_HistIS_M_Data,0,MATCH(J$5,_HistIS_M_MonthEnd,0)),_HistIS_M_Labels,$C39)/1000 -> 26.82209 | K39: =SUMIFS(INDEX(_HistIS_M_Data,0,MATCH(K$5,_HistIS_M_MonthEnd,0)),_HistIS_M_Labels,$C39)/1000 -> 50.23078 | L39: =SUMIFS(INDEX(_HistIS_M_Data,0,MATCH(L$5,_HistIS_M_MonthEnd,0)),_HistIS_M_Labels,$C39)/1000 -> 18.80301 | M39: =SUMIFS(INDEX(_HistIS_M_Data,0,MATCH(M$5,_HistIS_M_MonthEnd,0)),_HistIS_M_Labels,$C39)/1000 -> 14.7223 | N39: =SUMIFS(INDEX(_HistIS_M_Data,0,MATCH(N$5,_HistIS_M_MonthEnd,0)),_HistIS_M_Labels,$C39)/1000 -> 19.04436 | O39: =SUMIFS(INDEX(_HistIS_M_Data,0,MATCH(O$5,_HistIS_M_MonthEnd,0)),_HistIS_M_Labels,$C39)/1000 -> 8.54462 | ... AE39: =SUMIFS(INDEX(_HistIS_M_Data,0,MATCH(AE$5,_HistIS_M_MonthEnd,0)),_HistIS_M_Labels,$C39)/1000 -> 151.724
C40: Insurance | D40: $000 | E40: I/S | F40: =SUM(H40:AE40) -> 306.33645 | H40: =SUMIFS(INDEX(_HistIS_M_Data,0,MATCH(H$5,_HistIS_M_MonthEnd,0)),_HistIS_M_Labels,$C40)/1000 -> 2.8927 | I40: =SUMIFS(INDEX(_HistIS_M_Data,0,MATCH(I$5,_HistIS_M_MonthEnd,0)),_HistIS_M_Labels,$C40)/1000 -> 2.8927 | J40: =SUMIFS(INDEX(_HistIS_M_Data,0,MATCH(J$5,_HistIS_M_MonthEnd,0)),_HistIS_M_Labels,$C40)/1000 -> 2.96306 | K40: =SUMIFS(INDEX(_HistIS_M_Data,0,MATCH(K$5,_HistIS_M_MonthEnd,0)),_HistIS_M_Labels,$C40)/1000 -> 2.8927 | L40: =SUMIFS(INDEX(_HistIS_M_Data,0,MATCH(L$5,_HistIS_M_MonthEnd,0)),_HistIS_M_Labels,$C40)/1000 -> 2.8927 | M40: =SUMIFS(INDEX(_HistIS_M_Data,0,MATCH(M$5,_HistIS_M_MonthEnd,0)),_HistIS_M_Labels,$C40)/1000 -> 2.8927 | N40: =SUMIFS(INDEX(_HistIS_M_Data,0,MATCH(N$5,_HistIS_M_MonthEnd,0)),_HistIS_M_Labels,$C40)/1000 -> 2.8927 | O40: =SUMIFS(INDEX(_HistIS_M_Data,0,MATCH(O$5,_HistIS_M_MonthEnd,0)),_HistIS_M_Labels,$C40)/1000 -> 27.09995 | ... AE40: =SUMIFS(INDEX(_HistIS_M_Data,0,MATCH(AE$5,_HistIS_M_MonthEnd,0)),_HistIS_M_Labels,$C40)/1000 -> 16.901
C41: Office | D41: $000 | E41: I/S | F41: =SUM(H41:AE41) -> 491.16447 | H41: =SUMIFS(INDEX(_HistIS_M_Data,0,MATCH(H$5,_HistIS_M_MonthEnd,0)),_HistIS_M_Labels,$C41)/1000 -> 13.53369 | I41: =SUMIFS(INDEX(_HistIS_M_Data,0,MATCH(I$5,_HistIS_M_MonthEnd,0)),_HistIS_M_Labels,$C41)/1000 -> 14.11474 | J41: =SUMIFS(INDEX(_HistIS_M_Data,0,MATCH(J$5,_HistIS_M_MonthEnd,0)),_HistIS_M_Labels,$C41)/1000 -> 22.29183 | K41: =SUMIFS(INDEX(_HistIS_M_Data,0,MATCH(K$5,_HistIS_M_MonthEnd,0)),_HistIS_M_Labels,$C41)/1000 -> 29.25342 | L41: =SUMIFS(INDEX(_HistIS_M_Data,0,MATCH(L$5,_HistIS_M_MonthEnd,0)),_HistIS_M_Labels,$C41)/1000 -> 21.71002 | M41: =SUMIFS(INDEX(_HistIS_M_Data,0,MATCH(M$5,_HistIS_M_MonthEnd,0)),_HistIS_M_Labels,$C41)/1000 -> 17.80264 | N41: =SUMIFS(INDEX(_HistIS_M_Data,0,MATCH(N$5,_HistIS_M_MonthEnd,0)),_HistIS_M_Labels,$C41)/1000 -> 20.09958 | O41: =SUMIFS(INDEX(_HistIS_M_Data,0,MATCH(O$5,_HistIS_M_MonthEnd,0)),_HistIS_M_Labels,$C41)/1000 -> 22.78452 | ... AE41: =SUMIFS(INDEX(_HistIS_M_Data,0,MATCH(AE$5,_HistIS_M_MonthEnd,0)),_HistIS_M_Labels,$C41)/1000 -> 25.085
C42: Purchase/(Sale) of Fixed Assets | D42: $000 | E42: CFS | F42: =SUM(H42:AE42) -> -135.69242 | H42: =-SUMIFS(INDEX(_HistCFS_M_Data,0,MATCH(H$5,_HistCFS_M_MonthEnd,0)),_HistCFS_M_Labels,$C42)/1000 -> -199.523 | I42: =-SUMIFS(INDEX(_HistCFS_M_Data,0,MATCH(I$5,_HistCFS_M_MonthEnd,0)),_HistCFS_M_Labels,$C42)/1000 -> -1 | J42: =-SUMIFS(INDEX(_HistCFS_M_Data,0,MATCH(J$5,_HistCFS_M_MonthEnd,0)),_HistCFS_M_Labels,$C42)/1000 -> 19.06386 | K42: =-SUMIFS(INDEX(_HistCFS_M_Data,0,MATCH(K$5,_HistCFS_M_MonthEnd,0)),_HistCFS_M_Labels,$C42)/1000 -> -4.04002 | L42: =-SUMIFS(INDEX(_HistCFS_M_Data,0,MATCH(L$5,_HistCFS_M_MonthEnd,0)),_HistCFS_M_Labels,$C42)/1000 -> 0 | M42: =-SUMIFS(INDEX(_HistCFS_M_Data,0,MATCH(M$5,_HistCFS_M_MonthEnd,0)),_HistCFS_M_Labels,$C42)/1000 -> 0 | N42: =-SUMIFS(INDEX(_HistCFS_M_Data,0,MATCH(N$5,_HistCFS_M_MonthEnd,0)),_HistCFS_M_Labels,$C42)/1000 -> 0 | O42: =-SUMIFS(INDEX(_HistCFS_M_Data,0,MATCH(O$5,_HistCFS_M_MonthEnd,0)),_HistCFS_M_Labels,$C42)/1000 -> 0 | ... AE42: =-SUMIFS(INDEX(_HistCFS_M_Data,0,MATCH(AE$5,_HistCFS_M_MonthEnd,0)),_HistCFS_M_Labels,$C42)/1000 -> -4.398
C43: Other | D43: $000 | E43: I/S | F43: =SUM(H43:AE43) -> 58.10004 | H43: =SUMIFS(INDEX(_HistIS_M_Data,0,MATCH(H$5,_HistIS_M_MonthEnd,0)),_HistIS_M_Labels,$C43)/1000 -> 0 | I43: =SUMIFS(INDEX(_HistIS_M_Data,0,MATCH(I$5,_HistIS_M_MonthEnd,0)),_HistIS_M_Labels,$C43)/1000 -> 0 | J43: =SUMIFS(INDEX(_HistIS_M_Data,0,MATCH(J$5,_HistIS_M_MonthEnd,0)),_HistIS_M_Labels,$C43)/1000 -> 0 | K43: =SUMIFS(INDEX(_HistIS_M_Data,0,MATCH(K$5,_HistIS_M_MonthEnd,0)),_HistIS_M_Labels,$C43)/1000 -> 0 | L43: =SUMIFS(INDEX(_HistIS_M_Data,0,MATCH(L$5,_HistIS_M_MonthEnd,0)),_HistIS_M_Labels,$C43)/1000 -> 0.5 | M43: =SUMIFS(INDEX(_HistIS_M_Data,0,MATCH(M$5,_HistIS_M_MonthEnd,0)),_HistIS_M_Labels,$C43)/1000 -> 0 | N43: =SUMIFS(INDEX(_HistIS_M_Data,0,MATCH(N$5,_HistIS_M_MonthEnd,0)),_HistIS_M_Labels,$C43)/1000 -> 0 | O43: =SUMIFS(INDEX(_HistIS_M_Data,0,MATCH(O$5,_HistIS_M_MonthEnd,0)),_HistIS_M_Labels,$C43)/1000 -> 0 | ... AE43: =SUMIFS(INDEX(_HistIS_M_Data,0,MATCH(AE$5,_HistIS_M_MonthEnd,0)),_HistIS_M_Labels,$C43)/1000 -> 0
C44: Total Other Expenses | D44: $000 | F44: =SUM(H44:AE44) -> 2266.2181 | H44: =SUM(H37:H43) -> -166.99028 | I44: =SUM(I37:I43) -> 38.679 | J44: =SUM(J37:J43) -> 71.14084 | K44: =SUM(K37:K43) -> 84.46703 | L44: =SUM(L37:L43) -> 44.83073 | M44: =SUM(M37:M43) -> 37.1422 | N44: =SUM(N37:N43) -> 50.16164 | O44: =SUM(O37:O43) -> 63.72675 | ... AE44: =SUM(AE37:AE43) -> 298.575
C46: Total Expenses | D46: $000 | F46: =SUM(H46:AE46) -> 12513.898 | H46: =SUM(H18:H19,H30,H35,H44) -> 149.99281 | I46: =SUM(I18:I19,I30,I35,I44) -> 416.59019 | J46: =SUM(J18:J19,J30,J35,J44) -> 305.27989 | K46: =SUM(K18:K19,K30,K35,K44) -> 354.51782 | L46: =SUM(L18:L19,L30,L35,L44) -> 475.79428 | M46: =SUM(M18:M19,M30,M35,M44) -> 252.02582 | N46: =SUM(N18:N19,N30,N35,N44) -> 337.31456 | O46: =SUM(O18:O19,O30,O35,O44) -> 345.29608 | ... AE46: =SUM(AE18:AE19,AE30,AE35,AE44) -> 901.736
C47: Total Operating Expenses | D47: $000 | F47: =SUM(H47:AE47) -> 12650.196 | H47: =SUMIFS(INDEX(_HistIS_M_Data,0,MATCH(H$5,_HistIS_M_MonthEnd,0)),_HistIS_M_Labels,$C47)/1000 -> 349.51581 | I47: =SUMIFS(INDEX(_HistIS_M_Data,0,MATCH(I$5,_HistIS_M_MonthEnd,0)),_HistIS_M_Labels,$C47)/1000 -> 417.59019 | J47: =SUMIFS(INDEX(_HistIS_M_Data,0,MATCH(J$5,_HistIS_M_MonthEnd,0)),_HistIS_M_Labels,$C47)/1000 -> 286.21603 | K47: =SUMIFS(INDEX(_HistIS_M_Data,0,MATCH(K$5,_HistIS_M_MonthEnd,0)),_HistIS_M_Labels,$C47)/1000 -> 358.55784 | L47: =SUMIFS(INDEX(_HistIS_M_Data,0,MATCH(L$5,_HistIS_M_MonthEnd,0)),_HistIS_M_Labels,$C47)/1000 -> 475.79428 | M47: =SUMIFS(INDEX(_HistIS_M_Data,0,MATCH(M$5,_HistIS_M_MonthEnd,0)),_HistIS_M_Labels,$C47)/1000 -> 252.02582 | N47: =SUMIFS(INDEX(_HistIS_M_Data,0,MATCH(N$5,_HistIS_M_MonthEnd,0)),_HistIS_M_Labels,$C47)/1000 -> 337.31456 | O47: =SUMIFS(INDEX(_HistIS_M_Data,0,MATCH(O$5,_HistIS_M_MonthEnd,0)),_HistIS_M_Labels,$C47)/1000 -> 345.29608 | ... AE47: =SUMIFS(INDEX(_HistIS_M_Data,0,MATCH(AE$5,_HistIS_M_MonthEnd,0)),_HistIS_M_Labels,$C47)/1000 -> 906.714
C49: CHECK | F49: =SUM(H49:AE49) -> -0.605 | H49: =ROUND(H46-H42-H47,5) -> 0 | I49: =ROUND(I46-I42-I47,5) -> 0 | J49: =ROUND(J46-J42-J47,5) -> 0 | K49: =ROUND(K46-K42-K47,5) -> 0 | L49: =ROUND(L46-L42-L47,5) -> 0 | M49: =ROUND(M46-M42-M47,5) -> 0 | N49: =ROUND(N46-N42-N47,5) -> 0 | O49: =ROUND(O46-O42-O47,5) -> 0 | ... AE49: =ROUND(AE46-AE42-AE47,5) -> -0.58
C51: Operating Profit | D51: $000 | F51: =SUM(H51:AE51) -> -12513.898 | H51: =H12-H46 -> -149.99281 | I51: =I12-I46 -> -416.59019 | J51: =J12-J46 -> -305.27989 | K51: =K12-K46 -> -354.51782 | L51: =L12-L46 -> -475.79428 | M51: =M12-M46 -> -252.02582 | N51: =N12-N46 -> -337.31456 | O51: =O12-O46 -> -345.29608 | ... AE51: =AE12-AE46 -> -901.736
B53: R&D
C54: R&D | D54: $000 | E54: I/S | F54: =SUM(H54:AE54) -> 2765.8876 | H54: =SUMIFS(INDEX(_HistIS_M_Data,0,MATCH(H$5,_HistIS_M_MonthEnd,0)),_HistIS_M_Labels,$C54)/1000 -> 127.33802 | I54: =SUMIFS(INDEX(_HistIS_M_Data,0,MATCH(I$5,_HistIS_M_MonthEnd,0)),_HistIS_M_Labels,$C54)/1000 -> 97.82113 | J54: =SUMIFS(INDEX(_HistIS_M_Data,0,MATCH(J$5,_HistIS_M_MonthEnd,0)),_HistIS_M_Labels,$C54)/1000 -> 41.89728 | K54: =SUMIFS(INDEX(_HistIS_M_Data,0,MATCH(K$5,_HistIS_M_MonthEnd,0)),_HistIS_M_Labels,$C54)/1000 -> 133.15424 | L54: =SUMIFS(INDEX(_HistIS_M_Data,0,MATCH(L$5,_HistIS_M_MonthEnd,0)),_HistIS_M_Labels,$C54)/1000 -> 24.1708 | M54: =SUMIFS(INDEX(_HistIS_M_Data,0,MATCH(M$5,_HistIS_M_MonthEnd,0)),_HistIS_M_Labels,$C54)/1000 -> 356.09998 | N54: =SUMIFS(INDEX(_HistIS_M_Data,0,MATCH(N$5,_HistIS_M_MonthEnd,0)),_HistIS_M_Labels,$C54)/1000 -> 166.89554 | O54: =SUMIFS(INDEX(_HistIS_M_Data,0,MATCH(O$5,_HistIS_M_MonthEnd,0)),_HistIS_M_Labels,$C54)/1000 -> 44.4903 | ... AE54: =SUMIFS(INDEX(_HistIS_M_Data,0,MATCH(AE$5,_HistIS_M_MonthEnd,0)),_HistIS_M_Labels,$C54)/1000 -> 197.37
C55: Capitalized R&D | D55: $000 | E55: CFS | F55: =SUM(H55:AE55) -> 829.39949 | H55: =-SUMIFS(INDEX(_HistCFS_M_Data,0,MATCH(H$5,_HistCFS_M_MonthEnd,0)),_HistCFS_M_Labels,$C55)/1000 -> 0 | I55: =-SUMIFS(INDEX(_HistCFS_M_Data,0,MATCH(I$5,_HistCFS_M_MonthEnd,0)),_HistCFS_M_Labels,$C55)/1000 -> 64.40021 | J55: =-SUMIFS(INDEX(_HistCFS_M_Data,0,MATCH(J$5,_HistCFS_M_MonthEnd,0)),_HistCFS_M_Labels,$C55)/1000 -> 25.30614 | K55: =-SUMIFS(INDEX(_HistCFS_M_Data,0,MATCH(K$5,_HistCFS_M_MonthEnd,0)),_HistCFS_M_Labels,$C55)/1000 -> 49.30859 | L55: =-SUMIFS(INDEX(_HistCFS_M_Data,0,MATCH(L$5,_HistCFS_M_MonthEnd,0)),_HistCFS_M_Labels,$C55)/1000 -> 30.16919 | M55: =-SUMIFS(INDEX(_HistCFS_M_Data,0,MATCH(M$5,_HistCFS_M_MonthEnd,0)),_HistCFS_M_Labels,$C55)/1000 -> 0 | N55: =-SUMIFS(INDEX(_HistCFS_M_Data,0,MATCH(N$5,_HistCFS_M_MonthEnd,0)),_HistCFS_M_Labels,$C55)/1000 -> 21.09731 | O55: =-SUMIFS(INDEX(_HistCFS_M_Data,0,MATCH(O$5,_HistCFS_M_MonthEnd,0)),_HistCFS_M_Labels,$C55)/1000 -> 103.31705 | ... AE55: =-SUMIFS(INDEX(_HistCFS_M_Data,0,MATCH(AE$5,_HistCFS_M_MonthEnd,0)),_HistCFS_M_Labels,$C55)/1000 -> 21.34889
C56: Prototype - Brownfield Demo | D56: $000 | E56: I/S | F56: =SUM(H56:AE56) -> 13333.252 | H56: =SUMIFS(INDEX(_HistIS_M_Data,0,MATCH(H$5,_HistIS_M_MonthEnd,0)),_HistIS_M_Labels,$C56)/1000 -> 8.45787 | I56: =SUMIFS(INDEX(_HistIS_M_Data,0,MATCH(I$5,_HistIS_M_MonthEnd,0)),_HistIS_M_Labels,$C56)/1000 -> 16 | J56: =SUMIFS(INDEX(_HistIS_M_Data,0,MATCH(J$5,_HistIS_M_MonthEnd,0)),_HistIS_M_Labels,$C56)/1000 -> 480.66629 | K56: =SUMIFS(INDEX(_HistIS_M_Data,0,MATCH(K$5,_HistIS_M_MonthEnd,0)),_HistIS_M_Labels,$C56)/1000 -> 276.22385 | L56: =SUMIFS(INDEX(_HistIS_M_Data,0,MATCH(L$5,_HistIS_M_MonthEnd,0)),_HistIS_M_Labels,$C56)/1000 -> 62.38033 | M56: =SUMIFS(INDEX(_HistIS_M_Data,0,MATCH(M$5,_HistIS_M_MonthEnd,0)),_HistIS_M_Labels,$C56)/1000 -> 468.6073 | N56: =SUMIFS(INDEX(_HistIS_M_Data,0,MATCH(N$5,_HistIS_M_MonthEnd,0)),_HistIS_M_Labels,$C56)/1000 -> 1198.3943 | O56: =SUMIFS(INDEX(_HistIS_M_Data,0,MATCH(O$5,_HistIS_M_MonthEnd,0)),_HistIS_M_Labels,$C56)/1000 -> 679.38808 | ... AE56: =SUMIFS(INDEX(_HistIS_M_Data,0,MATCH(AE$5,_HistIS_M_MonthEnd,0)),_HistIS_M_Labels,$C56)/1000 -> 0.297
C57: Total R&D | D57: $000 | F57: =SUM(H57:AE57) -> 16928.539 | H57: =SUM(H54:H56) -> 135.79589 | I57: =SUM(I54:I56) -> 178.22134 | J57: =SUM(J54:J56) -> 547.86971 | K57: =SUM(K54:K56) -> 458.68668 | L57: =SUM(L54:L56) -> 116.72032 | M57: =SUM(M54:M56) -> 824.70728 | N57: =SUM(N54:N56) -> 1386.3872 | O57: =SUM(O54:O56) -> 827.19543 | ... AE57: =SUM(AE54:AE56) -> 219.01589
C58: Total R&D Expenses | D58: $000 | F58: =SUM(H58:AE58) -> 16099.14 | H58: =SUMIFS(INDEX(_HistIS_M_Data,0,MATCH(H$5,_HistIS_M_MonthEnd,0)),_HistIS_M_Labels,$C58)/1000 -> 135.79589 | I58: =SUMIFS(INDEX(_HistIS_M_Data,0,MATCH(I$5,_HistIS_M_MonthEnd,0)),_HistIS_M_Labels,$C58)/1000 -> 113.82113 | J58: =SUMIFS(INDEX(_HistIS_M_Data,0,MATCH(J$5,_HistIS_M_MonthEnd,0)),_HistIS_M_Labels,$C58)/1000 -> 522.56357 | K58: =SUMIFS(INDEX(_HistIS_M_Data,0,MATCH(K$5,_HistIS_M_MonthEnd,0)),_HistIS_M_Labels,$C58)/1000 -> 409.37809 | L58: =SUMIFS(INDEX(_HistIS_M_Data,0,MATCH(L$5,_HistIS_M_MonthEnd,0)),_HistIS_M_Labels,$C58)/1000 -> 86.55113 | M58: =SUMIFS(INDEX(_HistIS_M_Data,0,MATCH(M$5,_HistIS_M_MonthEnd,0)),_HistIS_M_Labels,$C58)/1000 -> 824.70728 | N58: =SUMIFS(INDEX(_HistIS_M_Data,0,MATCH(N$5,_HistIS_M_MonthEnd,0)),_HistIS_M_Labels,$C58)/1000 -> 1365.2899 | O58: =SUMIFS(INDEX(_HistIS_M_Data,0,MATCH(O$5,_HistIS_M_MonthEnd,0)),_HistIS_M_Labels,$C58)/1000 -> 723.87838 | ... AE58: =SUMIFS(INDEX(_HistIS_M_Data,0,MATCH(AE$5,_HistIS_M_MonthEnd,0)),_HistIS_M_Labels,$C58)/1000 -> 197.668
C60: CHECK | F60: =SUM(H60:AE60) -> -0.001 | H60: =ROUND(SUM(H54,H56)-H58,5) -> 0 | I60: =ROUND(SUM(I54,I56)-I58,5) -> 0 | J60: =ROUND(SUM(J54,J56)-J58,5) -> 0 | K60: =ROUND(SUM(K54,K56)-K58,5) -> 0 | L60: =ROUND(SUM(L54,L56)-L58,5) -> 0 | M60: =ROUND(SUM(M54,M56)-M58,5) -> 0 | N60: =ROUND(SUM(N54,N56)-N58,5) -> 0 | O60: =ROUND(SUM(O54,O56)-O58,5) -> 0 | ... AE60: =ROUND(SUM(AE54,AE56)-AE58,5) -> -0.001
C62: EBITDA | D62: $000 | F62: =SUM(H62:AE62) -> -29442.437 | H62: =H51-H57 -> -285.7887 | I62: =I51-I57 -> -594.81153 | J62: =J51-J57 -> -853.1496 | K62: =K51-K57 -> -813.2045 | L62: =L51-L57 -> -592.5146 | M62: =M51-M57 -> -1076.7331 | N62: =N51-N57 -> -1723.7017 | O62: =O51-O57 -> -1172.4915 | ... AE62: =AE51-AE57 -> -1120.7519
B64: Project Expenses
C65: Early Stage Project Development (Permitting, Power Delivery)* | D65: $000 | E65: I/S | F65: =SUM(H65:AE65) -> 433.7353 | H65: =SUMIFS(INDEX(_HistIS_M_Data,0,MATCH(H$5,_HistIS_M_MonthEnd,0)),_HistIS_M_Labels,$C65)/1000 -> 0 | I65: =SUMIFS(INDEX(_HistIS_M_Data,0,MATCH(I$5,_HistIS_M_MonthEnd,0)),_HistIS_M_Labels,$C65)/1000 -> 0 | J65: =SUMIFS(INDEX(_HistIS_M_Data,0,MATCH(J$5,_HistIS_M_MonthEnd,0)),_HistIS_M_Labels,$C65)/1000 -> 0 | K65: =SUMIFS(INDEX(_HistIS_M_Data,0,MATCH(K$5,_HistIS_M_MonthEnd,0)),_HistIS_M_Labels,$C65)/1000 -> 0 | L65: =SUMIFS(INDEX(_HistIS_M_Data,0,MATCH(L$5,_HistIS_M_MonthEnd,0)),_HistIS_M_Labels,$C65)/1000 -> 0 | M65: =SUMIFS(INDEX(_HistIS_M_Data,0,MATCH(M$5,_HistIS_M_MonthEnd,0)),_HistIS_M_Labels,$C65)/1000 -> 0 | N65: =SUMIFS(INDEX(_HistIS_M_Data,0,MATCH(N$5,_HistIS_M_MonthEnd,0)),_HistIS_M_Labels,$C65)/1000 -> 0 | O65: =SUMIFS(INDEX(_HistIS_M_Data,0,MATCH(O$5,_HistIS_M_MonthEnd,0)),_HistIS_M_Labels,$C65)/1000 -> 0 | ... AE65: =SUMIFS(INDEX(_HistIS_M_Data,0,MATCH(AE$5,_HistIS_M_MonthEnd,0)),_HistIS_M_Labels,$C65)/1000 -> 36.074
C66: Geophysical Surveys* | D66: $000 | E66: I/S | F66: =SUM(H66:AE66) -> 47.08 | H66: =SUMIFS(INDEX(_HistIS_M_Data,0,MATCH(H$5,_HistIS_M_MonthEnd,0)),_HistIS_M_Labels,$C66)/1000 -> 0 | I66: =SUMIFS(INDEX(_HistIS_M_Data,0,MATCH(I$5,_HistIS_M_MonthEnd,0)),_HistIS_M_Labels,$C66)/1000 -> 0 | J66: =SUMIFS(INDEX(_HistIS_M_Data,0,MATCH(J$5,_HistIS_M_MonthEnd,0)),_HistIS_M_Labels,$C66)/1000 -> 0 | K66: =SUMIFS(INDEX(_HistIS_M_Data,0,MATCH(K$5,_HistIS_M_MonthEnd,0)),_HistIS_M_Labels,$C66)/1000 -> 0 | L66: =SUMIFS(INDEX(_HistIS_M_Data,0,MATCH(L$5,_HistIS_M_MonthEnd,0)),_HistIS_M_Labels,$C66)/1000 -> 0 | M66: =SUMIFS(INDEX(_HistIS_M_Data,0,MATCH(M$5,_HistIS_M_MonthEnd,0)),_HistIS_M_Labels,$C66)/1000 -> 16.626 | N66: =SUMIFS(INDEX(_HistIS_M_Data,0,MATCH(N$5,_HistIS_M_MonthEnd,0)),_HistIS_M_Labels,$C66)/1000 -> 25.042 | O66: =SUMIFS(INDEX(_HistIS_M_Data,0,MATCH(O$5,_HistIS_M_MonthEnd,0)),_HistIS_M_Labels,$C66)/1000 -> 5.412 | ... AE66: =SUMIFS(INDEX(_HistIS_M_Data,0,MATCH(AE$5,_HistIS_M_MonthEnd,0)),_HistIS_M_Labels,$C66)/1000 -> 0
C67: Total Project Expenses | D67: $000 | F67: =SUM(H67:AE67) -> 480.8153 | H67: =SUM(H65:H66) -> 0 | I67: =SUM(I65:I66) -> 0 | J67: =SUM(J65:J66) -> 0 | K67: =SUM(K65:K66) -> 0 | L67: =SUM(L65:L66) -> 0 | M67: =SUM(M65:M66) -> 16.626 | N67: =SUM(N65:N66) -> 25.042 | O67: =SUM(O65:O66) -> 5.412 | ... AE67: =SUM(AE65:AE66) -> 36.074
C68: Project Expenses | D68: $000 | F68: =SUM(H68:AE68) -> 433.7353 | H68: =SUMIFS(INDEX(_HistIS_M_Data,0,MATCH(H$5,_HistIS_M_MonthEnd,0)),_HistIS_M_Labels,$C68)/1000 -> 0 | I68: =SUMIFS(INDEX(_HistIS_M_Data,0,MATCH(I$5,_HistIS_M_MonthEnd,0)),_HistIS_M_Labels,$C68)/1000 -> 0 | J68: =SUMIFS(INDEX(_HistIS_M_Data,0,MATCH(J$5,_HistIS_M_MonthEnd,0)),_HistIS_M_Labels,$C68)/1000 -> 0 | K68: =SUMIFS(INDEX(_HistIS_M_Data,0,MATCH(K$5,_HistIS_M_MonthEnd,0)),_HistIS_M_Labels,$C68)/1000 -> 0 | L68: =SUMIFS(INDEX(_HistIS_M_Data,0,MATCH(L$5,_HistIS_M_MonthEnd,0)),_HistIS_M_Labels,$C68)/1000 -> 0 | M68: =SUMIFS(INDEX(_HistIS_M_Data,0,MATCH(M$5,_HistIS_M_MonthEnd,0)),_HistIS_M_Labels,$C68)/1000 -> 0 | N68: =SUMIFS(INDEX(_HistIS_M_Data,0,MATCH(N$5,_HistIS_M_MonthEnd,0)),_HistIS_M_Labels,$C68)/1000 -> 0 | O68: =SUMIFS(INDEX(_HistIS_M_Data,0,MATCH(O$5,_HistIS_M_MonthEnd,0)),_HistIS_M_Labels,$C68)/1000 -> 0 | ... AE68: =SUMIFS(INDEX(_HistIS_M_Data,0,MATCH(AE$5,_HistIS_M_MonthEnd,0)),_HistIS_M_Labels,$C68)/1000 -> 36.074
C70: CHECK | F70: =SUM(H70:AE70) -> 0 | H70: =ROUND(H65-H68,5) -> 0 | I70: =ROUND(I65-I68,5) -> 0 | J70: =ROUND(J65-J68,5) -> 0 | K70: =ROUND(K65-K68,5) -> 0 | L70: =ROUND(L65-L68,5) -> 0 | M70: =ROUND(M65-M68,5) -> 0 | N70: =ROUND(N65-N68,5) -> 0 | O70: =ROUND(O65-O68,5) -> 0 | ... AE70: =ROUND(AE65-AE68,5) -> 0
C72: EBITDA Less Capex & Devex | D72: $000 | F72: =SUM(H72:AE72) -> -29923.252 | H72: =H62-H67 -> -285.7887 | I72: =I62-I67 -> -594.81153 | J72: =J62-J67 -> -853.1496 | K72: =K62-K67 -> -813.2045 | L72: =L62-L67 -> -592.5146 | M72: =M62-M67 -> -1093.3591 | N72: =N62-N67 -> -1748.7437 | O72: =O62-O67 -> -1177.9035 | ... AE72: =AE62-AE67 -> -1156.8259
A74: Free Cash Flow
B76: Interest Expense
C77: Interest Expense | D77: $000 | E77: I/S | F77: =SUM(H77:AE77) -> 212.35 | H77: =SUMIFS(INDEX(_HistIS_M_Data,0,MATCH(H$5,_HistIS_M_MonthEnd,0)),_HistIS_M_Labels,$C77)/1000 -> 0 | I77: =SUMIFS(INDEX(_HistIS_M_Data,0,MATCH(I$5,_HistIS_M_MonthEnd,0)),_HistIS_M_Labels,$C77)/1000 -> 0 | J77: =SUMIFS(INDEX(_HistIS_M_Data,0,MATCH(J$5,_HistIS_M_MonthEnd,0)),_HistIS_M_Labels,$C77)/1000 -> 0 | K77: =SUMIFS(INDEX(_HistIS_M_Data,0,MATCH(K$5,_HistIS_M_MonthEnd,0)),_HistIS_M_Labels,$C77)/1000 -> 0 | L77: =SUMIFS(INDEX(_HistIS_M_Data,0,MATCH(L$5,_HistIS_M_MonthEnd,0)),_HistIS_M_Labels,$C77)/1000 -> 0 | M77: =SUMIFS(INDEX(_HistIS_M_Data,0,MATCH(M$5,_HistIS_M_MonthEnd,0)),_HistIS_M_Labels,$C77)/1000 -> 0 | N77: =SUMIFS(INDEX(_HistIS_M_Data,0,MATCH(N$5,_HistIS_M_MonthEnd,0)),_HistIS_M_Labels,$C77)/1000 -> 0 | O77: =SUMIFS(INDEX(_HistIS_M_Data,0,MATCH(O$5,_HistIS_M_MonthEnd,0)),_HistIS_M_Labels,$C77)/1000 -> 0 | ... AE77: =SUMIFS(INDEX(_HistIS_M_Data,0,MATCH(AE$5,_HistIS_M_MonthEnd,0)),_HistIS_M_Labels,$C77)/1000 -> 22.807
C78: Interest Income | D78: $000 | E78: I/S | F78: =SUM(H78:AE78) -> 908.94194 | H78: =SUMIFS(INDEX(_HistIS_M_Data,0,MATCH(H$5,_HistIS_M_MonthEnd,0)),_HistIS_M_Labels,$C78)/1000 -> 34.96986 | I78: =SUMIFS(INDEX(_HistIS_M_Data,0,MATCH(I$5,_HistIS_M_MonthEnd,0)),_HistIS_M_Labels,$C78)/1000 -> 40.89493 | J78: =SUMIFS(INDEX(_HistIS_M_Data,0,MATCH(J$5,_HistIS_M_MonthEnd,0)),_HistIS_M_Labels,$C78)/1000 -> 54.25143 | K78: =SUMIFS(INDEX(_HistIS_M_Data,0,MATCH(K$5,_HistIS_M_MonthEnd,0)),_HistIS_M_Labels,$C78)/1000 -> 58.66717 | L78: =SUMIFS(INDEX(_HistIS_M_Data,0,MATCH(L$5,_HistIS_M_MonthEnd,0)),_HistIS_M_Labels,$C78)/1000 -> 69.16705 | M78: =SUMIFS(INDEX(_HistIS_M_Data,0,MATCH(M$5,_HistIS_M_MonthEnd,0)),_HistIS_M_Labels,$C78)/1000 -> 70.23309 | N78: =SUMIFS(INDEX(_HistIS_M_Data,0,MATCH(N$5,_HistIS_M_MonthEnd,0)),_HistIS_M_Labels,$C78)/1000 -> 69.25871 | O78: =SUMIFS(INDEX(_HistIS_M_Data,0,MATCH(O$5,_HistIS_M_MonthEnd,0)),_HistIS_M_Labels,$C78)/1000 -> 63.56653 | ... AE78: =SUMIFS(INDEX(_HistIS_M_Data,0,MATCH(AE$5,_HistIS_M_MonthEnd,0)),_HistIS_M_Labels,$C78)/1000 -> 13.684
C79: Total Interest Expense / (Income) | D79: $000 | F79: =SUM(H79:AE79) -> -696.59194 | H79: =H77-H78 -> -34.96986 | I79: =I77-I78 -> -40.89493 | J79: =J77-J78 -> -54.25143 | K79: =K77-K78 -> -58.66717 | L79: =L77-L78 -> -69.16705 | M79: =M77-M78 -> -70.23309 | N79: =N77-N78 -> -69.25871 | O79: =O77-O78 -> -63.56653 | ... AE79: =AE77-AE78 -> 9.123
B81: Taxes
C82: Taxes | D82: $000 | E82: I/S | F82: =SUM(H82:AE82) -> 32.60458 | H82: =SUMIFS(INDEX(_HistIS_M_Data,0,MATCH(H$5,_HistIS_M_MonthEnd,0)),_HistIS_M_Labels,$C82)/1000 -> 0 | I82: =SUMIFS(INDEX(_HistIS_M_Data,0,MATCH(I$5,_HistIS_M_MonthEnd,0)),_HistIS_M_Labels,$C82)/1000 -> 2.86644 | J82: =SUMIFS(INDEX(_HistIS_M_Data,0,MATCH(J$5,_HistIS_M_MonthEnd,0)),_HistIS_M_Labels,$C82)/1000 -> 0 | K82: =SUMIFS(INDEX(_HistIS_M_Data,0,MATCH(K$5,_HistIS_M_MonthEnd,0)),_HistIS_M_Labels,$C82)/1000 -> 0 | L82: =SUMIFS(INDEX(_HistIS_M_Data,0,MATCH(L$5,_HistIS_M_MonthEnd,0)),_HistIS_M_Labels,$C82)/1000 -> 0 | M82: =SUMIFS(INDEX(_HistIS_M_Data,0,MATCH(M$5,_HistIS_M_MonthEnd,0)),_HistIS_M_Labels,$C82)/1000 -> 0 | N82: =SUMIFS(INDEX(_HistIS_M_Data,0,MATCH(N$5,_HistIS_M_MonthEnd,0)),_HistIS_M_Labels,$C82)/1000 -> 0 | O82: =SUMIFS(INDEX(_HistIS_M_Data,0,MATCH(O$5,_HistIS_M_MonthEnd,0)),_HistIS_M_Labels,$C82)/1000 -> 0 | ... AE82: =SUMIFS(INDEX(_HistIS_M_Data,0,MATCH(AE$5,_HistIS_M_MonthEnd,0)),_HistIS_M_Labels,$C82)/1000 -> 13.011
C84: FCF | D84: $000 | F84: =SUM(H84:AE84) -> -29259.265 | H84: =H72-H79-H82 -> -250.81884 | I84: =I72-I79-I82 -> -556.78304 | J84: =J72-J79-J82 -> -798.89817 | K84: =K72-K79-K82 -> -754.53733 | L84: =L72-L79-L82 -> -523.34755 | M84: =M72-M79-M82 -> -1023.126 | N84: =N72-N79-N82 -> -1679.485 | O84: =O72-O79-O82 -> -1114.337 | ... AE84: =AE72-AE79-AE82 -> -1178.9599
A86: Accounts & Funding
B88: Cash Accounts
C89: Starting Balance | D89: $000 | E89: B/S | H89: =G98 -> 3791.304 | I89: =H98 -> 12169.436 | J89: =I98 -> 11289.145 | K89: =J98 -> 16445.416 | L89: =K98 -> 18340.621 | M89: =L98 -> 19141.44 | N89: =M98 -> 18317.375 | O89: =N98 -> 17262.017 | ... AE89: =AD98 -> 6148.9074
C90: Plus: FCF | D90: $000 | F90: =SUM(H90:AE90) -> -29259.265 | H90: =H84 -> -250.81884 | I90: =I84 -> -556.78304 | J90: =J84 -> -798.89817 | K90: =K84 -> -754.53733 | L90: =L84 -> -523.34755 | M90: =M84 -> -1023.126 | N90: =N84 -> -1679.485 | O90: =O84 -> -1114.337 | ... AE90: =AE84 -> -1178.9599
C91: Plus: Accrual to Cash Adjustment | D91: $000 | F91: =SUM(H91:AE91) -> -6096.9479 | H91: =H104 -> -1241.0834 | I91: =I104 -> -229.1525 | J91: =J104 -> -148.50089 | K91: =K104 -> 463.41823 | L91: =L104 -> -253.19128 | M91: =M104 -> 215.97138 | N91: =N104 -> 132.50682 | O91: =O104 -> -208.43045 | ... AE91: =AE104 -> -33.81792
C92: Plus: Reconcile D&A | D92: $000 | F92: =SUM(H92:AE92) -> -187.08037 | H92: =H109 -> -0.76517 | I92: =I109 -> -0.59094 | J92: =J109 -> -0.59094 | K92: =K109 -> -2.21818 | L92: =L109 -> -0.59094 | M92: =M109 -> -0.59094 | N92: =N109 -> -0.59094 | O92: =O109 -> -2.31426 | ... AE92: =AE109 -> -6.57734
C93: Minus: Financing Expenses | D93: $000 | F93: =SUM(H93:AE93) -> -313.64941 | H93: =-H124 -> -129.18615 | I93: =-I124 -> -93.7645 | J93: =-J124 -> -5.73615 | K93: =-K124 -> -11.4525 | L93: =-L124 -> -12.04785 | M93: =-M124 -> -16.3188 | N93: =-N124 -> -7.7888 | O93: =-O124 -> -1.6353 | ... AE93: =-AE124 -> 1.19064
C94: Plus: Equity Injections | D94: $000 | F94: =SUM(H94:AE94) -> 33717.499 | H94: =H114 -> 9999.9852 | I94: =I114 -> 0 | J94: =J114 -> 6109.9979 | K94: =K114 -> 2599.9942 | L94: =L114 -> 1589.9963 | M94: =M114 -> 0 | N94: =N114 -> 500 | O94: =O114 -> 0 | ... AE94: =AE114 -> 0
C95: Plus: Debt Drawdown / (Repayment) | D95: $000 | F95: =SUM(H95:AE95) -> 3750 | H95: =H128 -> 0 | I95: =I128 -> 0 | J95: =J128 -> 0 | K95: =K128 -> 0 | L95: =L128 -> 0 | M95: =M128 -> 0 | N95: =N128 -> 0 | O95: =O128 -> 0 | ... AE95: =AE128 -> -125
C96: Minus: Investment in Subsidiaries | D96: $000 | F96: =SUM(H96:AE96) -> -400 | H96: =H119 -> 0 | I96: =I119 -> 0 | J96: =J119 -> 0 | K96: =K119 -> -400 | L96: =L119 -> 0 | M96: =M119 -> 0 | N96: =N119 -> 0 | O96: =O119 -> 0 | ... AE96: =AE119 -> 0
C97: Minus: Cash Balance Reconciliation | D97: $000 | F97: =SUM(H97:AE97) -> -227.354 | H97: =H105 -> 0 | I97: =I105 -> 0 | J97: =J105 -> 0 | K97: =K105 -> 0 | L97: =L105 -> 0 | M97: =M105 -> 0 | N97: =N105 -> 0 | O97: =O105 -> 0 | ... AE97: =AE105 -> -31.237
C98: Ending Balance | D98: $000 | E98: =3791304/1000 -> 3791.304 | G98: =E98 -> 3791.304 | H98: =SUM(H89:H97) -> 12169.436 | I98: =SUM(I89:I97) -> 11289.145 | J98: =SUM(J89:J97) -> 16445.416 | K98: =SUM(K89:K97) -> 18340.621 | L98: =SUM(L89:L97) -> 19141.44 | M98: =SUM(M89:M97) -> 18317.375 | N98: =SUM(N89:N97) -> 17262.017 | O98: =SUM(O89:O97) -> 15935.3 | ... AE98: =SUM(AE89:AE97) -> 4774.5058
C99: Cash Check | E99: B/S | H99: 12169.436 | I99: 11289.145 | J99: 16445.417 | K99: 18340.621 | L99: 19141.44 | M99: 18317.376 | N99: 17262.018 | O99: 15935.301 | P99: 14750.147 | Q99: 12293.711 | R99: 10264.786 | S99: 8841.3917 | T99: 7958.2174 | U99: 14459.919 | V99: 13080.819 | W99: 12825.14 | X99: 13380.308 | Y99: 12151.546 | Z99: 11120.557 | AA99: 9534.9185 | AB99: 8208.624 | AC99: 6858.4349 | AD99: 6148.9072 | AE99: 4774.5058
C101: CHECK | F101: =SUM(H101:AE101) -> 0 | H101: =ROUND(H98-H99,3) -> 0 | I101: =ROUND(I98-I99,3) -> 0 | J101: =ROUND(J98-J99,3) -> 0 | K101: =ROUND(K98-K99,3) -> 0 | L101: =ROUND(L98-L99,3) -> 0 | M101: =ROUND(M98-M99,3) -> 0 | N101: =ROUND(N98-N99,3) -> 0 | O101: =ROUND(O98-O99,3) -> 0 | ... AE101: =ROUND(AE98-AE99,3) -> 0
B103: Changes to Working Capital
C104: Accrual to Cash Adjustment | D104: $000 | E104: CFS | F104: =SUM(H104:AE104) -> -6096.9479 | H104: =SUMIFS(INDEX(_HistCFS_M_Data,0,MATCH(H$5,_HistCFS_M_MonthEnd,0)),_HistCFS_M_Labels,$C104)/1000 -> -1241.0834 | I104: =SUMIFS(INDEX(_HistCFS_M_Data,0,MATCH(I$5,_HistCFS_M_MonthEnd,0)),_HistCFS_M_Labels,$C104)/1000 -> -229.1525 | J104: =SUMIFS(INDEX(_HistCFS_M_Data,0,MATCH(J$5,_HistCFS_M_MonthEnd,0)),_HistCFS_M_Labels,$C104)/1000 -> -148.50089 | K104: =SUMIFS(INDEX(_HistCFS_M_Data,0,MATCH(K$5,_HistCFS_M_MonthEnd,0)),_HistCFS_M_Labels,$C104)/1000 -> 463.41823 | L104: =SUMIFS(INDEX(_HistCFS_M_Data,0,MATCH(L$5,_HistCFS_M_MonthEnd,0)),_HistCFS_M_Labels,$C104)/1000 -> -253.19128 | M104: =SUMIFS(INDEX(_HistCFS_M_Data,0,MATCH(M$5,_HistCFS_M_MonthEnd,0)),_HistCFS_M_Labels,$C104)/1000 -> 215.97138 | N104: =SUMIFS(INDEX(_HistCFS_M_Data,0,MATCH(N$5,_HistCFS_M_MonthEnd,0)),_HistCFS_M_Labels,$C104)/1000 -> 132.50682 | O104: =SUMIFS(INDEX(_HistCFS_M_Data,0,MATCH(O$5,_HistCFS_M_MonthEnd,0)),_HistCFS_M_Labels,$C104)/1000 -> -208.43045 | ... AE104: =SUMIFS(INDEX(_HistCFS_M_Data,0,MATCH(AE$5,_HistCFS_M_MonthEnd,0)),_HistCFS_M_Labels,$C104)/1000 -> -33.81792
C105: Cash Balance Reconciliation | D105: $000 | F105: =SUM(H105:AE105) -> -227.354 | H105: 0 | I105: 0 | J105: 0 | K105: 0 | L105: 0 | M105: 0 | N105: 0 | O105: 0 | P105: 0 | Q105: 0 | R105: 0 | S105: 0 | T105: 0 | U105: 0 | V105: 0 | W105: -0.001 | X105: 0.002 | Y105: 0.003 | Z105: 0.003 | AA105: -45.752 | AB105: -123.276 | AC105: -21.476 | AD105: -5.62 | AE105: -31.237
C107: D&A | D107: $000 | E107: I/S | F107: =SUM(H107:AE107) -> 193.05955 | H107: =SUMIFS(INDEX(_HistIS_M_Data,0,MATCH(H$5,_HistIS_M_MonthEnd,0)),_HistIS_M_Labels,$C107)/1000 -> 0.80347 | I107: =SUMIFS(INDEX(_HistIS_M_Data,0,MATCH(I$5,_HistIS_M_MonthEnd,0)),_HistIS_M_Labels,$C107)/1000 -> 0.62924 | J107: =SUMIFS(INDEX(_HistIS_M_Data,0,MATCH(J$5,_HistIS_M_MonthEnd,0)),_HistIS_M_Labels,$C107)/1000 -> 0.69004 | K107: =SUMIFS(INDEX(_HistIS_M_Data,0,MATCH(K$5,_HistIS_M_MonthEnd,0)),_HistIS_M_Labels,$C107)/1000 -> 0.69572 | L107: =SUMIFS(INDEX(_HistIS_M_Data,0,MATCH(L$5,_HistIS_M_MonthEnd,0)),_HistIS_M_Labels,$C107)/1000 -> 0.7133 | M107: =SUMIFS(INDEX(_HistIS_M_Data,0,MATCH(M$5,_HistIS_M_MonthEnd,0)),_HistIS_M_Labels,$C107)/1000 -> 0.70451 | N107: =SUMIFS(INDEX(_HistIS_M_Data,0,MATCH(N$5,_HistIS_M_MonthEnd,0)),_HistIS_M_Labels,$C107)/1000 -> 0.70451 | O107: =SUMIFS(INDEX(_HistIS_M_Data,0,MATCH(O$5,_HistIS_M_MonthEnd,0)),_HistIS_M_Labels,$C107)/1000 -> 2.42783 | ... AE107: =SUMIFS(INDEX(_HistIS_M_Data,0,MATCH(AE$5,_HistIS_M_MonthEnd,0)),_HistIS_M_Labels,$C107)/1000 -> 7.037
C108: D&A | D108: $000 | E108: CFS | F108: =SUM(H108:AE108) -> 5.97918 | H108: =SUMIFS(INDEX(_HistCFS_M_Data,0,MATCH(H$5,_HistCFS_M_MonthEnd,0)),_HistCFS_M_Labels,$C108)/1000 -> 0.0383 | I108: =SUMIFS(INDEX(_HistCFS_M_Data,0,MATCH(I$5,_HistCFS_M_MonthEnd,0)),_HistCFS_M_Labels,$C108)/1000 -> 0.0383 | J108: =SUMIFS(INDEX(_HistCFS_M_Data,0,MATCH(J$5,_HistCFS_M_MonthEnd,0)),_HistCFS_M_Labels,$C108)/1000 -> 0.0991 | K108: =SUMIFS(INDEX(_HistCFS_M_Data,0,MATCH(K$5,_HistCFS_M_MonthEnd,0)),_HistCFS_M_Labels,$C108)/1000 -> -1.52246 | L108: =SUMIFS(INDEX(_HistCFS_M_Data,0,MATCH(L$5,_HistCFS_M_MonthEnd,0)),_HistCFS_M_Labels,$C108)/1000 -> 0.12236 | M108: =SUMIFS(INDEX(_HistCFS_M_Data,0,MATCH(M$5,_HistCFS_M_MonthEnd,0)),_HistCFS_M_Labels,$C108)/1000 -> 0.11357 | N108: =SUMIFS(INDEX(_HistCFS_M_Data,0,MATCH(N$5,_HistCFS_M_MonthEnd,0)),_HistCFS_M_Labels,$C108)/1000 -> 0.11357 | O108: =SUMIFS(INDEX(_HistCFS_M_Data,0,MATCH(O$5,_HistCFS_M_MonthEnd,0)),_HistCFS_M_Labels,$C108)/1000 -> 0.11357 | ... AE108: =SUMIFS(INDEX(_HistCFS_M_Data,0,MATCH(AE$5,_HistCFS_M_MonthEnd,0)),_HistCFS_M_Labels,$C108)/1000 -> 0.45966
C109: Reconciling D&A Across I/S and CFS | D109: $000 | F109: =SUM(H109:AE109) -> -187.08037 | H109: =H108-H107 -> -0.76517 | I109: =I108-I107 -> -0.59094 | J109: =J108-J107 -> -0.59094 | K109: =K108-K107 -> -2.21818 | L109: =L108-L107 -> -0.59094 | M109: =M108-M107 -> -0.59094 | N109: =N108-N107 -> -0.59094 | O109: =O108-O107 -> -2.31426 | ... AE109: =AE108-AE107 -> -6.57734
B111: Equity
C112: Equity - Series A | D112: $000 | E112: CFS | F112: =SUM(H112:AE112) -> 20799.974 | H112: =SUMIFS(INDEX(_HistCFS_M_Data,0,MATCH(H$5,_HistCFS_M_MonthEnd,0)),_HistCFS_M_Labels,$C112)/1000 -> 9999.9852 | I112: =SUMIFS(INDEX(_HistCFS_M_Data,0,MATCH(I$5,_HistCFS_M_MonthEnd,0)),_HistCFS_M_Labels,$C112)/1000 -> 0 | J112: =SUMIFS(INDEX(_HistCFS_M_Data,0,MATCH(J$5,_HistCFS_M_MonthEnd,0)),_HistCFS_M_Labels,$C112)/1000 -> 6109.9979 | K112: =SUMIFS(INDEX(_HistCFS_M_Data,0,MATCH(K$5,_HistCFS_M_MonthEnd,0)),_HistCFS_M_Labels,$C112)/1000 -> 2599.9942 | L112: =SUMIFS(INDEX(_HistCFS_M_Data,0,MATCH(L$5,_HistCFS_M_MonthEnd,0)),_HistCFS_M_Labels,$C112)/1000 -> 1589.9963 | M112: =SUMIFS(INDEX(_HistCFS_M_Data,0,MATCH(M$5,_HistCFS_M_MonthEnd,0)),_HistCFS_M_Labels,$C112)/1000 -> 0 | N112: =SUMIFS(INDEX(_HistCFS_M_Data,0,MATCH(N$5,_HistCFS_M_MonthEnd,0)),_HistCFS_M_Labels,$C112)/1000 -> 500 | O112: =SUMIFS(INDEX(_HistCFS_M_Data,0,MATCH(O$5,_HistCFS_M_MonthEnd,0)),_HistCFS_M_Labels,$C112)/1000 -> 0 | ... AE112: =SUMIFS(INDEX(_HistCFS_M_Data,0,MATCH(AE$5,_HistCFS_M_MonthEnd,0)),_HistCFS_M_Labels,$C112)/1000 -> 0
C113: Equity - SAFE | D113: $000 | E113: CFS | F113: =SUM(H113:AE113) -> 12917.525 | H113: =SUMIFS(INDEX(_HistCFS_M_Data,0,MATCH(H$5,_HistCFS_M_MonthEnd,0)),_HistCFS_M_Labels,$C113)/1000 -> 0 | I113: =SUMIFS(INDEX(_HistCFS_M_Data,0,MATCH(I$5,_HistCFS_M_MonthEnd,0)),_HistCFS_M_Labels,$C113)/1000 -> 0 | J113: =SUMIFS(INDEX(_HistCFS_M_Data,0,MATCH(J$5,_HistCFS_M_MonthEnd,0)),_HistCFS_M_Labels,$C113)/1000 -> 0 | K113: =SUMIFS(INDEX(_HistCFS_M_Data,0,MATCH(K$5,_HistCFS_M_MonthEnd,0)),_HistCFS_M_Labels,$C113)/1000 -> 0 | L113: =SUMIFS(INDEX(_HistCFS_M_Data,0,MATCH(L$5,_HistCFS_M_MonthEnd,0)),_HistCFS_M_Labels,$C113)/1000 -> 0 | M113: =SUMIFS(INDEX(_HistCFS_M_Data,0,MATCH(M$5,_HistCFS_M_MonthEnd,0)),_HistCFS_M_Labels,$C113)/1000 -> 0 | N113: =SUMIFS(INDEX(_HistCFS_M_Data,0,MATCH(N$5,_HistCFS_M_MonthEnd,0)),_HistCFS_M_Labels,$C113)/1000 -> 0 | O113: =SUMIFS(INDEX(_HistCFS_M_Data,0,MATCH(O$5,_HistCFS_M_MonthEnd,0)),_HistCFS_M_Labels,$C113)/1000 -> 0 | ... AE113: =SUMIFS(INDEX(_HistCFS_M_Data,0,MATCH(AE$5,_HistCFS_M_MonthEnd,0)),_HistCFS_M_Labels,$C113)/1000 -> 0
C114: Total Equity Injection | D114: $000 | F114: =SUM(H114:AE114) -> 33717.499 | H114: =SUM(H112:H113) -> 9999.9852 | I114: =SUM(I112:I113) -> 0 | J114: =SUM(J112:J113) -> 6109.9979 | K114: =SUM(K112:K113) -> 2599.9942 | L114: =SUM(L112:L113) -> 1589.9963 | M114: =SUM(M112:M113) -> 0 | N114: =SUM(N112:N113) -> 500 | O114: =SUM(O112:O113) -> 0 | ... AE114: =SUM(AE112:AE113) -> 0
C116: Investment in Subsidiaries | D116: $000 | E116: CFS | F116: =SUM(H116:AE116) -> 383.988 | H116: =SUMIFS(INDEX(_HistCFS_M_Data,0,MATCH(H$5,_HistCFS_M_MonthEnd,0)),_HistCFS_M_Labels,$C116)/1000 -> 0 | I116: =SUMIFS(INDEX(_HistCFS_M_Data,0,MATCH(I$5,_HistCFS_M_MonthEnd,0)),_HistCFS_M_Labels,$C116)/1000 -> 0 | J116: =SUMIFS(INDEX(_HistCFS_M_Data,0,MATCH(J$5,_HistCFS_M_MonthEnd,0)),_HistCFS_M_Labels,$C116)/1000 -> 0 | K116: =SUMIFS(INDEX(_HistCFS_M_Data,0,MATCH(K$5,_HistCFS_M_MonthEnd,0)),_HistCFS_M_Labels,$C116)/1000 -> -400 | L116: =SUMIFS(INDEX(_HistCFS_M_Data,0,MATCH(L$5,_HistCFS_M_MonthEnd,0)),_HistCFS_M_Labels,$C116)/1000 -> 0 | M116: =SUMIFS(INDEX(_HistCFS_M_Data,0,MATCH(M$5,_HistCFS_M_MonthEnd,0)),_HistCFS_M_Labels,$C116)/1000 -> 0 | N116: =SUMIFS(INDEX(_HistCFS_M_Data,0,MATCH(N$5,_HistCFS_M_MonthEnd,0)),_HistCFS_M_Labels,$C116)/1000 -> 0 | O116: =SUMIFS(INDEX(_HistCFS_M_Data,0,MATCH(O$5,_HistCFS_M_MonthEnd,0)),_HistCFS_M_Labels,$C116)/1000 -> 0 | ... AE116: =SUMIFS(INDEX(_HistCFS_M_Data,0,MATCH(AE$5,_HistCFS_M_MonthEnd,0)),_HistCFS_M_Labels,$C116)/1000 -> 0
C117: Disposal of Investment | D117: $000 | E117: I/S | F117: =SUM(H117:AE117) -> -483.988 | H117: =-SUMIFS(INDEX(_HistIS_M_Data,0,MATCH(H$5,_HistIS_M_MonthEnd,0)),_HistIS_M_Labels,$C117)/1000 -> 0 | I117: =-SUMIFS(INDEX(_HistIS_M_Data,0,MATCH(I$5,_HistIS_M_MonthEnd,0)),_HistIS_M_Labels,$C117)/1000 -> 0 | J117: =-SUMIFS(INDEX(_HistIS_M_Data,0,MATCH(J$5,_HistIS_M_MonthEnd,0)),_HistIS_M_Labels,$C117)/1000 -> 0 | K117: =-SUMIFS(INDEX(_HistIS_M_Data,0,MATCH(K$5,_HistIS_M_MonthEnd,0)),_HistIS_M_Labels,$C117)/1000 -> 0 | L117: =-SUMIFS(INDEX(_HistIS_M_Data,0,MATCH(L$5,_HistIS_M_MonthEnd,0)),_HistIS_M_Labels,$C117)/1000 -> 0 | M117: =-SUMIFS(INDEX(_HistIS_M_Data,0,MATCH(M$5,_HistIS_M_MonthEnd,0)),_HistIS_M_Labels,$C117)/1000 -> 0 | N117: =-SUMIFS(INDEX(_HistIS_M_Data,0,MATCH(N$5,_HistIS_M_MonthEnd,0)),_HistIS_M_Labels,$C117)/1000 -> 0 | O117: =-SUMIFS(INDEX(_HistIS_M_Data,0,MATCH(O$5,_HistIS_M_MonthEnd,0)),_HistIS_M_Labels,$C117)/1000 -> 0 | ... AE117: =-SUMIFS(INDEX(_HistIS_M_Data,0,MATCH(AE$5,_HistIS_M_MonthEnd,0)),_HistIS_M_Labels,$C117)/1000 -> 0
C118: Disposal of Investment | D118: $000 | E118: CFS | F118: =SUM(H118:AE118) -> -300 | H118: =SUMIFS(INDEX(_HistCFS_M_Data,0,MATCH(H$5,_HistCFS_M_MonthEnd,0)),_HistCFS_M_Labels,$C118)/1000 -> 0 | I118: =SUMIFS(INDEX(_HistCFS_M_Data,0,MATCH(I$5,_HistCFS_M_MonthEnd,0)),_HistCFS_M_Labels,$C118)/1000 -> 0 | J118: =SUMIFS(INDEX(_HistCFS_M_Data,0,MATCH(J$5,_HistCFS_M_MonthEnd,0)),_HistCFS_M_Labels,$C118)/1000 -> 0 | K118: =SUMIFS(INDEX(_HistCFS_M_Data,0,MATCH(K$5,_HistCFS_M_MonthEnd,0)),_HistCFS_M_Labels,$C118)/1000 -> 0 | L118: =SUMIFS(INDEX(_HistCFS_M_Data,0,MATCH(L$5,_HistCFS_M_MonthEnd,0)),_HistCFS_M_Labels,$C118)/1000 -> 0 | M118: =SUMIFS(INDEX(_HistCFS_M_Data,0,MATCH(M$5,_HistCFS_M_MonthEnd,0)),_HistCFS_M_Labels,$C118)/1000 -> 0 | N118: =SUMIFS(INDEX(_HistCFS_M_Data,0,MATCH(N$5,_HistCFS_M_MonthEnd,0)),_HistCFS_M_Labels,$C118)/1000 -> 0 | O118: =SUMIFS(INDEX(_HistCFS_M_Data,0,MATCH(O$5,_HistCFS_M_MonthEnd,0)),_HistCFS_M_Labels,$C118)/1000 -> 0 | ... AE118: =SUMIFS(INDEX(_HistCFS_M_Data,0,MATCH(AE$5,_HistCFS_M_MonthEnd,0)),_HistCFS_M_Labels,$C118)/1000 -> 0
C119: Total Investment in Subsidiaries | D119: $000 | F119: =SUM(H119:AE119) -> -400 | H119: =SUM(H116:H118) -> 0 | I119: =SUM(I116:I118) -> 0 | J119: =SUM(J116:J118) -> 0 | K119: =SUM(K116:K118) -> -400 | L119: =SUM(L116:L118) -> 0 | M119: =SUM(M116:M118) -> 0 | N119: =SUM(N116:N118) -> 0 | O119: =SUM(O116:O118) -> 0 | ... AE119: =SUM(AE116:AE118) -> 0
B121: Financing Fees (Admin, Closing Fees)
C122: Series A Financing Fees | D122: $000 | E122: CFS | F122: =SUM(H122:AE122) -> 277.93005 | H122: =-SUMIFS(INDEX(_HistCFS_M_Data,0,MATCH(H$5,_HistCFS_M_MonthEnd,0)),_HistCFS_M_Labels,$C122)/1000 -> 129.18615 | I122: =-SUMIFS(INDEX(_HistCFS_M_Data,0,MATCH(I$5,_HistCFS_M_MonthEnd,0)),_HistCFS_M_Labels,$C122)/1000 -> 93.7645 | J122: =-SUMIFS(INDEX(_HistCFS_M_Data,0,MATCH(J$5,_HistCFS_M_MonthEnd,0)),_HistCFS_M_Labels,$C122)/1000 -> 5.73615 | K122: =-SUMIFS(INDEX(_HistCFS_M_Data,0,MATCH(K$5,_HistCFS_M_MonthEnd,0)),_HistCFS_M_Labels,$C122)/1000 -> 11.4525 | L122: =-SUMIFS(INDEX(_HistCFS_M_Data,0,MATCH(L$5,_HistCFS_M_MonthEnd,0)),_HistCFS_M_Labels,$C122)/1000 -> 12.04785 | M122: =-SUMIFS(INDEX(_HistCFS_M_Data,0,MATCH(M$5,_HistCFS_M_MonthEnd,0)),_HistCFS_M_Labels,$C122)/1000 -> 16.3188 | N122: =-SUMIFS(INDEX(_HistCFS_M_Data,0,MATCH(N$5,_HistCFS_M_MonthEnd,0)),_HistCFS_M_Labels,$C122)/1000 -> 7.7888 | O122: =-SUMIFS(INDEX(_HistCFS_M_Data,0,MATCH(O$5,_HistCFS_M_MonthEnd,0)),_HistCFS_M_Labels,$C122)/1000 -> 1.6353 | ... AE122: =-SUMIFS(INDEX(_HistCFS_M_Data,0,MATCH(AE$5,_HistCFS_M_MonthEnd,0)),_HistCFS_M_Labels,$C122)/1000 -> 0
C123: Debt Financing Fees | D123: $000 | E123: CFS | F123: =SUM(H123:AE123) -> 35.71936 | H123: =-SUMIFS(INDEX(_HistCFS_M_Data,0,MATCH(H$5,_HistCFS_M_MonthEnd,0)),_HistCFS_M_Labels,$C123)/1000 -> 0 | I123: =-SUMIFS(INDEX(_HistCFS_M_Data,0,MATCH(I$5,_HistCFS_M_MonthEnd,0)),_HistCFS_M_Labels,$C123)/1000 -> 0 | J123: =-SUMIFS(INDEX(_HistCFS_M_Data,0,MATCH(J$5,_HistCFS_M_MonthEnd,0)),_HistCFS_M_Labels,$C123)/1000 -> 0 | K123: =-SUMIFS(INDEX(_HistCFS_M_Data,0,MATCH(K$5,_HistCFS_M_MonthEnd,0)),_HistCFS_M_Labels,$C123)/1000 -> 0 | L123: =-SUMIFS(INDEX(_HistCFS_M_Data,0,MATCH(L$5,_HistCFS_M_MonthEnd,0)),_HistCFS_M_Labels,$C123)/1000 -> 0 | M123: =-SUMIFS(INDEX(_HistCFS_M_Data,0,MATCH(M$5,_HistCFS_M_MonthEnd,0)),_HistCFS_M_Labels,$C123)/1000 -> 0 | N123: =-SUMIFS(INDEX(_HistCFS_M_Data,0,MATCH(N$5,_HistCFS_M_MonthEnd,0)),_HistCFS_M_Labels,$C123)/1000 -> 0 | O123: =-SUMIFS(INDEX(_HistCFS_M_Data,0,MATCH(O$5,_HistCFS_M_MonthEnd,0)),_HistCFS_M_Labels,$C123)/1000 -> 0 | ... AE123: =-SUMIFS(INDEX(_HistCFS_M_Data,0,MATCH(AE$5,_HistCFS_M_MonthEnd,0)),_HistCFS_M_Labels,$C123)/1000 -> -1.19064
C124: Total Financing Expenses | D124: $000 | F124: =SUM(H124:AE124) -> 313.64941 | H124: =SUM(H122:H123) -> 129.18615 | I124: =SUM(I122:I123) -> 93.7645 | J124: =SUM(J122:J123) -> 5.73615 | K124: =SUM(K122:K123) -> 11.4525 | L124: =SUM(L122:L123) -> 12.04785 | M124: =SUM(M122:M123) -> 16.3188 | N124: =SUM(N122:N123) -> 7.7888 | O124: =SUM(O122:O123) -> 1.6353 | ... AE124: =SUM(AE122:AE123) -> -1.19064
B126: Venture Debt
C127: Opening Balance | D127: $000 | H127: =G129 -> 0 | I127: =H129 -> 0 | J127: =I129 -> 0 | K127: =J129 -> 0 | L127: =K129 -> 0 | M127: =L129 -> 0 | N127: =M129 -> 0 | O127: =N129 -> 0 | ... AE127: =AD129 -> 3875
C128: Loan Drawdown / (Repayment) | D128: $000 | E128: CFS | F128: =SUM(H128:AE128) -> 3750 | H128: =SUMIFS(INDEX(_HistCFS_M_Data,0,MATCH(H$5,_HistCFS_M_MonthEnd,0)),_HistCFS_M_Labels,$C128)/1000 -> 0 | I128: =SUMIFS(INDEX(_HistCFS_M_Data,0,MATCH(I$5,_HistCFS_M_MonthEnd,0)),_HistCFS_M_Labels,$C128)/1000 -> 0 | J128: =SUMIFS(INDEX(_HistCFS_M_Data,0,MATCH(J$5,_HistCFS_M_MonthEnd,0)),_HistCFS_M_Labels,$C128)/1000 -> 0 | K128: =SUMIFS(INDEX(_HistCFS_M_Data,0,MATCH(K$5,_HistCFS_M_MonthEnd,0)),_HistCFS_M_Labels,$C128)/1000 -> 0 | L128: =SUMIFS(INDEX(_HistCFS_M_Data,0,MATCH(L$5,_HistCFS_M_MonthEnd,0)),_HistCFS_M_Labels,$C128)/1000 -> 0 | M128: =SUMIFS(INDEX(_HistCFS_M_Data,0,MATCH(M$5,_HistCFS_M_MonthEnd,0)),_HistCFS_M_Labels,$C128)/1000 -> 0 | N128: =SUMIFS(INDEX(_HistCFS_M_Data,0,MATCH(N$5,_HistCFS_M_MonthEnd,0)),_HistCFS_M_Labels,$C128)/1000 -> 0 | O128: =SUMIFS(INDEX(_HistCFS_M_Data,0,MATCH(O$5,_HistCFS_M_MonthEnd,0)),_HistCFS_M_Labels,$C128)/1000 -> 0 | ... AE128: =SUMIFS(INDEX(_HistCFS_M_Data,0,MATCH(AE$5,_HistCFS_M_MonthEnd,0)),_HistCFS_M_Labels,$C128)/1000 -> -125
C129: Ending Balance | D129: $000 | G129: 0 | H129: =SUM(H127:H128) -> 0 | I129: =SUM(I127:I128) -> 0 | J129: =SUM(J127:J128) -> 0 | K129: =SUM(K127:K128) -> 0 | L129: =SUM(L127:L128) -> 0 | M129: =SUM(M127:M128) -> 0 | N129: =SUM(N127:N128) -> 0 | O129: =SUM(O127:O128) -> 0 | ... AE129: =SUM(AE127:AE128) -> 3750

Sheet Historical FS Inputs>

Sheet Historical IS
A1: XGS Energy, Inc.
A2: Profit and Loss by Month
A3: January 2024 - December 2025
E4: Monthly | AD4: Quarterly | AM4: Annual
A5: Month End | E5: 45322 | F5: 45351 | G5: 45382 | H5: 45412 | I5: 45443 | J5: 45473 | K5: 45504 | L5: 45535 | M5: 45565 | N5: 45596 | O5: 45626 | P5: 45657 | Q5: 45688 | R5: 45716 | S5: 45747 | T5: 45777 | U5: 45808 | V5: 45838 | W5: 45869 | X5: 45900 | Y5: =EOMONTH(X5,1) -> 45930 | Z5: =EOMONTH(Y5,1) -> 45961 | AA5: =EOMONTH(Z5,1) -> 45991 | AB5: =EOMONTH(AA5,1) -> 46022 | AD5: =$E$6 -> 45382 | AE5: =EOMONTH(AD5,3) -> 45473 | AF5: =EOMONTH(AE5,3) -> 45565 | AG5: =EOMONTH(AF5,3) -> 45657 | AH5: =EOMONTH(AG5,3) -> 45747 | AI5: =EOMONTH(AH5,3) -> 45838 | AJ5: =EOMONTH(AI5,3) -> 45930 | AK5: =EOMONTH(AJ5,3) -> 46022 | AM5: =$E$7 -> 45657 | AN5: =EOMONTH(AM5,12) -> 46022
A6: Quarter End | E6: =DATE(YEAR(E5),ROUNDUP(MONTH(E5)/3,0)*3+1,1)-1 -> 45382 | F6: =DATE(YEAR(F5),ROUNDUP(MONTH(F5)/3,0)*3+1,1)-1 -> 45382 | G6: =DATE(YEAR(G5),ROUNDUP(MONTH(G5)/3,0)*3+1,1)-1 -> 45382 | H6: =DATE(YEAR(H5),ROUNDUP(MONTH(H5)/3,0)*3+1,1)-1 -> 45473 | I6: =DATE(YEAR(I5),ROUNDUP(MONTH(I5)/3,0)*3+1,1)-1 -> 45473 | J6: =DATE(YEAR(J5),ROUNDUP(MONTH(J5)/3,0)*3+1,1)-1 -> 45473 | K6: =DATE(YEAR(K5),ROUNDUP(MONTH(K5)/3,0)*3+1,1)-1 -> 45565 | L6: =DATE(YEAR(L5),ROUNDUP(MONTH(L5)/3,0)*3+1,1)-1 -> 45565 | ... AB6: =DATE(YEAR(AB5),ROUNDUP(MONTH(AB5)/3,0)*3+1,1)-1 -> 46022 | AD6: =DATE(YEAR(AD5),ROUNDUP(MONTH(AD5)/3,0)*3+1,1)-1 -> 45382 | AE6: =DATE(YEAR(AE5),ROUNDUP(MONTH(AE5)/3,0)*3+1,1)-1 -> 45473 | AF6: =DATE(YEAR(AF5),ROUNDUP(MONTH(AF5)/3,0)*3+1,1)-1 -> 45565 | AG6: =DATE(YEAR(AG5),ROUNDUP(MONTH(AG5)/3,0)*3+1,1)-1 -> 45657 | AH6: =DATE(YEAR(AH5),ROUNDUP(MONTH(AH5)/3,0)*3+1,1)-1 -> 45747 | AI6: =DATE(YEAR(AI5),ROUNDUP(MONTH(AI5)/3,0)*3+1,1)-1 -> 45838 | AJ6: =DATE(YEAR(AJ5),ROUNDUP(MONTH(AJ5)/3,0)*3+1,1)-1 -> 45930 | AK6: =DATE(YEAR(AK5),ROUNDUP(MONTH(AK5)/3,0)*3+1,1)-1 -> 46022 | AM6: =DATE(YEAR(AM5),ROUNDUP(MONTH(AM5)/3,0)*3+1,1)-1 -> 45657 | AN6: =DATE(YEAR(AN5),ROUNDUP(MONTH(AN5)/3,0)*3+1,1)-1 -> 46022
A7: Year End | B7: Code Ref | C7: PnL Ref | E7: =DATE(YEAR(E5),12,31) -> 45657 | F7: =DATE(YEAR(F5),12,31) -> 45657 | G7: =DATE(YEAR(G5),12,31) -> 45657 | H7: =DATE(YEAR(H5),12,31) -> 45657 | I7: =DATE(YEAR(I5),12,31) -> 45657 | J7: =DATE(YEAR(J5),12,31) -> 45657 | K7: =DATE(YEAR(K5),12,31) -> 45657 | L7: =DATE(YEAR(L5),12,31) -> 45657 | ... AB7: =DATE(YEAR(AB5),12,31) -> 46022 | AD7: =DATE(YEAR(AD5),12,31) -> 45657 | AE7: =DATE(YEAR(AE5),12,31) -> 45657 | AF7: =DATE(YEAR(AF5),12,31) -> 45657 | AG7: =DATE(YEAR(AG5),12,31) -> 45657 | AH7: =DATE(YEAR(AH5),12,31) -> 46022 | AI7: =DATE(YEAR(AI5),12,31) -> 46022 | AJ7: =DATE(YEAR(AJ5),12,31) -> 46022 | AK7: =DATE(YEAR(AK5),12,31) -> 46022 | AM7: =DATE(YEAR(AM5),12,31) -> 45657 | AN7: =DATE(YEAR(AN5),12,31) -> 46022
A8: Income | C8: Revenue | E8: =0 -> 0 | F8: =0 -> 0 | G8: =0 -> 0 | H8: =0 -> 0 | I8: =0 -> 0 | J8: =0 -> 0 | K8: =0 -> 0 | L8: =0 -> 0 | ... AB8: =0 -> 0 | AD8: =SUMIFS($E8:$AB8,$E$6:$AB$6,AD$5) -> 0 | AE8: =SUMIFS($E8:$AB8,$E$6:$AB$6,AE$5) -> 0 | AF8: =SUMIFS($E8:$AB8,$E$6:$AB$6,AF$5) -> 0 | AG8: =SUMIFS($E8:$AB8,$E$6:$AB$6,AG$5) -> 0 | AH8: =SUMIFS($E8:$AB8,$E$6:$AB$6,AH$5) -> 0 | AI8: =SUMIFS($E8:$AB8,$E$6:$AB$6,AI$5) -> 0 | AJ8: =SUMIFS($E8:$AB8,$E$6:$AB$6,AJ$5) -> 0 | AK8: =SUMIFS($E8:$AB8,$E$6:$AB$6,AK$5) -> 0 | AM8: =SUMIFS($E8:$AB8,$E$7:$AB$7,AM$5) -> 0 | AN8: =SUMIFS($E8:$AB8,$E$7:$AB$7,AN$5) -> 0
A9: Cost of Goods Sold | E9: =0 -> 0 | F9: =0 -> 0 | G9: =0 -> 0 | H9: =0 -> 0 | I9: =0 -> 0 | J9: =0 -> 0 | K9: =0 -> 0 | L9: =0 -> 0 | ... AB9: =0 -> 0 | AD9: =SUMIFS($E9:$AB9,$E$6:$AB$6,AD$5) -> 0 | AE9: =SUMIFS($E9:$AB9,$E$6:$AB$6,AE$5) -> 0 | AF9: =SUMIFS($E9:$AB9,$E$6:$AB$6,AF$5) -> 0 | AG9: =SUMIFS($E9:$AB9,$E$6:$AB$6,AG$5) -> 0 | AH9: =SUMIFS($E9:$AB9,$E$6:$AB$6,AH$5) -> 0 | AI9: =SUMIFS($E9:$AB9,$E$6:$AB$6,AI$5) -> 0 | AJ9: =SUMIFS($E9:$AB9,$E$6:$AB$6,AJ$5) -> 0 | AK9: =SUMIFS($E9:$AB9,$E$6:$AB$6,AK$5) -> 0 | AM9: =SUMIFS($E9:$AB9,$E$7:$AB$7,AM$5) -> 0 | AN9: =SUMIFS($E9:$AB9,$E$7:$AB$7,AN$5) -> 0
A10: Gross Profit | E10: =E8-E9 -> 0 | F10: =F8-F9 -> 0 | G10: =G8-G9 -> 0 | H10: =H8-H9 -> 0 | I10: =I8-I9 -> 0 | J10: =J8-J9 -> 0 | K10: =K8-K9 -> 0 | L10: =L8-L9 -> 0 | ... AB10: =AB8-AB9 -> 0 | AD10: =SUMIFS($E10:$AB10,$E$6:$AB$6,AD$5) -> 0 | AE10: =SUMIFS($E10:$AB10,$E$6:$AB$6,AE$5) -> 0 | AF10: =SUMIFS($E10:$AB10,$E$6:$AB$6,AF$5) -> 0 | AG10: =SUMIFS($E10:$AB10,$E$6:$AB$6,AG$5) -> 0 | AH10: =SUMIFS($E10:$AB10,$E$6:$AB$6,AH$5) -> 0 | AI10: =SUMIFS($E10:$AB10,$E$6:$AB$6,AI$5) -> 0 | AJ10: =SUMIFS($E10:$AB10,$E$6:$AB$6,AJ$5) -> 0 | AK10: =SUMIFS($E10:$AB10,$E$6:$AB$6,AK$5) -> 0 | AM10: =SUMIFS($E10:$AB10,$E$7:$AB$7,AM$5) -> 0 | AN10: =SUMIFS($E10:$AB10,$E$7:$AB$7,AN$5) -> 0
A11: Expenses | AM11: =SUMIFS($E11:$AB11,$E$7:$AB$7,AM$5) -> 0 | AN11: =SUMIFS($E11:$AB11,$E$7:$AB$7,AN$5) -> 0
A12: 6010 PR & Marketing | B12: 6010 | C12: Marketing | E12: =0 -> 0 | F12: =0 -> 0 | G12: =0 -> 0 | H12: =2142.15 -> 2142.15 | I12: =925 -> 925 | J12: =584.56 -> 584.56 | K12: =0 -> 0 | L12: =0 -> 0 | M12: =0 -> 0 | N12: =177.12 -> 177.12 | O12: =4812.54 -> 4812.54 | P12: =0 -> 0 | Q12: =0 -> 0 | R12: 6000 | S12: =0 -> 0 | T12: 0 | U12: 29618 | V12: 29411 | W12: 7724 | X12: 2444 | Y12: 25476 | Z12: 25281 | AA12: 15093 | AB12: 12888 | AD12: =SUMIFS($E12:$AB12,$E$6:$AB$6,AD$5) -> 0 | AE12: =SUMIFS($E12:$AB12,$E$6:$AB$6,AE$5) -> 3651.71 | AF12: =SUMIFS($E12:$AB12,$E$6:$AB$6,AF$5) -> 0 | AG12: =SUMIFS($E12:$AB12,$E$6:$AB$6,AG$5) -> 4989.66 | AH12: =SUMIFS($E12:$AB12,$E$6:$AB$6,AH$5) -> 6000 | AI12: =SUMIFS($E12:$AB12,$E$6:$AB$6,AI$5) -> 59029 | AJ12: =SUMIFS($E12:$AB12,$E$6:$AB$6,AJ$5) -> 35644 | AK12: =SUMIFS($E12:$AB12,$E$6:$AB$6,AK$5) -> 53262 | AM12: =SUMIFS($E12:$AB12,$E$7:$AB$7,AM$5) -> 8641.37 | AN12: =SUMIFS($E12:$AB12,$E$7:$AB$7,AN$5) -> 153935
A13: 6020 Conference Expenses | B13: 6020 | C13: Marketing | E13: =0 -> 0 | F13: =3840 -> 3840 | G13: =0 -> 0 | H13: =3988 -> 3988 | I13: =0 -> 0 | J13: =1140 -> 1140 | K13: =3125 -> 3125 | L13: =3006 -> 3006 | M13: =1367.16 -> 1367.16 | N13: =-136.75 -> -136.75 | O13: =8887.38 -> 8887.38 | P13: =4636.26 -> 4636.26 | Q13: 315 | R13: 7997.27 | S13: 215.91 | T13: 1606 | U13: 411 | V13: 1271 | W13: 3110 | Y13: 5804 | Z13: 2059 | AA13: 505 | AB13: 1375 | AD13: =SUMIFS($E13:$AB13,$E$6:$AB$6,AD$5) -> 3840 | AE13: =SUMIFS($E13:$AB13,$E$6:$AB$6,AE$5) -> 5128 | AF13: =SUMIFS($E13:$AB13,$E$6:$AB$6,AF$5) -> 7498.16 | AG13: =SUMIFS($E13:$AB13,$E$6:$AB$6,AG$5) -> 13386.89 | AH13: =SUMIFS($E13:$AB13,$E$6:$AB$6,AH$5) -> 8528.18 | AI13: =SUMIFS($E13:$AB13,$E$6:$AB$6,AI$5) -> 3288 | AJ13: =SUMIFS($E13:$AB13,$E$6:$AB$6,AJ$5) -> 8914 | AK13: =SUMIFS($E13:$AB13,$E$6:$AB$6,AK$5) -> 3939 | AM13: =SUMIFS($E13:$AB13,$E$7:$AB$7,AM$5) -> 29853.05 | AN13: =SUMIFS($E13:$AB13,$E$7:$AB$7,AN$5) -> 24669.18
A14: 6030 Government Affairs | B14: 6030 | C14: Government Affairs | E14: =0 -> 0 | F14: =0 -> 0 | G14: =0 -> 0 | H14: =0 -> 0 | I14: =0 -> 0 | J14: =0 -> 0 | K14: =5000 -> 5000 | L14: =2291.66 -> 2291.66 | M14: =42016.25 -> 42016.25 | N14: =20000 -> 20000 | O14: =20000 -> 20000 | P14: =25000 -> 25000 | Q14: 20000 | R14: =0 -> 0 | S14: 9975 | T14: 34000 | U14: 70000 | V14: 50000 | W14: 30000 | X14: 50000 | Y14: 50000 | Z14: 75000 | AA14: 50000 | AB14: 95000 | AD14: =SUMIFS($E14:$AB14,$E$6:$AB$6,AD$5) -> 0 | AE14: =SUMIFS($E14:$AB14,$E$6:$AB$6,AE$5) -> 0 | AF14: =SUMIFS($E14:$AB14,$E$6:$AB$6,AF$5) -> 49307.91 | AG14: =SUMIFS($E14:$AB14,$E$6:$AB$6,AG$5) -> 65000 | AH14: =SUMIFS($E14:$AB14,$E$6:$AB$6,AH$5) -> 29975 | AI14: =SUMIFS($E14:$AB14,$E$6:$AB$6,AI$5) -> 154000 | AJ14: =SUMIFS($E14:$AB14,$E$6:$AB$6,AJ$5) -> 130000 | AK14: =SUMIFS($E14:$AB14,$E$6:$AB$6,AK$5) -> 220000 | AM14: =SUMIFS($E14:$AB14,$E$7:$AB$7,AM$5) -> 114307.91 | AN14: =SUMIFS($E14:$AB14,$E$7:$AB$7,AN$5) -> 533975
A15: 6100 Payroll | B15: 6100 | E15: =0 -> 0 | F15: =0 -> 0 | G15: =0 -> 0 | H15: =0 -> 0 | I15: =0 -> 0 | J15: =0 -> 0 | K15: =0 -> 0 | L15: =0 -> 0 | ... S15: =0 -> 0 | T15: 0 | U15: 0 | AD15: =SUMIFS($E15:$AB15,$E$6:$AB$6,AD$5) -> 0 | AE15: =SUMIFS($E15:$AB15,$E$6:$AB$6,AE$5) -> 0 | AF15: =SUMIFS($E15:$AB15,$E$6:$AB$6,AF$5) -> 0 | AG15: =SUMIFS($E15:$AB15,$E$6:$AB$6,AG$5) -> 0 | AH15: =SUMIFS($E15:$AB15,$E$6:$AB$6,AH$5) -> 0 | AI15: =SUMIFS($E15:$AB15,$E$6:$AB$6,AI$5) -> 0 | AJ15: =SUMIFS($E15:$AB15,$E$6:$AB$6,AJ$5) -> 0 | AK15: =SUMIFS($E15:$AB15,$E$6:$AB$6,AK$5) -> 0 | AM15: =SUMIFS($E15:$AB15,$E$7:$AB$7,AM$5) -> 0 | AN15: =SUMIFS($E15:$AB15,$E$7:$AB$7,AN$5) -> 0
A16: 6110 Salaries Expense | B16: 6110 | E16: =114019.76 -> 114019.76 | F16: =132307.76 -> 132307.76 | G16: =132307.76 -> 132307.76 | H16: =138307.77 -> 138307.77 | I16: =219580.91 -> 219580.91 | J16: =149282.78 -> 149282.78 | K16: =160175.06 -> 160175.06 | L16: =170673.17 -> 170673.17 | M16: =201802.94 -> 201802.94 | N16: =193851.4 -> 193851.4 | O16: =190885.81 -> 190885.81 | P16: =342048.79 -> 342048.79 | Q16: 247436.4 | R16: 229092.07 | S16: 230600.36 | T16: 295527 | U16: 344462 | V16: 350068 | W16: 361639 | X16: 376572 | Y16: 413287 | Z16: 428019 | AA16: 434564 | AB16: 442737 | AD16: =SUMIFS($E16:$AB16,$E$6:$AB$6,AD$5) -> 378635.28 | AE16: =SUMIFS($E16:$AB16,$E$6:$AB$6,AE$5) -> 507171.46 | AF16: =SUMIFS($E16:$AB16,$E$6:$AB$6,AF$5) -> 532651.17 | AG16: =SUMIFS($E16:$AB16,$E$6:$AB$6,AG$5) -> 726786 | AH16: =SUMIFS($E16:$AB16,$E$6:$AB$6,AH$5) -> 707128.83 | AI16: =SUMIFS($E16:$AB16,$E$6:$AB$6,AI$5) -> 990057 | AJ16: =SUMIFS($E16:$AB16,$E$6:$AB$6,AJ$5) -> 1151498 | AK16: =SUMIFS($E16:$AB16,$E$6:$AB$6,AK$5) -> 1305320 | AM16: =SUMIFS($E16:$AB16,$E$7:$AB$7,AM$5) -> 2145243.9 | AN16: =SUMIFS($E16:$AB16,$E$7:$AB$7,AN$5) -> 4154003.8
A17: 6120 Payroll Taxes | B17: 6120 | E17: =12379.52 -> 12379.52 | F17: =10778.2 -> 10778.2 | G17: =9379.02 -> 9379.02 | H17: =-12816.11 -> -12816.11 | I17: =17004.84 -> 17004.84 | J17: =-20716.7 -> -20716.7 | K17: =10138.03 -> 10138.03 | L17: =11282.58 -> 11282.58 | M17: =-24361.6 -> -24361.6 | N17: =11106.98 -> 11106.98 | O17: =10889.88 -> 10889.88 | P17: =8204.99 -> 8204.99 | Q17: 21767.05 | R17: 19514.91 | S17: 22261.51 | T17: 24372 | U17: 27874 | V17: 26735 | W17: 27644 | X17: 25770 | Y17: 28395 | Z17: 25939 | AA17: 25621 | AB17: 20368 | AD17: =SUMIFS($E17:$AB17,$E$6:$AB$6,AD$5) -> 32536.74 | AE17: =SUMIFS($E17:$AB17,$E$6:$AB$6,AE$5) -> -16527.97 | AF17: =SUMIFS($E17:$AB17,$E$6:$AB$6,AF$5) -> -2940.99 | AG17: =SUMIFS($E17:$AB17,$E$6:$AB$6,AG$5) -> 30201.85 | AH17: =SUMIFS($E17:$AB17,$E$6:$AB$6,AH$5) -> 63543.47 | AI17: =SUMIFS($E17:$AB17,$E$6:$AB$6,AI$5) -> 78981 | AJ17: =SUMIFS($E17:$AB17,$E$6:$AB$6,AJ$5) -> 81809 | AK17: =SUMIFS($E17:$AB17,$E$6:$AB$6,AK$5) -> 71928 | AM17: =SUMIFS($E17:$AB17,$E$7:$AB$7,AM$5) -> 43269.63 | AN17: =SUMIFS($E17:$AB17,$E$7:$AB$7,AN$5) -> 296261.47
A18: 6130 Employee Benefit Program | B18: 6130 | E18: =15024.37 -> 15024.37 | F18: =150916.18 -> 150916.18 | G18: =17431.31 -> 17431.31 | H18: =17580.31 -> 17580.31 | I18: =24796.97 -> 24796.97 | J18: =21618.88 -> 21618.88 | K18: =21945.47 -> 21945.47 | L18: =22032.7 -> 22032.7 | M18: =23221.44 -> 23221.44 | N18: =22323.23 -> 22323.23 | O18: =5053.68 -> 5053.68 | P18: =1831.56 -> 1831.56 | Q18: =0 -> 0 | R18: 155032.82 | S18: 43348.61 | T18: 17406 | U18: 22738 | V18: 27660 | W18: 31850 | X18: 35450 | Y18: 39107 | Z18: 38553 | AA18: 41203 | AB18: 42159 | AD18: =SUMIFS($E18:$AB18,$E$6:$AB$6,AD$5) -> 183371.86 | AE18: =SUMIFS($E18:$AB18,$E$6:$AB$6,AE$5) -> 63996.16 | AF18: =SUMIFS($E18:$AB18,$E$6:$AB$6,AF$5) -> 67199.61 | AG18: =SUMIFS($E18:$AB18,$E$6:$AB$6,AG$5) -> 29208.47 | AH18: =SUMIFS($E18:$AB18,$E$6:$AB$6,AH$5) -> 198381.43 | AI18: =SUMIFS($E18:$AB18,$E$6:$AB$6,AI$5) -> 67804 | AJ18: =SUMIFS($E18:$AB18,$E$6:$AB$6,AJ$5) -> 106407 | AK18: =SUMIFS($E18:$AB18,$E$6:$AB$6,AK$5) -> 121915 | AM18: =SUMIFS($E18:$AB18,$E$7:$AB$7,AM$5) -> 343776.1 | AN18: =SUMIFS($E18:$AB18,$E$7:$AB$7,AN$5) -> 494507.43
A19: 6160 Severance Expense | B19: 6160 | E19: =125000 -> 125000 | F19: =0 -> 0 | G19: =0 -> 0 | H19: =0 -> 0 | I19: =0 -> 0 | J19: =0 -> 0 | K19: =0 -> 0 | L19: =0 -> 0 | M19: =0 -> 0 | ... R19: =0 -> 0 | S19: 20018 | T19: 0 | U19: 0 | AD19: =SUMIFS($E19:$AB19,$E$6:$AB$6,AD$5) -> 125000 | AE19: =SUMIFS($E19:$AB19,$E$6:$AB$6,AE$5) -> 0 | AF19: =SUMIFS($E19:$AB19,$E$6:$AB$6,AF$5) -> 0 | AG19: =SUMIFS($E19:$AB19,$E$6:$AB$6,AG$5) -> 0 | AH19: =SUMIFS($E19:$AB19,$E$6:$AB$6,AH$5) -> 20018 | AI19: =SUMIFS($E19:$AB19,$E$6:$AB$6,AI$5) -> 0 | AJ19: =SUMIFS($E19:$AB19,$E$6:$AB$6,AJ$5) -> 0 | AK19: =SUMIFS($E19:$AB19,$E$6:$AB$6,AK$5) -> 0 | AM19: =SUMIFS($E19:$AB19,$E$7:$AB$7,AM$5) -> 125000 | AN19: =SUMIFS($E19:$AB19,$E$7:$AB$7,AN$5) -> 20018
A20: 6170 Relocation Exp | B20: 6170 | E20: =0 -> 0 | F20: =0 -> 0 | G20: =0 -> 0 | H20: =0 -> 0 | I20: =0 -> 0 | J20: =0 -> 0 | K20: =25000 -> 25000 | L20: =0 -> 0 | M20: =0 -> 0 | N20: =0 -> 0 | O20: =0 -> 0 | P20: =0 -> 0 | Q20: =0 -> 0 | R20: =0 -> 0 | S20: =0 -> 0 | T20: 0 | U20: 0 | X20: 2953 | AD20: =SUMIFS($E20:$AB20,$E$6:$AB$6,AD$5) -> 0 | AE20: =SUMIFS($E20:$AB20,$E$6:$AB$6,AE$5) -> 0 | AF20: =SUMIFS($E20:$AB20,$E$6:$AB$6,AF$5) -> 25000 | AG20: =SUMIFS($E20:$AB20,$E$6:$AB$6,AG$5) -> 0 | AH20: =SUMIFS($E20:$AB20,$E$6:$AB$6,AH$5) -> 0 | AI20: =SUMIFS($E20:$AB20,$E$6:$AB$6,AI$5) -> 0 | AJ20: =SUMIFS($E20:$AB20,$E$6:$AB$6,AJ$5) -> 2953 | AK20: =SUMIFS($E20:$AB20,$E$6:$AB$6,AK$5) -> 0 | AM20: =SUMIFS($E20:$AB20,$E$7:$AB$7,AM$5) -> 25000 | AN20: =SUMIFS($E20:$AB20,$E$7:$AB$7,AN$5) -> 2953
A21: 6190 ADP Service Charges | B21: 6190 | E21: =946.85 -> 946.85 | F21: =411 -> 411 | G21: =1275.32 -> 1275.32 | H21: =884.37 -> 884.37 | I21: =614.86 -> 614.86 | J21: =1128.32 -> 1128.32 | K21: =445.84 -> 445.84 | L21: =995.17 -> 995.17 | M21: =4884.66 -> 4884.66 | N21: =3193.29 -> 3193.29 | O21: =3142.69 -> 3142.69 | P21: =3148.47 -> 3148.47 | Q21: 3644.8 | R21: 3078.82 | S21: 4194.79 | T21: 4256 | U21: 4795 | V21: 5389 | W21: 5508 | X21: 5588 | Y21: 6278 | Z21: 6736 | AA21: 5992 | AB21: 6449 | AD21: =SUMIFS($E21:$AB21,$E$6:$AB$6,AD$5) -> 2633.17 | AE21: =SUMIFS($E21:$AB21,$E$6:$AB$6,AE$5) -> 2627.55 | AF21: =SUMIFS($E21:$AB21,$E$6:$AB$6,AF$5) -> 6325.67 | AG21: =SUMIFS($E21:$AB21,$E$6:$AB$6,AG$5) -> 9484.45 | AH21: =SUMIFS($E21:$AB21,$E$6:$AB$6,AH$5) -> 10918.41 | AI21: =SUMIFS($E21:$AB21,$E$6:$AB$6,AI$5) -> 14440 | AJ21: =SUMIFS($E21:$AB21,$E$6:$AB$6,AJ$5) -> 17374 | AK21: =SUMIFS($E21:$AB21,$E$6:$AB$6,AK$5) -> 19177 | AM21: =SUMIFS($E21:$AB21,$E$7:$AB$7,AM$5) -> 21070.84 | AN21: =SUMIFS($E21:$AB21,$E$7:$AB$7,AN$5) -> 61909.41
A22: Total for 6100 Payroll | B22: 6100 | C22: Payroll | E22: =SUM(E15:E21) -> 267370.5 | F22: =SUM(F15:F21) -> 294413.14 | G22: =SUM(G15:G21) -> 160393.41 | H22: =SUM(H15:H21) -> 143956.34 | I22: =SUM(I15:I21) -> 261997.58 | J22: =SUM(J15:J21) -> 151313.28 | K22: =SUM(K15:K21) -> 217704.4 | L22: =SUM(L15:L21) -> 204983.62 | ... S22: =SUM(S15:S21) -> 320423.27 | T22: 341561 | U22: 399868 | V22: 409853 | W22: 426641 | X22: 446332 | Y22: 487067 | Z22: 499247 | AA22: 507379 | AB22: 511714 | AD22: =SUMIFS($E22:$AB22,$E$6:$AB$6,AD$5) -> 722177.05 | AE22: =SUMIFS($E22:$AB22,$E$6:$AB$6,AE$5) -> 557267.2 | AF22: =SUMIFS($E22:$AB22,$E$6:$AB$6,AF$5) -> 628235.46 | AG22: =SUMIFS($E22:$AB22,$E$6:$AB$6,AG$5) -> 795680.77 | AH22: =SUMIFS($E22:$AB22,$E$6:$AB$6,AH$5) -> 999990.14 | AI22: =SUMIFS($E22:$AB22,$E$6:$AB$6,AI$5) -> 1151282 | AJ22: =SUMIFS($E22:$AB22,$E$6:$AB$6,AJ$5) -> 1360040 | AK22: =SUMIFS($E22:$AB22,$E$6:$AB$6,AK$5) -> 1518340 | AM22: =SUMIFS($E22:$AB22,$E$7:$AB$7,AM$5) -> 2703360.5 | AN22: =SUMIFS($E22:$AB22,$E$7:$AB$7,AN$5) -> 5029652.1
A23: 6200 Gift Expense | B23: 6200 | C23: Other | E23: =0 -> 0 | F23: =0 -> 0 | G23: =0 -> 0 | H23: =0 -> 0 | I23: =0 -> 0 | J23: =0 -> 0 | K23: =0 -> 0 | L23: =0 -> 0 | ... P23: =0 -> 0 | Q23: 499.78 | R23: 439.96 | S23: =0 -> 0 | T23: 0 | U23: 0 | V23: 0 | W23: 0 | X23: 0 | Y23: 0 | Z23: 0 | AA23: 0 | AB23: 0 | AD23: =SUMIFS($E23:$AB23,$E$6:$AB$6,AD$5) -> 0 | AE23: =SUMIFS($E23:$AB23,$E$6:$AB$6,AE$5) -> 0 | AF23: =SUMIFS($E23:$AB23,$E$6:$AB$6,AF$5) -> 0 | AG23: =SUMIFS($E23:$AB23,$E$6:$AB$6,AG$5) -> 0 | AH23: =SUMIFS($E23:$AB23,$E$6:$AB$6,AH$5) -> 939.74 | AI23: =SUMIFS($E23:$AB23,$E$6:$AB$6,AI$5) -> 0 | AJ23: =SUMIFS($E23:$AB23,$E$6:$AB$6,AJ$5) -> 0 | AK23: =SUMIFS($E23:$AB23,$E$6:$AB$6,AK$5) -> 0 | AM23: =SUMIFS($E23:$AB23,$E$7:$AB$7,AM$5) -> 0 | AN23: =SUMIFS($E23:$AB23,$E$7:$AB$7,AN$5) -> 939.74
A24: 6600 Travel Expense | B24: 6600 | E24: =1616.22 -> 1616.22 | F24: =8780.62 -> 8780.62 | G24: =1727.49 -> 1727.49 | H24: =17634.09 -> 17634.09 | I24: =190.65 -> 190.65 | J24: =2676.92 -> 2676.92 | K24: =1140.02 -> 1140.02 | L24: =2084.44 -> 2084.44 | M24: =1388.79 -> 1388.79 | N24: =4859.2 -> 4859.2 | O24: =4578.7 -> 4578.7 | P24: =2591.51 -> 2591.51 | Q24: =0 -> 0 | R24: =0 -> 0 | S24: =0 -> 0 | T24: 854 | U24: 0 | Z24: -854 | AD24: =SUMIFS($E24:$AB24,$E$6:$AB$6,AD$5) -> 12124.33 | AE24: =SUMIFS($E24:$AB24,$E$6:$AB$6,AE$5) -> 20501.66 | AF24: =SUMIFS($E24:$AB24,$E$6:$AB$6,AF$5) -> 4613.25 | AG24: =SUMIFS($E24:$AB24,$E$6:$AB$6,AG$5) -> 12029.41 | AH24: =SUMIFS($E24:$AB24,$E$6:$AB$6,AH$5) -> 0 | AI24: =SUMIFS($E24:$AB24,$E$6:$AB$6,AI$5) -> 854 | AJ24: =SUMIFS($E24:$AB24,$E$6:$AB$6,AJ$5) -> 0 | AK24: =SUMIFS($E24:$AB24,$E$6:$AB$6,AK$5) -> -854 | AM24: =SUMIFS($E24:$AB24,$E$7:$AB$7,AM$5) -> 49268.65 | AN24: =SUMIFS($E24:$AB24,$E$7:$AB$7,AN$5) -> 0
A25: 6601 Airlines | B25: 6601 | E25: =0 -> 0 | F25: =0 -> 0 | G25: =0 -> 0 | H25: =56.1 -> 56.1 | I25: =0 -> 0 | J25: =0 -> 0 | K25: =0 -> 0 | L25: =0 -> 0 | M25: =0 -> 0 | N25: =34 -> 34 | O25: =0 -> 0 | P25: =0 -> 0 | Q25: 8318.15 | R25: 21053.39 | S25: 492.96 | T25: 2619 | U25: 8317 | V25: 7517 | W25: 3583 | X25: 12682 | Y25: 3538 | Z25: 14879 | AA25: 4652 | AB25: 44817 | AD25: =SUMIFS($E25:$AB25,$E$6:$AB$6,AD$5) -> 0 | AE25: =SUMIFS($E25:$AB25,$E$6:$AB$6,AE$5) -> 56.1 | AF25: =SUMIFS($E25:$AB25,$E$6:$AB$6,AF$5) -> 0 | AG25: =SUMIFS($E25:$AB25,$E$6:$AB$6,AG$5) -> 34 | AH25: =SUMIFS($E25:$AB25,$E$6:$AB$6,AH$5) -> 29864.5 | AI25: =SUMIFS($E25:$AB25,$E$6:$AB$6,AI$5) -> 18453 | AJ25: =SUMIFS($E25:$AB25,$E$6:$AB$6,AJ$5) -> 19803 | AK25: =SUMIFS($E25:$AB25,$E$6:$AB$6,AK$5) -> 64348 | AM25: =SUMIFS($E25:$AB25,$E$7:$AB$7,AM$5) -> 90.1 | AN25: =SUMIFS($E25:$AB25,$E$7:$AB$7,AN$5) -> 132468.5
A26: 6602 Public Transit | E26: 0 | F26: 0 | G26: 0 | H26: 0 | I26: 0 | J26: 0 | K26: 0 | L26: 0 | M26: 0 | N26: 0 | O26: 0 | P26: 0 | Q26: 0 | R26: 0 | S26: 0 | T26: 0 | U26: 0 | Z26: 107 | AA26: 99 | AB26: 276
A27: 6603 Gas - etc | B27: 6603 | E27: =0 -> 0 | F27: =150.46 -> 150.46 | G27: =73.82 -> 73.82 | H27: =539.64 -> 539.64 | I27: =0 -> 0 | J27: =1173.01 -> 1173.01 | K27: =0 -> 0 | L27: =102.53 -> 102.53 | M27: =23.81 -> 23.81 | N27: =0 -> 0 | O27: =58.96 -> 58.96 | P27: =10.85 -> 10.85 | Q27: 75.96 | R27: 303.81 | S27: =0 -> 0 | T27: 193 | U27: 968 | V27: 969 | W27: 85 | X27: 981 | Y27: 921 | Z27: 386 | AA27: 662 | AB27: 892 | AD27: =SUMIFS($E27:$AB27,$E$6:$AB$6,AD$5) -> 224.28 | AE27: =SUMIFS($E27:$AB27,$E$6:$AB$6,AE$5) -> 1712.65 | AF27: =SUMIFS($E27:$AB27,$E$6:$AB$6,AF$5) -> 126.34 | AG27: =SUMIFS($E27:$AB27,$E$6:$AB$6,AG$5) -> 69.81 | AH27: =SUMIFS($E27:$AB27,$E$6:$AB$6,AH$5) -> 379.77 | AI27: =SUMIFS($E27:$AB27,$E$6:$AB$6,AI$5) -> 2130 | AJ27: =SUMIFS($E27:$AB27,$E$6:$AB$6,AJ$5) -> 1987 | AK27: =SUMIFS($E27:$AB27,$E$6:$AB$6,AK$5) -> 1940 | AM27: =SUMIFS($E27:$AB27,$E$7:$AB$7,AM$5) -> 2133.08 | AN27: =SUMIFS($E27:$AB27,$E$7:$AB$7,AN$5) -> 6436.77
A28: 6605 Groceries | B28: 6605 | E28: =766.39 -> 766.39 | F28: =667.5 -> 667.5 | G28: =4629.69 -> 4629.69 | H28: =8031.88 -> 8031.88 | I28: =2044.11 -> 2044.11 | J28: =2986.07 -> 2986.07 | K28: =2081.2 -> 2081.2 | L28: =1731.55 -> 1731.55 | M28: =1095.69 -> 1095.69 | N28: =2159.83 -> 2159.83 | O28: =2976.88 -> 2976.88 | P28: =3037.99 -> 3037.99 | Q28: =0 -> 0 | R28: 308.59 | S28: =0 -> 0 | T28: 0 | U28: 0 | AD28: =SUMIFS($E28:$AB28,$E$6:$AB$6,AD$5) -> 6063.58 | AE28: =SUMIFS($E28:$AB28,$E$6:$AB$6,AE$5) -> 13062.06 | AF28: =SUMIFS($E28:$AB28,$E$6:$AB$6,AF$5) -> 4908.44 | AG28: =SUMIFS($E28:$AB28,$E$6:$AB$6,AG$5) -> 8174.7 | AH28: =SUMIFS($E28:$AB28,$E$6:$AB$6,AH$5) -> 308.59 | AI28: =SUMIFS($E28:$AB28,$E$6:$AB$6,AI$5) -> 0 | AJ28: =SUMIFS($E28:$AB28,$E$6:$AB$6,AJ$5) -> 0 | AK28: =SUMIFS($E28:$AB28,$E$6:$AB$6,AK$5) -> 0 | AM28: =SUMIFS($E28:$AB28,$E$7:$AB$7,AM$5) -> 32208.78 | AN28: =SUMIFS($E28:$AB28,$E$7:$AB$7,AN$5) -> 308.59
A29: 6606 Lodging | B29: 6606 | E29: =0 -> 0 | F29: =46 -> 46 | G29: =0 -> 0 | H29: =12.4 -> 12.4 | I29: =0 -> 0 | J29: =88 -> 88 | K29: =0 -> 0 | L29: =58 -> 58 | M29: =54 -> 54 | N29: =151.74 -> 151.74 | O29: =124 -> 124 | P29: =478.28 -> 478.28 | Q29: 2975.97 | R29: 10161.3 | S29: 340.77 | T29: 375 | U29: 7821 | V29: 5424 | W29: 3260 | X29: 6727 | Y29: 5681 | Z29: 8790 | AA29: 3989 | AB29: 24054 | AD29: =SUMIFS($E29:$AB29,$E$6:$AB$6,AD$5) -> 46 | AE29: =SUMIFS($E29:$AB29,$E$6:$AB$6,AE$5) -> 100.4 | AF29: =SUMIFS($E29:$AB29,$E$6:$AB$6,AF$5) -> 112 | AG29: =SUMIFS($E29:$AB29,$E$6:$AB$6,AG$5) -> 754.02 | AH29: =SUMIFS($E29:$AB29,$E$6:$AB$6,AH$5) -> 13478.04 | AI29: =SUMIFS($E29:$AB29,$E$6:$AB$6,AI$5) -> 13620 | AJ29: =SUMIFS($E29:$AB29,$E$6:$AB$6,AJ$5) -> 15668 | AK29: =SUMIFS($E29:$AB29,$E$6:$AB$6,AK$5) -> 36833 | AM29: =SUMIFS($E29:$AB29,$E$7:$AB$7,AM$5) -> 1012.42 | AN29: =SUMIFS($E29:$AB29,$E$7:$AB$7,AN$5) -> 79599.04
A30: 6607 Parking | B30: 6607 | E30: =123.76 -> 123.76 | F30: =150.32 -> 150.32 | G30: =509.5 -> 509.5 | H30: =678.56 -> 678.56 | I30: =3713.36 -> 3713.36 | J30: =296.85 -> 296.85 | K30: =39.3 -> 39.3 | L30: =135.94 -> 135.94 | M30: =302.02 -> 302.02 | N30: =501.83 -> 501.83 | O30: =288.46 -> 288.46 | P30: =454.72 -> 454.72 | Q30: 16 | R30: 90.3 | S30: 67.58 | T30: 0 | U30: 39 | V30: 399 | W30: 131 | Y30: 145 | Z30: 95 | AA30: 70 | AB30: 294 | AD30: =SUMIFS($E30:$AB30,$E$6:$AB$6,AD$5) -> 783.58 | AE30: =SUMIFS($E30:$AB30,$E$6:$AB$6,AE$5) -> 4688.77 | AF30: =SUMIFS($E30:$AB30,$E$6:$AB$6,AF$5) -> 477.26 | AG30: =SUMIFS($E30:$AB30,$E$6:$AB$6,AG$5) -> 1245.01 | AH30: =SUMIFS($E30:$AB30,$E$6:$AB$6,AH$5) -> 173.88 | AI30: =SUMIFS($E30:$AB30,$E$6:$AB$6,AI$5) -> 438 | AJ30: =SUMIFS($E30:$AB30,$E$6:$AB$6,AJ$5) -> 276 | AK30: =SUMIFS($E30:$AB30,$E$6:$AB$6,AK$5) -> 459 | AM30: =SUMIFS($E30:$AB30,$E$7:$AB$7,AM$5) -> 7194.62 | AN30: =SUMIFS($E30:$AB30,$E$7:$AB$7,AN$5) -> 1346.88
A31: 6608 Meals | B31: 6608 | E31: =3373.01 -> 3373.01 | F31: =834.4 -> 834.4 | G31: =847.1 -> 847.1 | H31: =1722.44 -> 1722.44 | I31: =358.3 -> 358.3 | J31: =1342.49 -> 1342.49 | K31: =52.25 -> 52.25 | L31: =250 -> 250 | M31: =400.84 -> 400.84 | N31: =202.57 -> 202.57 | O31: =71.66 -> 71.66 | P31: =2549.88 -> 2549.88 | Q31: 423.95 | R31: 654.55 | S31: 119.09 | T31: 58 | U31: 1368 | V31: 1310 | W31: 1614 | X31: 607 | Y31: 688 | Z31: 863 | AA31: 366 | AB31: 3193 | AD31: =SUMIFS($E31:$AB31,$E$6:$AB$6,AD$5) -> 5054.51 | AE31: =SUMIFS($E31:$AB31,$E$6:$AB$6,AE$5) -> 3423.23 | AF31: =SUMIFS($E31:$AB31,$E$6:$AB$6,AF$5) -> 703.09 | AG31: =SUMIFS($E31:$AB31,$E$6:$AB$6,AG$5) -> 2824.11 | AH31: =SUMIFS($E31:$AB31,$E$6:$AB$6,AH$5) -> 1197.59 | AI31: =SUMIFS($E31:$AB31,$E$6:$AB$6,AI$5) -> 2736 | AJ31: =SUMIFS($E31:$AB31,$E$6:$AB$6,AJ$5) -> 2909 | AK31: =SUMIFS($E31:$AB31,$E$6:$AB$6,AK$5) -> 4422 | AM31: =SUMIFS($E31:$AB31,$E$7:$AB$7,AM$5) -> 12004.94 | AN31: =SUMIFS($E31:$AB31,$E$7:$AB$7,AN$5) -> 11264.59
A32: 6609 Meals with Team | B32: 6609 | E32: =0 -> 0 | F32: =0 -> 0 | G32: =89.11 -> 89.11 | H32: =362.97 -> 362.97 | I32: =0 -> 0 | J32: =492.64 -> 492.64 | K32: =0 -> 0 | L32: =0 -> 0 | M32: =0 -> 0 | N32: =0 -> 0 | O32: =0 -> 0 | P32: =0 -> 0 | Q32: 386.51 | R32: 3084.91 | S32: 383.27 | T32: 89 | U32: 277 | V32: 891 | W32: 5024 | X32: 1400 | Z32: 1883 | AA32: 337 | AB32: 2452 | AD32: =SUMIFS($E32:$AB32,$E$6:$AB$6,AD$5) -> 89.11 | AE32: =SUMIFS($E32:$AB32,$E$6:$AB$6,AE$5) -> 855.61 | AF32: =SUMIFS($E32:$AB32,$E$6:$AB$6,AF$5) -> 0 | AG32: =SUMIFS($E32:$AB32,$E$6:$AB$6,AG$5) -> 0 | AH32: =SUMIFS($E32:$AB32,$E$6:$AB$6,AH$5) -> 3854.69 | AI32: =SUMIFS($E32:$AB32,$E$6:$AB$6,AI$5) -> 1257 | AJ32: =SUMIFS($E32:$AB32,$E$6:$AB$6,AJ$5) -> 6424 | AK32: =SUMIFS($E32:$AB32,$E$6:$AB$6,AK$5) -> 4672 | AM32: =SUMIFS($E32:$AB32,$E$7:$AB$7,AM$5) -> 944.72 | AN32: =SUMIFS($E32:$AB32,$E$7:$AB$7,AN$5) -> 16207.69
A33: 6610 Meals with Client | B33: 6610 | E33: =0 -> 0 | F33: =118.21 -> 118.21 | G33: =297.12 -> 297.12 | H33: =745.96 -> 745.96 | I33: =0 -> 0 | J33: =0 -> 0 | K33: =0 -> 0 | L33: =486.76 -> 486.76 | M33: =647.22 -> 647.22 | N33: =1264.57 -> 1264.57 | O33: =601.23 -> 601.23 | P33: =622.22 -> 622.22 | Q33: 476.01 | R33: 902.26 | S33: =0 -> 0 | T33: 0 | U33: 249 | Y33: 199 | Z33: 57 | AA33: 15 | AB33: 8478 | AD33: =SUMIFS($E33:$AB33,$E$6:$AB$6,AD$5) -> 415.33 | AE33: =SUMIFS($E33:$AB33,$E$6:$AB$6,AE$5) -> 745.96 | AF33: =SUMIFS($E33:$AB33,$E$6:$AB$6,AF$5) -> 1133.98 | AG33: =SUMIFS($E33:$AB33,$E$6:$AB$6,AG$5) -> 2488.02 | AH33: =SUMIFS($E33:$AB33,$E$6:$AB$6,AH$5) -> 1378.27 | AI33: =SUMIFS($E33:$AB33,$E$6:$AB$6,AI$5) -> 249 | AJ33: =SUMIFS($E33:$AB33,$E$6:$AB$6,AJ$5) -> 199 | AK33: =SUMIFS($E33:$AB33,$E$6:$AB$6,AK$5) -> 8550 | AM33: =SUMIFS($E33:$AB33,$E$7:$AB$7,AM$5) -> 4783.29 | AN33: =SUMIFS($E33:$AB33,$E$7:$AB$7,AN$5) -> 10376.27
A34: 6611 Rental Car | B34: 6611 | E34: =0 -> 0 | F34: =0 -> 0 | G34: =204.91 -> 204.91 | H34: =0 -> 0 | I34: =0 -> 0 | J34: =0 -> 0 | K34: =0 -> 0 | L34: =0 -> 0 | M34: =0 -> 0 | N34: =0 -> 0 | O34: =0 -> 0 | ... Q34: =0 -> 0 | R34: 506.44 | S34: 128.36 | T34: 0 | U34: 1816 | V34: 1426 | X34: 242 | Y34: 1071 | Z34: 335 | AA34: 628 | AB34: 1327 | AD34: =SUMIFS($E34:$AB34,$E$6:$AB$6,AD$5) -> 204.91 | AE34: =SUMIFS($E34:$AB34,$E$6:$AB$6,AE$5) -> 0 | AF34: =SUMIFS($E34:$AB34,$E$6:$AB$6,AF$5) -> 0 | AG34: =SUMIFS($E34:$AB34,$E$6:$AB$6,AG$5) -> 0 | AH34: =SUMIFS($E34:$AB34,$E$6:$AB$6,AH$5) -> 634.8 | AI34: =SUMIFS($E34:$AB34,$E$6:$AB$6,AI$5) -> 3242 | AJ34: =SUMIFS($E34:$AB34,$E$6:$AB$6,AJ$5) -> 1313 | AK34: =SUMIFS($E34:$AB34,$E$6:$AB$6,AK$5) -> 2290 | AM34: =SUMIFS($E34:$AB34,$E$7:$AB$7,AM$5) -> 204.91 | AN34: =SUMIFS($E34:$AB34,$E$7:$AB$7,AN$5) -> 7479.8
A35: 6612 Services/Conference Room Rental | E35: 0 | F35: 0 | G35: 0 | H35: 0 | I35: 0 | J35: 0 | K35: 0 | L35: 0 | M35: 0 | N35: 0 | O35: 0 | P35: 0 | Q35: 0 | R35: 0 | S35: 0 | T35: 0 | U35: 0 | Z35: 1234 | AB35: 105
A36: 6613 Taxi/Shared Ride Apps | B36: 6613 | E36: =0 -> 0 | F36: =496.42 -> 496.42 | G36: =1219.15 -> 1219.15 | H36: =6589.89 -> 6589.89 | I36: =425.6 -> 425.6 | J36: =1175.62 -> 1175.62 | K36: =624.18 -> 624.18 | L36: =349.24 -> 349.24 | M36: =411.22 -> 411.22 | N36: =1000.07 -> 1000.07 | O36: =542.6 -> 542.6 | P36: =1327.22 -> 1327.22 | Q36: 2849.71 | R36: 4471.77 | S36: =0 -> 0 | T36: 650 | U36: 2131 | V36: 1500 | W36: 1912 | X36: 676 | Y36: 841 | AA36: 578 | AB36: 13698 | AD36: =SUMIFS($E36:$AB36,$E$6:$AB$6,AD$5) -> 1715.57 | AE36: =SUMIFS($E36:$AB36,$E$6:$AB$6,AE$5) -> 8191.11 | AF36: =SUMIFS($E36:$AB36,$E$6:$AB$6,AF$5) -> 1384.64 | AG36: =SUMIFS($E36:$AB36,$E$6:$AB$6,AG$5) -> 2869.89 | AH36: =SUMIFS($E36:$AB36,$E$6:$AB$6,AH$5) -> 7321.48 | AI36: =SUMIFS($E36:$AB36,$E$6:$AB$6,AI$5) -> 4281 | AJ36: =SUMIFS($E36:$AB36,$E$6:$AB$6,AJ$5) -> 3429 | AK36: =SUMIFS($E36:$AB36,$E$6:$AB$6,AK$5) -> 14276 | AM36: =SUMIFS($E36:$AB36,$E$7:$AB$7,AM$5) -> 14161.21 | AN36: =SUMIFS($E36:$AB36,$E$7:$AB$7,AN$5) -> 29307.48
A37: 6614 Other | B37: 6614 | E37: =0 -> 0 | F37: =0 -> 0 | G37: =0 -> 0 | H37: =1220 -> 1220 | I37: =0 -> 0 | J37: =0 -> 0 | K37: =0 -> 0 | L37: =0 -> 0 | M37: =0 -> 0 | N37: =0 -> 0 | O37: =0 -> 0 | P37: =0 -> 0 | Q37: =0 -> 0 | R37: 837.12 | S37: =0 -> 0 | T37: 186 | U37: 16 | V37: 85 | Y37: 37 | AB37: 36607 | AD37: =SUMIFS($E37:$AB37,$E$6:$AB$6,AD$5) -> 0 | AE37: =SUMIFS($E37:$AB37,$E$6:$AB$6,AE$5) -> 1220 | AF37: =SUMIFS($E37:$AB37,$E$6:$AB$6,AF$5) -> 0 | AG37: =SUMIFS($E37:$AB37,$E$6:$AB$6,AG$5) -> 0 | AH37: =SUMIFS($E37:$AB37,$E$6:$AB$6,AH$5) -> 837.12 | AI37: =SUMIFS($E37:$AB37,$E$6:$AB$6,AI$5) -> 287 | AJ37: =SUMIFS($E37:$AB37,$E$6:$AB$6,AJ$5) -> 37 | AK37: =SUMIFS($E37:$AB37,$E$6:$AB$6,AK$5) -> 36607 | AM37: =SUMIFS($E37:$AB37,$E$7:$AB$7,AM$5) -> 1220 | AN37: =SUMIFS($E37:$AB37,$E$7:$AB$7,AN$5) -> 37768.12
A38: Total for 6600 Travel Expense | B38: 6600 | C38: T&E | E38: =SUM(E24:E37) -> 5879.38 | F38: =SUM(F24:F37) -> 11243.93 | G38: =SUM(G24:G37) -> 9597.89 | H38: =SUM(H24:H37) -> 37593.93 | I38: =SUM(I24:I37) -> 6732.02 | J38: =SUM(J24:J37) -> 10231.6 | K38: =SUM(K24:K37) -> 3936.95 | L38: =SUM(L24:L37) -> 5198.46 | ... S38: =SUM(S24:S37) -> 1532.03 | T38: 5024 | U38: 23002 | V38: 19522 | W38: 15609 | X38: 23316 | Y38: 13120 | Z38: 27776 | AA38: 11479 | AB38: 136723 | AD38: =SUMIFS($E38:$AB38,$E$6:$AB$6,AD$5) -> 26721.2 | AE38: =SUMIFS($E38:$AB38,$E$6:$AB$6,AE$5) -> 54557.55 | AF38: =SUMIFS($E38:$AB38,$E$6:$AB$6,AF$5) -> 13459 | AG38: =SUMIFS($E38:$AB38,$E$6:$AB$6,AG$5) -> 30488.97 | AH38: =SUMIFS($E38:$AB38,$E$6:$AB$6,AH$5) -> 59428.73 | AI38: =SUMIFS($E38:$AB38,$E$6:$AB$6,AI$5) -> 47548 | AJ38: =SUMIFS($E38:$AB38,$E$6:$AB$6,AJ$5) -> 52045 | AK38: =SUMIFS($E38:$AB38,$E$6:$AB$6,AK$5) -> 175978 | AM38: =SUMIFS($E38:$AB38,$E$7:$AB$7,AM$5) -> 125226.72 | AN38: =SUMIFS($E38:$AB38,$E$7:$AB$7,AN$5) -> 334999.73
A39: 6650 Board Meeting Travel Expense | B39: 6650 | E39: =0 -> 0 | F39: =0 -> 0 | G39: =0 -> 0 | H39: =0 -> 0 | I39: =0 -> 0 | J39: =0 -> 0 | K39: =0 -> 0 | L39: =0 -> 0 | ... S39: =0 -> 0 | T39: 0 | U39: 0 | AD39: =SUMIFS($E39:$AB39,$E$6:$AB$6,AD$5) -> 0 | AE39: =SUMIFS($E39:$AB39,$E$6:$AB$6,AE$5) -> 0 | AF39: =SUMIFS($E39:$AB39,$E$6:$AB$6,AF$5) -> 0 | AG39: =SUMIFS($E39:$AB39,$E$6:$AB$6,AG$5) -> 0 | AH39: =SUMIFS($E39:$AB39,$E$6:$AB$6,AH$5) -> 0 | AI39: =SUMIFS($E39:$AB39,$E$6:$AB$6,AI$5) -> 0 | AJ39: =SUMIFS($E39:$AB39,$E$6:$AB$6,AJ$5) -> 0 | AK39: =SUMIFS($E39:$AB39,$E$6:$AB$6,AK$5) -> 0 | AM39: =SUMIFS($E39:$AB39,$E$7:$AB$7,AM$5) -> 0 | AN39: =SUMIFS($E39:$AB39,$E$7:$AB$7,AN$5) -> 0
A40: 6651 Board Meeting Airlines | B40: 6651 | E40: =2300.98 -> 2300.98 | F40: =4921.1 -> 4921.1 | G40: =2716.03 -> 2716.03 | H40: =6493.51 -> 6493.51 | I40: =3298.54 -> 3298.54 | J40: =0 -> 0 | K40: =5035.5 -> 5035.5 | L40: =768.06 -> 768.06 | M40: =1768.32 -> 1768.32 | N40: =992.98 -> 992.98 | O40: =2356.38 -> 2356.38 | P40: =0 -> 0 | Q40: 9791.57 | R40: 3027.05 | S40: 1006.99 | T40: 1555 | U40: 7190 | V40: 5568 | W40: 4409 | Y40: 6515 | Z40: 7857 | AA40: 5431 | AB40: 8263 | AD40: =SUMIFS($E40:$AB40,$E$6:$AB$6,AD$5) -> 9938.11 | AE40: =SUMIFS($E40:$AB40,$E$6:$AB$6,AE$5) -> 9792.05 | AF40: =SUMIFS($E40:$AB40,$E$6:$AB$6,AF$5) -> 7571.88 | AG40: =SUMIFS($E40:$AB40,$E$6:$AB$6,AG$5) -> 3349.36 | AH40: =SUMIFS($E40:$AB40,$E$6:$AB$6,AH$5) -> 13825.61 | AI40: =SUMIFS($E40:$AB40,$E$6:$AB$6,AI$5) -> 14313 | AJ40: =SUMIFS($E40:$AB40,$E$6:$AB$6,AJ$5) -> 10924 | AK40: =SUMIFS($E40:$AB40,$E$6:$AB$6,AK$5) -> 21551 | AM40: =SUMIFS($E40:$AB40,$E$7:$AB$7,AM$5) -> 30651.4 | AN40: =SUMIFS($E40:$AB40,$E$7:$AB$7,AN$5) -> 60613.61
A41: 6652 Board Meeting Gas - etc | B41: 6652 | E41: =25.28 -> 25.28 | F41: =0 -> 0 | G41: =0 -> 0 | H41: =0 -> 0 | I41: =107.87 -> 107.87 | J41: =0 -> 0 | K41: =55.89 -> 55.89 | L41: =107.87 -> 107.87 | M41: =0 -> 0 | N41: =0 -> 0 | O41: =0 -> 0 | P41: =0 -> 0 | Q41: 107.87 | R41: =0 -> 0 | S41: =0 -> 0 | T41: 60 | U41: 0 | AD41: =SUMIFS($E41:$AB41,$E$6:$AB$6,AD$5) -> 25.28 | AE41: =SUMIFS($E41:$AB41,$E$6:$AB$6,AE$5) -> 107.87 | AF41: =SUMIFS($E41:$AB41,$E$6:$AB$6,AF$5) -> 163.76 | AG41: =SUMIFS($E41:$AB41,$E$6:$AB$6,AG$5) -> 0 | AH41: =SUMIFS($E41:$AB41,$E$6:$AB$6,AH$5) -> 107.87 | AI41: =SUMIFS($E41:$AB41,$E$6:$AB$6,AI$5) -> 60 | AJ41: =SUMIFS($E41:$AB41,$E$6:$AB$6,AJ$5) -> 0 | AK41: =SUMIFS($E41:$AB41,$E$6:$AB$6,AK$5) -> 0 | AM41: =SUMIFS($E41:$AB41,$E$7:$AB$7,AM$5) -> 296.91 | AN41: =SUMIFS($E41:$AB41,$E$7:$AB$7,AN$5) -> 167.87
A42: 6653 Board Meeting Lodging | B42: 6653 | E42: =5784.16 -> 5784.16 | F42: =230.34 -> 230.34 | G42: =8877.79 -> 8877.79 | H42: =1375.93 -> 1375.93 | I42: =2830 -> 2830 | J42: =259.72 -> 259.72 | K42: =3751.14 -> 3751.14 | L42: =1187.02 -> 1187.02 | M42: =4079.03 -> 4079.03 | N42: =326.97 -> 326.97 | O42: =428.96 -> 428.96 | P42: =200 -> 200 | Q42: =0 -> 0 | R42: =0 -> 0 | S42: =0 -> 0 | T42: 445 | U42: 445 | V42: 2530 | W42: 2812 | Y42: 2785 | Z42: 1273 | AA42: 1305 | AB42: 3041 | AD42: =SUMIFS($E42:$AB42,$E$6:$AB$6,AD$5) -> 14892.29 | AE42: =SUMIFS($E42:$AB42,$E$6:$AB$6,AE$5) -> 4465.65 | AF42: =SUMIFS($E42:$AB42,$E$6:$AB$6,AF$5) -> 9017.19 | AG42: =SUMIFS($E42:$AB42,$E$6:$AB$6,AG$5) -> 955.93 | AH42: =SUMIFS($E42:$AB42,$E$6:$AB$6,AH$5) -> 0 | AI42: =SUMIFS($E42:$AB42,$E$6:$AB$6,AI$5) -> 3420 | AJ42: =SUMIFS($E42:$AB42,$E$6:$AB$6,AJ$5) -> 5597 | AK42: =SUMIFS($E42:$AB42,$E$6:$AB$6,AK$5) -> 5619 | AM42: =SUMIFS($E42:$AB42,$E$7:$AB$7,AM$5) -> 29331.06 | AN42: =SUMIFS($E42:$AB42,$E$7:$AB$7,AN$5) -> 14636
A43: 6654 Board Meeting Parking | B43: 6654 | E43: =236 -> 236 | F43: =66 -> 66 | G43: =72 -> 72 | H43: =0 -> 0 | I43: =158 -> 158 | J43: =0 -> 0 | K43: =29.69 -> 29.69 | L43: =0 -> 0 | M43: =76 -> 76 | N43: =0 -> 0 | O43: =20 -> 20 | P43: =0 -> 0 | Q43: 4298.47 | R43: 648.5 | S43: =0 -> 0 | T43: 0 | U43: 0 | Z43: 152 | AD43: =SUMIFS($E43:$AB43,$E$6:$AB$6,AD$5) -> 374 | AE43: =SUMIFS($E43:$AB43,$E$6:$AB$6,AE$5) -> 158 | AF43: =SUMIFS($E43:$AB43,$E$6:$AB$6,AF$5) -> 105.69 | AG43: =SUMIFS($E43:$AB43,$E$6:$AB$6,AG$5) -> 20 | AH43: =SUMIFS($E43:$AB43,$E$6:$AB$6,AH$5) -> 4946.97 | AI43: =SUMIFS($E43:$AB43,$E$6:$AB$6,AI$5) -> 0 | AJ43: =SUMIFS($E43:$AB43,$E$6:$AB$6,AJ$5) -> 0 | AK43: =SUMIFS($E43:$AB43,$E$6:$AB$6,AK$5) -> 152 | AM43: =SUMIFS($E43:$AB43,$E$7:$AB$7,AM$5) -> 657.69 | AN43: =SUMIFS($E43:$AB43,$E$7:$AB$7,AN$5) -> 5098.97
A44: 6655 Board Meeting Meals-50% | B44: 6655 | E44: =-1285.68 -> -1285.68 | F44: =0 -> 0 | G44: =0 -> 0 | H44: =0 -> 0 | I44: =207.55 -> 207.55 | J44: =0 -> 0 | K44: =388.64 -> 388.64 | L44: =0 -> 0 | M44: =0 -> 0 | N44: =0 -> 0 | O44: =139.08 -> 139.08 | P44: =0 -> 0 | Q44: 106.05 | R44: 604.45 | S44: 102.49 | T44: 0 | U44: 0 | V44: 127 | Z44: 22 | AA44: 43 | AB44: 1443 | AD44: =SUMIFS($E44:$AB44,$E$6:$AB$6,AD$5) -> -1285.68 | AE44: =SUMIFS($E44:$AB44,$E$6:$AB$6,AE$5) -> 207.55 | AF44: =SUMIFS($E44:$AB44,$E$6:$AB$6,AF$5) -> 388.64 | AG44: =SUMIFS($E44:$AB44,$E$6:$AB$6,AG$5) -> 139.08 | AH44: =SUMIFS($E44:$AB44,$E$6:$AB$6,AH$5) -> 812.99 | AI44: =SUMIFS($E44:$AB44,$E$6:$AB$6,AI$5) -> 127 | AJ44: =SUMIFS($E44:$AB44,$E$6:$AB$6,AJ$5) -> 0 | AK44: =SUMIFS($E44:$AB44,$E$6:$AB$6,AK$5) -> 1508 | AM44: =SUMIFS($E44:$AB44,$E$7:$AB$7,AM$5) -> -550.41 | AN44: =SUMIFS($E44:$AB44,$E$7:$AB$7,AN$5) -> 2447.99
A45: 6656 Board Meeting Meals-100% | B45: 6656 | E45: =51.55 -> 51.55 | F45: =565.11 -> 565.11 | G45: =4987.55 -> 4987.55 | H45: =0 -> 0 | I45: =2194.29 -> 2194.29 | J45: =0 -> 0 | K45: =454.27 -> 454.27 | L45: =900 -> 900 | M45: =1688.25 -> 1688.25 | N45: =0 -> 0 | O45: =2207.19 -> 2207.19 | P45: =0 -> 0 | Q45: 545.06 | R45: 302.45 | S45: =0 -> 0 | T45: 202 | U45: 2204 | V45: 1287 | X45: 1251 | Y45: 621 | Z45: 350 | AA45: 3882 | AB45: 496 | AD45: =SUMIFS($E45:$AB45,$E$6:$AB$6,AD$5) -> 5604.21 | AE45: =SUMIFS($E45:$AB45,$E$6:$AB$6,AE$5) -> 2194.29 | AF45: =SUMIFS($E45:$AB45,$E$6:$AB$6,AF$5) -> 3042.52 | AG45: =SUMIFS($E45:$AB45,$E$6:$AB$6,AG$5) -> 2207.19 | AH45: =SUMIFS($E45:$AB45,$E$6:$AB$6,AH$5) -> 847.51 | AI45: =SUMIFS($E45:$AB45,$E$6:$AB$6,AI$5) -> 3693 | AJ45: =SUMIFS($E45:$AB45,$E$6:$AB$6,AJ$5) -> 1872 | AK45: =SUMIFS($E45:$AB45,$E$6:$AB$6,AK$5) -> 4728 | AM45: =SUMIFS($E45:$AB45,$E$7:$AB$7,AM$5) -> 13048.21 | AN45: =SUMIFS($E45:$AB45,$E$7:$AB$7,AN$5) -> 11140.51
A46: 6657 Board Meeting Rental Car | B46: 6657 | E46: =232.51 -> 232.51 | F46: =0 -> 0 | G46: =0 -> 0 | H46: =0 -> 0 | I46: =523.93 -> 523.93 | J46: =0 -> 0 | K46: =0 -> 0 | L46: =308.36 -> 308.36 | M46: =0 -> 0 | N46: =0 -> 0 | O46: =0 -> 0 | P46: =0 -> 0 | Q46: 131.09 | R46: =0 -> 0 | S46: =0 -> 0 | T46: 0 | U46: 344 | AD46: =SUMIFS($E46:$AB46,$E$6:$AB$6,AD$5) -> 232.51 | AE46: =SUMIFS($E46:$AB46,$E$6:$AB$6,AE$5) -> 523.93 | AF46: =SUMIFS($E46:$AB46,$E$6:$AB$6,AF$5) -> 308.36 | AG46: =SUMIFS($E46:$AB46,$E$6:$AB$6,AG$5) -> 0 | AH46: =SUMIFS($E46:$AB46,$E$6:$AB$6,AH$5) -> 131.09 | AI46: =SUMIFS($E46:$AB46,$E$6:$AB$6,AI$5) -> 344 | AJ46: =SUMIFS($E46:$AB46,$E$6:$AB$6,AJ$5) -> 0 | AK46: =SUMIFS($E46:$AB46,$E$6:$AB$6,AK$5) -> 0 | AM46: =SUMIFS($E46:$AB46,$E$7:$AB$7,AM$5) -> 1064.8 | AN46: =SUMIFS($E46:$AB46,$E$7:$AB$7,AN$5) -> 475.09
A47: 6658 Board Meeting Taxi/Shared Ride | B47: 6658 | E47: =1206.52 -> 1206.52 | F47: =177.31 -> 177.31 | G47: =550.06 -> 550.06 | H47: =769.95 -> 769.95 | I47: =520.02 -> 520.02 | J47: =45.98 -> 45.98 | K47: =1055.57 -> 1055.57 | L47: =74.85 -> 74.85 | M47: =612.82 -> 612.82 | N47: =395.65 -> 395.65 | O47: =384.83 -> 384.83 | P47: =32.98 -> 32.98 | Q47: 1025.24 | R47: 1160.44 | S47: =0 -> 0 | T47: 163 | U47: 56 | V47: 1592 | W47: 223 | Y47: 475 | Z47: 523 | AA47: 221 | AB47: 1757 | AD47: =SUMIFS($E47:$AB47,$E$6:$AB$6,AD$5) -> 1933.89 | AE47: =SUMIFS($E47:$AB47,$E$6:$AB$6,AE$5) -> 1335.95 | AF47: =SUMIFS($E47:$AB47,$E$6:$AB$6,AF$5) -> 1743.24 | AG47: =SUMIFS($E47:$AB47,$E$6:$AB$6,AG$5) -> 813.46 | AH47: =SUMIFS($E47:$AB47,$E$6:$AB$6,AH$5) -> 2185.68 | AI47: =SUMIFS($E47:$AB47,$E$6:$AB$6,AI$5) -> 1811 | AJ47: =SUMIFS($E47:$AB47,$E$6:$AB$6,AJ$5) -> 698 | AK47: =SUMIFS($E47:$AB47,$E$6:$AB$6,AK$5) -> 2501 | AM47: =SUMIFS($E47:$AB47,$E$7:$AB$7,AM$5) -> 5826.54 | AN47: =SUMIFS($E47:$AB47,$E$7:$AB$7,AN$5) -> 7195.68
A48: 6659 Board Meeting Services/Conference | B48: 6659 | E48: =1675.63 -> 1675.63 | F48: =1627.77 -> 1627.77 | G48: =0 -> 0 | H48: =3997.46 -> 3997.46 | I48: =2230.79 -> 2230.79 | J48: =4185 -> 4185 | K48: =4336.71 -> 4336.71 | L48: =0 -> 0 | M48: =0 -> 0 | N48: =0 -> 0 | O48: =0 -> 0 | P48: =0 -> 0 | Q48: =0 -> 0 | R48: =0 -> 0 | S48: 2500 | T48: 15640 | U48: 0 | V48: 2131 | AD48: =SUMIFS($E48:$AB48,$E$6:$AB$6,AD$5) -> 3303.4 | AE48: =SUMIFS($E48:$AB48,$E$6:$AB$6,AE$5) -> 10413.25 | AF48: =SUMIFS($E48:$AB48,$E$6:$AB$6,AF$5) -> 4336.71 | AG48: =SUMIFS($E48:$AB48,$E$6:$AB$6,AG$5) -> 0 | AH48: =SUMIFS($E48:$AB48,$E$6:$AB$6,AH$5) -> 2500 | AI48: =SUMIFS($E48:$AB48,$E$6:$AB$6,AI$5) -> 17771 | AJ48: =SUMIFS($E48:$AB48,$E$6:$AB$6,AJ$5) -> 0 | AK48: =SUMIFS($E48:$AB48,$E$6:$AB$6,AK$5) -> 0 | AM48: =SUMIFS($E48:$AB48,$E$7:$AB$7,AM$5) -> 18053.36 | AN48: =SUMIFS($E48:$AB48,$E$7:$AB$7,AN$5) -> 20271
A49: 6660 Board Meeting Others | B49: 6660 | E49: =0 -> 0 | F49: =0 -> 0 | G49: =20.77 -> 20.77 | H49: =0 -> 0 | I49: =0 -> 0 | J49: =0 -> 0 | K49: =0 -> 0 | L49: =0 -> 0 | M49: =0 -> 0 | N49: =0 -> 0 | O49: =0 -> 0 | ... R49: =0 -> 0 | S49: 222.55 | T49: 30 | U49: 0 | AD49: =SUMIFS($E49:$AB49,$E$6:$AB$6,AD$5) -> 20.77 | AE49: =SUMIFS($E49:$AB49,$E$6:$AB$6,AE$5) -> 0 | AF49: =SUMIFS($E49:$AB49,$E$6:$AB$6,AF$5) -> 0 | AG49: =SUMIFS($E49:$AB49,$E$6:$AB$6,AG$5) -> 0 | AH49: =SUMIFS($E49:$AB49,$E$6:$AB$6,AH$5) -> 222.55 | AI49: =SUMIFS($E49:$AB49,$E$6:$AB$6,AI$5) -> 30 | AJ49: =SUMIFS($E49:$AB49,$E$6:$AB$6,AJ$5) -> 0 | AK49: =SUMIFS($E49:$AB49,$E$6:$AB$6,AK$5) -> 0 | AM49: =SUMIFS($E49:$AB49,$E$7:$AB$7,AM$5) -> 20.77 | AN49: =SUMIFS($E49:$AB49,$E$7:$AB$7,AN$5) -> 252.55
A50: Total for 6650 Board Meeting Travel Expense | B50: 6650 | C50: T&E | E50: =((((((((((E39)+(E40))+(E41))+(E42))+(E43))+(E44))+(E45))+(E46))+(E47))+(E48))+(E49) -> 10226.95 | F50: =((((((((((F39)+(F40))+(F41))+(F42))+(F43))+(F44))+(F45))+(F46))+(F47))+(F48))+(F49) -> 7587.63 | G50: =((((((((((G39)+(G40))+(G41))+(G42))+(G43))+(G44))+(G45))+(G46))+(G47))+(G48))+(G49) -> 17224.2 | H50: =((((((((((H39)+(H40))+(H41))+(H42))+(H43))+(H44))+(H45))+(H46))+(H47))+(H48))+(H49) -> 12636.85 | I50: =((((((((((I39)+(I40))+(I41))+(I42))+(I43))+(I44))+(I45))+(I46))+(I47))+(I48))+(I49) -> 12070.99 | J50: =((((((((((J39)+(J40))+(J41))+(J42))+(J43))+(J44))+(J45))+(J46))+(J47))+(J48))+(J49) -> 4490.7 | K50: =((((((((((K39)+(K40))+(K41))+(K42))+(K43))+(K44))+(K45))+(K46))+(K47))+(K48))+(K49) -> 15107.41 | L50: =((((((((((L39)+(L40))+(L41))+(L42))+(L43))+(L44))+(L45))+(L46))+(L47))+(L48))+(L49) -> 3346.16 | ... P50: =((((((((((P39)+(P40))+(P41))+(P42))+(P43))+(P44))+(P45))+(P46))+(P47))+(P48))+(P49) -> 232.98 | Q50: 16005.35 | R50: 5742.89 | S50: 3832.03 | T50: 18095 | U50: 10239 | V50: 13235 | W50: 7445 | X50: 1251 | Y50: 10396 | Z50: 10176 | AA50: 10883 | AB50: 15001 | AD50: =SUMIFS($E50:$AB50,$E$6:$AB$6,AD$5) -> 35038.78 | AE50: =SUMIFS($E50:$AB50,$E$6:$AB$6,AE$5) -> 29198.54 | AF50: =SUMIFS($E50:$AB50,$E$6:$AB$6,AF$5) -> 26677.99 | AG50: =SUMIFS($E50:$AB50,$E$6:$AB$6,AG$5) -> 7485.02 | AH50: =SUMIFS($E50:$AB50,$E$6:$AB$6,AH$5) -> 25580.27 | AI50: =SUMIFS($E50:$AB50,$E$6:$AB$6,AI$5) -> 41569 | AJ50: =SUMIFS($E50:$AB50,$E$6:$AB$6,AJ$5) -> 19092 | AK50: =SUMIFS($E50:$AB50,$E$6:$AB$6,AK$5) -> 36060 | AM50: =SUMIFS($E50:$AB50,$E$7:$AB$7,AM$5) -> 98400.33 | AN50: =SUMIFS($E50:$AB50,$E$7:$AB$7,AN$5) -> 122301.27
A51: 6750 Professional Fees | B51: 6750 | AD51: =SUMIFS($E51:$AB51,$E$6:$AB$6,AD$5) -> 0 | AE51: =SUMIFS($E51:$AB51,$E$6:$AB$6,AE$5) -> 0 | AF51: =SUMIFS($E51:$AB51,$E$6:$AB$6,AF$5) -> 0 | AG51: =SUMIFS($E51:$AB51,$E$6:$AB$6,AG$5) -> 0 | AH51: =SUMIFS($E51:$AB51,$E$6:$AB$6,AH$5) -> 0 | AI51: =SUMIFS($E51:$AB51,$E$6:$AB$6,AI$5) -> 0 | AJ51: =SUMIFS($E51:$AB51,$E$6:$AB$6,AJ$5) -> 0 | AK51: =SUMIFS($E51:$AB51,$E$6:$AB$6,AK$5) -> 0 | AM51: =SUMIFS($E51:$AB51,$E$7:$AB$7,AM$5) -> 0 | AN51: =SUMIFS($E51:$AB51,$E$7:$AB$7,AN$5) -> 0
A52: 6751 Legal Fees - Corporate | B52: 6751 | C52: Legal Fees - Corporate | E52: =378.5 -> 378.5 | F52: =14918 -> 14918 | G52: =2610 -> 2610 | H52: =13077 -> 13077 | I52: =21476.5 -> 21476.5 | J52: =6267 -> 6267 | K52: =3270.45 -> 3270.45 | L52: =8297 -> 8297 | M52: =16083.4 -> 16083.4 | N52: =22934.43 -> 22934.43 | O52: =5969.6 -> 5969.6 | P52: =3464.05 -> 3464.05 | Q52: 14830.15 | R52: 11656.75 | S52: 43723.61 | T52: 0 | U52: 8749 | V52: 16291 | W52: 52525 | X52: 22079 | Y52: 39545 | Z52: 40981 | AA52: 42772 | AB52: 41716 | AD52: =SUMIFS($E52:$AB52,$E$6:$AB$6,AD$5) -> 17906.5 | AE52: =SUMIFS($E52:$AB52,$E$6:$AB$6,AE$5) -> 40820.5 | AF52: =SUMIFS($E52:$AB52,$E$6:$AB$6,AF$5) -> 27650.85 | AG52: =SUMIFS($E52:$AB52,$E$6:$AB$6,AG$5) -> 32368.08 | AH52: =SUMIFS($E52:$AB52,$E$6:$AB$6,AH$5) -> 70210.51 | AI52: =SUMIFS($E52:$AB52,$E$6:$AB$6,AI$5) -> 25040 | AJ52: =SUMIFS($E52:$AB52,$E$6:$AB$6,AJ$5) -> 114149 | AK52: =SUMIFS($E52:$AB52,$E$6:$AB$6,AK$5) -> 125469 | AM52: =SUMIFS($E52:$AB52,$E$7:$AB$7,AM$5) -> 118745.93 | AN52: =SUMIFS($E52:$AB52,$E$7:$AB$7,AN$5) -> 334868.51
A53: 6752 Legal Fees - Intellectual Property | B53: 6752 | C53: Legal Fees - Intellectual Property | E53: =0.13 -> 0.13 | F53: =2275 -> 2275 | G53: =2179.95 -> 2179.95 | H53: =-26073.98 -> -26073.98 | I53: =40676.18 -> 40676.18 | J53: =0 -> 0 | K53: =2900 -> 2900 | L53: =2832.27 -> 2832.27 | M53: =1558.5 -> 1558.5 | N53: =0 -> 0 | O53: =3240.5 -> 3240.5 | P53: =4900.5 -> 4900.5 | Q53: 235 | R53: =0 -> 0 | S53: 115 | T53: 9220 | U53: 410 | V53: 4531 | W53: 1637 | X53: 2735 | Y53: 455 | Z53: 7556 | AA53: 3028 | AD53: =SUMIFS($E53:$AB53,$E$6:$AB$6,AD$5) -> 4455.08 | AE53: =SUMIFS($E53:$AB53,$E$6:$AB$6,AE$5) -> 14602.2 | AF53: =SUMIFS($E53:$AB53,$E$6:$AB$6,AF$5) -> 7290.77 | AG53: =SUMIFS($E53:$AB53,$E$6:$AB$6,AG$5) -> 8141 | AH53: =SUMIFS($E53:$AB53,$E$6:$AB$6,AH$5) -> 350 | AI53: =SUMIFS($E53:$AB53,$E$6:$AB$6,AI$5) -> 14161 | AJ53: =SUMIFS($E53:$AB53,$E$6:$AB$6,AJ$5) -> 4827 | AK53: =SUMIFS($E53:$AB53,$E$6:$AB$6,AK$5) -> 10584 | AM53: =SUMIFS($E53:$AB53,$E$7:$AB$7,AM$5) -> 34489.05 | AN53: =SUMIFS($E53:$AB53,$E$7:$AB$7,AN$5) -> 29922
A54: 6753 FundraisingLegal | B54: 6753 | E54: =0 -> 0 | F54: =0 -> 0 | G54: =0 -> 0 | H54: =0 -> 0 | I54: =0 -> 0 | J54: =0 -> 0 | K54: =0 -> 0 | L54: =0 -> 0 | ... S54: =0 -> 0 | T54: 0 | U54: 0 | AD54: =SUMIFS($E54:$AB54,$E$6:$AB$6,AD$5) -> 0 | AE54: =SUMIFS($E54:$AB54,$E$6:$AB$6,AE$5) -> 0 | AF54: =SUMIFS($E54:$AB54,$E$6:$AB$6,AF$5) -> 0 | AG54: =SUMIFS($E54:$AB54,$E$6:$AB$6,AG$5) -> 0 | AH54: =SUMIFS($E54:$AB54,$E$6:$AB$6,AH$5) -> 0 | AI54: =SUMIFS($E54:$AB54,$E$6:$AB$6,AI$5) -> 0 | AJ54: =SUMIFS($E54:$AB54,$E$6:$AB$6,AJ$5) -> 0 | AK54: =SUMIFS($E54:$AB54,$E$6:$AB$6,AK$5) -> 0 | AM54: =SUMIFS($E54:$AB54,$E$7:$AB$7,AM$5) -> 0 | AN54: =SUMIFS($E54:$AB54,$E$7:$AB$7,AN$5) -> 0
A55: 6756 SAFE Legal | B55: 6756 | E55: =0 -> 0 | F55: =0 -> 0 | G55: =0 -> 0 | H55: =0 -> 0 | I55: =0 -> 0 | J55: =0 -> 0 | K55: =0 -> 0 | L55: =0 -> 0 | ... Q55: =0 -> 0 | R55: 31774 | S55: 58766.85 | T55: 0 | U55: 0 | V55: 12581 | AB55: 5122 | AD55: =SUMIFS($E55:$AB55,$E$6:$AB$6,AD$5) -> 0 | AE55: =SUMIFS($E55:$AB55,$E$6:$AB$6,AE$5) -> 0 | AF55: =SUMIFS($E55:$AB55,$E$6:$AB$6,AF$5) -> 0 | AG55: =SUMIFS($E55:$AB55,$E$6:$AB$6,AG$5) -> 0 | AH55: =SUMIFS($E55:$AB55,$E$6:$AB$6,AH$5) -> 90540.85 | AI55: =SUMIFS($E55:$AB55,$E$6:$AB$6,AI$5) -> 12581 | AJ55: =SUMIFS($E55:$AB55,$E$6:$AB$6,AJ$5) -> 0 | AK55: =SUMIFS($E55:$AB55,$E$6:$AB$6,AK$5) -> 5122 | AM55: =SUMIFS($E55:$AB55,$E$7:$AB$7,AM$5) -> 0 | AN55: =SUMIFS($E55:$AB55,$E$7:$AB$7,AN$5) -> 108243.85
A56: Total for 6753 FundraisingLegal | B56: 6753 | C56: Legal Fees - Fundraising | E56: =SUM(E54:E55) -> 0 | F56: =SUM(F54:F55) -> 0 | G56: =SUM(G54:G55) -> 0 | H56: =SUM(H54:H55) -> 0 | I56: =SUM(I54:I55) -> 0 | J56: =SUM(J54:J55) -> 0 | K56: =SUM(K54:K55) -> 0 | L56: =SUM(L54:L55) -> 0 | ... AB56: =SUM(AB54:AB55) -> 5122 | AD56: =SUMIFS($E56:$AB56,$E$6:$AB$6,AD$5) -> 0 | AE56: =SUMIFS($E56:$AB56,$E$6:$AB$6,AE$5) -> 0 | AF56: =SUMIFS($E56:$AB56,$E$6:$AB$6,AF$5) -> 0 | AG56: =SUMIFS($E56:$AB56,$E$6:$AB$6,AG$5) -> 0 | AH56: =SUMIFS($E56:$AB56,$E$6:$AB$6,AH$5) -> 90540.85 | AI56: =SUMIFS($E56:$AB56,$E$6:$AB$6,AI$5) -> 12581 | AJ56: =SUMIFS($E56:$AB56,$E$6:$AB$6,AJ$5) -> 0 | AK56: =SUMIFS($E56:$AB56,$E$6:$AB$6,AK$5) -> 5122 | AM56: =SUMIFS($E56:$AB56,$E$7:$AB$7,AM$5) -> 0 | AN56: =SUMIFS($E56:$AB56,$E$7:$AB$7,AN$5) -> 108243.85
A57: Total for 6750 Professional Fees | B57: 6750 | E57: =((E51)+(E52))+(E53)+E56 -> 378.63 | F57: =((F51)+(F52))+(F53)+F56 -> 17193 | G57: =((G51)+(G52))+(G53)+G56 -> 4789.95 | H57: =((H51)+(H52))+(H53)+H56 -> -12996.98 | I57: =((I51)+(I52))+(I53)+I56 -> 62152.68 | J57: =((J51)+(J52))+(J53)+J56 -> 6267 | K57: =((K51)+(K52))+(K53)+K56 -> 6170.45 | L57: =((L51)+(L52))+(L53)+L56 -> 11129.27 | ... S57: =((S51)+(S52))+(S53)+S56 -> 102605.46 | T57: 9220 | U57: 9159 | V57: 33403 | W57: 54162 | X57: 24815 | Y57: 40000 | Z57: 48537 | AA57: 45800 | AB57: 46838 | AD57: =SUMIFS($E57:$AB57,$E$6:$AB$6,AD$5) -> 22361.58 | AE57: =SUMIFS($E57:$AB57,$E$6:$AB$6,AE$5) -> 55422.7 | AF57: =SUMIFS($E57:$AB57,$E$6:$AB$6,AF$5) -> 34941.62 | AG57: =SUMIFS($E57:$AB57,$E$6:$AB$6,AG$5) -> 40509.08 | AH57: =SUMIFS($E57:$AB57,$E$6:$AB$6,AH$5) -> 161101.36 | AI57: =SUMIFS($E57:$AB57,$E$6:$AB$6,AI$5) -> 51782 | AJ57: =SUMIFS($E57:$AB57,$E$6:$AB$6,AJ$5) -> 118977 | AK57: =SUMIFS($E57:$AB57,$E$6:$AB$6,AK$5) -> 141175 | AM57: =SUMIFS($E57:$AB57,$E$7:$AB$7,AM$5) -> 153234.98 | AN57: =SUMIFS($E57:$AB57,$E$7:$AB$7,AN$5) -> 473035.36
A58: 6800 License and Subscription Expense | B58: 6800 | C58: Overhead | E58: =6742.5 -> 6742.5 | F58: =6669.58 -> 6669.58 | G58: =6234.71 -> 6234.71 | H58: =5436.89 -> 5436.89 | I58: =8850.51 -> 8850.51 | J58: =8221.81 -> 8221.81 | K58: =8594.53 -> 8594.53 | L58: =13595.66 -> 13595.66 | M58: =13432.25 -> 13432.25 | N58: =5595.33 -> 5595.33 | O58: =5366.26 -> 5366.26 | P58: =7454.08 -> 7454.08 | Q58: 9758.01 | R58: 9948.32 | S58: 7891.82 | T58: 10336 | U58: 18833 | V58: 11870 | W58: 8042 | X58: 15014 | Y58: 14795 | Z58: 11735 | AA58: 21502 | AB58: 18858 | AD58: =SUMIFS($E58:$AB58,$E$6:$AB$6,AD$5) -> 19646.79 | AE58: =SUMIFS($E58:$AB58,$E$6:$AB$6,AE$5) -> 22509.21 | AF58: =SUMIFS($E58:$AB58,$E$6:$AB$6,AF$5) -> 35622.44 | AG58: =SUMIFS($E58:$AB58,$E$6:$AB$6,AG$5) -> 18415.67 | AH58: =SUMIFS($E58:$AB58,$E$6:$AB$6,AH$5) -> 27598.15 | AI58: =SUMIFS($E58:$AB58,$E$6:$AB$6,AI$5) -> 41039 | AJ58: =SUMIFS($E58:$AB58,$E$6:$AB$6,AJ$5) -> 37851 | AK58: =SUMIFS($E58:$AB58,$E$6:$AB$6,AK$5) -> 52095 | AM58: =SUMIFS($E58:$AB58,$E$7:$AB$7,AM$5) -> 96194.11 | AN58: =SUMIFS($E58:$AB58,$E$7:$AB$7,AN$5) -> 158583.15
A59: 6801 Business registration | B59: 6801 | C59: Overhead | E59: =2748.5 -> 2748.5 | F59: =0 -> 0 | G59: =2500 -> 2500 | H59: =0 -> 0 | I59: =0 -> 0 | J59: =0 -> 0 | K59: =198.04 -> 198.04 | L59: =468.05 -> 468.05 | M59: =2075.26 -> 2075.26 | N59: =1768.24 -> 1768.24 | O59: =0 -> 0 | P59: =511.16 -> 511.16 | Q59: =0 -> 0 | R59: =0 -> 0 | S59: 1500 | T59: 0 | U59: 0 | V59: 703 | W59: 0 | X59: 0 | Y59: 565 | Z59: 115 | AA59: 0 | AB59: 0 | AD59: =SUMIFS($E59:$AB59,$E$6:$AB$6,AD$5) -> 5248.5 | AE59: =SUMIFS($E59:$AB59,$E$6:$AB$6,AE$5) -> 0 | AF59: =SUMIFS($E59:$AB59,$E$6:$AB$6,AF$5) -> 2741.35 | AG59: =SUMIFS($E59:$AB59,$E$6:$AB$6,AG$5) -> 2279.4 | AH59: =SUMIFS($E59:$AB59,$E$6:$AB$6,AH$5) -> 1500 | AI59: =SUMIFS($E59:$AB59,$E$6:$AB$6,AI$5) -> 703 | AJ59: =SUMIFS($E59:$AB59,$E$6:$AB$6,AJ$5) -> 565 | AK59: =SUMIFS($E59:$AB59,$E$6:$AB$6,AK$5) -> 115 | AM59: =SUMIFS($E59:$AB59,$E$7:$AB$7,AM$5) -> 10269.25 | AN59: =SUMIFS($E59:$AB59,$E$7:$AB$7,AN$5) -> 2883
A60: 6802 Membership and dues | B60: 6802 | C60: Overhead | E60: =5000 -> 5000 | F60: =5610.49 -> 5610.49 | G60: =479.98 -> 479.98 | H60: =239.99 -> 239.99 | I60: =280 -> 280 | J60: =329 -> 329 | K60: =2520 -> 2520 | L60: =0 -> 0 | M60: =0 -> 0 | N60: =0 -> 0 | O60: =0 -> 0 | P60: =130 -> 130 | Q60: =0 -> 0 | R60: 130 | S60: =0 -> 0 | T60: 0 | U60: 0 | V60: 0 | W60: 0 | X60: 298 | Y60: 0 | Z60: 355 | AA60: 21000 | AB60: 4149 | AD60: =SUMIFS($E60:$AB60,$E$6:$AB$6,AD$5) -> 11090.47 | AE60: =SUMIFS($E60:$AB60,$E$6:$AB$6,AE$5) -> 848.99 | AF60: =SUMIFS($E60:$AB60,$E$6:$AB$6,AF$5) -> 2520 | AG60: =SUMIFS($E60:$AB60,$E$6:$AB$6,AG$5) -> 130 | AH60: =SUMIFS($E60:$AB60,$E$6:$AB$6,AH$5) -> 130 | AI60: =SUMIFS($E60:$AB60,$E$6:$AB$6,AI$5) -> 0 | AJ60: =SUMIFS($E60:$AB60,$E$6:$AB$6,AJ$5) -> 298 | AK60: =SUMIFS($E60:$AB60,$E$6:$AB$6,AK$5) -> 25504 | AM60: =SUMIFS($E60:$AB60,$E$7:$AB$7,AM$5) -> 14589.46 | AN60: =SUMIFS($E60:$AB60,$E$7:$AB$7,AN$5) -> 25932
A61: 6803 PPE | B61: 6803 | C61: Overhead | E61: =0 -> 0 | F61: =0 -> 0 | G61: =2524.6 -> 2524.6 | H61: =888.24 -> 888.24 | I61: =0 -> 0 | J61: =1164.86 -> 1164.86 | K61: =0 -> 0 | L61: =0 -> 0 | M61: =0 -> 0 | N61: =211.01 -> 211.01 | O61: =0 -> 0 | P61: =0 -> 0 | Q61: 860.74 | R61: =0 -> 0 | S61: -465.26 | T61: 0 | U61: 0 | V61: 0 | W61: 0 | X61: 0 | Y61: 0 | Z61: 0 | AA61: 0 | AB61: 0 | AD61: =SUMIFS($E61:$AB61,$E$6:$AB$6,AD$5) -> 2524.6 | AE61: =SUMIFS($E61:$AB61,$E$6:$AB$6,AE$5) -> 2053.1 | AF61: =SUMIFS($E61:$AB61,$E$6:$AB$6,AF$5) -> 0 | AG61: =SUMIFS($E61:$AB61,$E$6:$AB$6,AG$5) -> 211.01 | AH61: =SUMIFS($E61:$AB61,$E$6:$AB$6,AH$5) -> 395.48 | AI61: =SUMIFS($E61:$AB61,$E$6:$AB$6,AI$5) -> 0 | AJ61: =SUMIFS($E61:$AB61,$E$6:$AB$6,AJ$5) -> 0 | AK61: =SUMIFS($E61:$AB61,$E$6:$AB$6,AK$5) -> 0 | AM61: =SUMIFS($E61:$AB61,$E$7:$AB$7,AM$5) -> 4788.71 | AN61: =SUMIFS($E61:$AB61,$E$7:$AB$7,AN$5) -> 395.48
A62: 6804 Training | B62: 6804 | C62: Overhead | E62: =0 -> 0 | F62: =0 -> 0 | G62: =0 -> 0 | H62: =0 -> 0 | I62: =0 -> 0 | J62: =0 -> 0 | K62: =0 -> 0 | L62: =819.96 -> 819.96 | M62: =0 -> 0 | N62: =0 -> 0 | O62: =0 -> 0 | P62: =0 -> 0 | Q62: =0 -> 0 | R62: =0 -> 0 | S62: =0 -> 0 | T62: 0 | U62: 1380 | V62: 0 | W62: 0 | X62: 4485 | Y62: 589 | Z62: 0 | AA62: 0 | AB62: 0 | AD62: =SUMIFS($E62:$AB62,$E$6:$AB$6,AD$5) -> 0 | AE62: =SUMIFS($E62:$AB62,$E$6:$AB$6,AE$5) -> 0 | AF62: =SUMIFS($E62:$AB62,$E$6:$AB$6,AF$5) -> 819.96 | AG62: =SUMIFS($E62:$AB62,$E$6:$AB$6,AG$5) -> 0 | AH62: =SUMIFS($E62:$AB62,$E$6:$AB$6,AH$5) -> 0 | AI62: =SUMIFS($E62:$AB62,$E$6:$AB$6,AI$5) -> 1380 | AJ62: =SUMIFS($E62:$AB62,$E$6:$AB$6,AJ$5) -> 5074 | AK62: =SUMIFS($E62:$AB62,$E$6:$AB$6,AK$5) -> 0 | AM62: =SUMIFS($E62:$AB62,$E$7:$AB$7,AM$5) -> 819.96 | AN62: =SUMIFS($E62:$AB62,$E$7:$AB$7,AN$5) -> 6454
A63: 6850 Maintenance Expense | B63: 6805 | C63: Overhead | E63: 0 | F63: 0 | G63: 0 | H63: 0 | I63: 0 | J63: 0 | K63: 0 | L63: 0 | M63: 0 | N63: 0 | O63: 0 | P63: 0 | Q63: 0 | R63: 0 | S63: 0 | T63: 2060 | U63: 2060 | V63: 2060 | W63: 2060 | X63: 2060 | Y63: 2060 | Z63: 2060 | AA63: 2060 | AB63: 2060 | AD63: =SUMIFS($E63:$AB63,$E$6:$AB$6,AD$5) -> 0 | AE63: =SUMIFS($E63:$AB63,$E$6:$AB$6,AE$5) -> 0 | AF63: =SUMIFS($E63:$AB63,$E$6:$AB$6,AF$5) -> 0 | AG63: =SUMIFS($E63:$AB63,$E$6:$AB$6,AG$5) -> 0 | AH63: =SUMIFS($E63:$AB63,$E$6:$AB$6,AH$5) -> 0 | AI63: =SUMIFS($E63:$AB63,$E$6:$AB$6,AI$5) -> 6180 | AJ63: =SUMIFS($E63:$AB63,$E$6:$AB$6,AJ$5) -> 6180 | AK63: =SUMIFS($E63:$AB63,$E$6:$AB$6,AK$5) -> 6180 | AM63: =SUMIFS($E63:$AB63,$E$7:$AB$7,AM$5) -> 0 | AN63: =SUMIFS($E63:$AB63,$E$7:$AB$7,AN$5) -> 18540
A64: 6900 Consultant Expense | B64: 6900 | C64: N/A | E64: =0 -> 0 | F64: =0 -> 0 | G64: =0 -> 0 | H64: =0 -> 0 | I64: =0 -> 0 | J64: =0 -> 0 | K64: =0 -> 0 | L64: =0 -> 0 | ... S64: =0 -> 0 | T64: 0 | U64: 0 | V64: 0 | W64: 0 | X64: 0 | Y64: 0 | Z64: 0 | AA64: 0 | AB64: 0 | AD64: =SUMIFS($E64:$AB64,$E$6:$AB$6,AD$5) -> 0 | AE64: =SUMIFS($E64:$AB64,$E$6:$AB$6,AE$5) -> 0 | AF64: =SUMIFS($E64:$AB64,$E$6:$AB$6,AF$5) -> 0 | AG64: =SUMIFS($E64:$AB64,$E$6:$AB$6,AG$5) -> 0 | AH64: =SUMIFS($E64:$AB64,$E$6:$AB$6,AH$5) -> 0 | AI64: =SUMIFS($E64:$AB64,$E$6:$AB$6,AI$5) -> 0 | AJ64: =SUMIFS($E64:$AB64,$E$6:$AB$6,AJ$5) -> 0 | AK64: =SUMIFS($E64:$AB64,$E$6:$AB$6,AK$5) -> 0 | AM64: =SUMIFS($E64:$AB64,$E$7:$AB$7,AM$5) -> 0 | AN64: =SUMIFS($E64:$AB64,$E$7:$AB$7,AN$5) -> 0
A65: 6910 Project Consulting Expense - all technical work | B65: 6910 | C65: N/A | E65: =0 -> 0 | F65: =0 -> 0 | G65: =0 -> 0 | H65: =0 -> 0 | I65: =0 -> 0 | J65: =0 -> 0 | K65: =0 -> 0 | L65: =0 -> 0 | ... S65: =0 -> 0 | T65: 0 | U65: 0 | V65: 0 | W65: 0 | X65: 0 | Y65: 0 | Z65: 0 | AA65: 0 | AB65: 0 | AD65: =SUMIFS($E65:$AB65,$E$6:$AB$6,AD$5) -> 0 | AE65: =SUMIFS($E65:$AB65,$E$6:$AB$6,AE$5) -> 0 | AF65: =SUMIFS($E65:$AB65,$E$6:$AB$6,AF$5) -> 0 | AG65: =SUMIFS($E65:$AB65,$E$6:$AB$6,AG$5) -> 0 | AH65: =SUMIFS($E65:$AB65,$E$6:$AB$6,AH$5) -> 0 | AI65: =SUMIFS($E65:$AB65,$E$6:$AB$6,AI$5) -> 0 | AJ65: =SUMIFS($E65:$AB65,$E$6:$AB$6,AJ$5) -> 0 | AK65: =SUMIFS($E65:$AB65,$E$6:$AB$6,AK$5) -> 0 | AM65: =SUMIFS($E65:$AB65,$E$7:$AB$7,AM$5) -> 0 | AN65: =SUMIFS($E65:$AB65,$E$7:$AB$7,AN$5) -> 0
A66: 6911 Subject matter experts | B66: 6911 | C66: Subject Matter experts | E66: =20000 -> 20000 | F66: =20000 -> 20000 | G66: =20000 -> 20000 | H66: =20000 -> 20000 | I66: =20000 -> 20000 | J66: =9000 -> 9000 | K66: =0 -> 0 | L66: =0 -> 0 | M66: =0 -> 0 | N66: =0 -> 0 | O66: =0 -> 0 | P66: =0 -> 0 | Q66: =0 -> 0 | R66: =0 -> 0 | S66: 6600 | T66: 12700 | U66: 0 | V66: 13700 | W66: 0 | X66: 0 | Y66: 0 | Z66: 0 | AA66: 0 | AB66: 0 | AD66: =SUMIFS($E66:$AB66,$E$6:$AB$6,AD$5) -> 60000 | AE66: =SUMIFS($E66:$AB66,$E$6:$AB$6,AE$5) -> 49000 | AF66: =SUMIFS($E66:$AB66,$E$6:$AB$6,AF$5) -> 0 | AG66: =SUMIFS($E66:$AB66,$E$6:$AB$6,AG$5) -> 0 | AH66: =SUMIFS($E66:$AB66,$E$6:$AB$6,AH$5) -> 6600 | AI66: =SUMIFS($E66:$AB66,$E$6:$AB$6,AI$5) -> 26400 | AJ66: =SUMIFS($E66:$AB66,$E$6:$AB$6,AJ$5) -> 0 | AK66: =SUMIFS($E66:$AB66,$E$6:$AB$6,AK$5) -> 0 | AM66: =SUMIFS($E66:$AB66,$E$7:$AB$7,AM$5) -> 109000 | AN66: =SUMIFS($E66:$AB66,$E$7:$AB$7,AN$5) -> 33000
A67: 6912 Software Services | B67: 6912 | C67: Software services | E67: =0 -> 0 | F67: =0 -> 0 | G67: =0 -> 0 | H67: =0 -> 0 | I67: =1340 -> 1340 | J67: =0 -> 0 | K67: =0 -> 0 | L67: =0 -> 0 | M67: =5116.72 -> 5116.72 | N67: =5116.72 -> 5116.72 | O67: =5116.72 -> 5116.72 | P67: =5116.72 -> 5116.72 | Q67: 5116.72 | R67: 5116.72 | S67: 5116.72 | T67: 90398 | U67: 1539 | V67: 1539 | W67: 0 | X67: 0 | Y67: 0 | Z67: 0 | AA67: 0 | AB67: 0 | AD67: =SUMIFS($E67:$AB67,$E$6:$AB$6,AD$5) -> 0 | AE67: =SUMIFS($E67:$AB67,$E$6:$AB$6,AE$5) -> 1340 | AF67: =SUMIFS($E67:$AB67,$E$6:$AB$6,AF$5) -> 5116.72 | AG67: =SUMIFS($E67:$AB67,$E$6:$AB$6,AG$5) -> 15350.16 | AH67: =SUMIFS($E67:$AB67,$E$6:$AB$6,AH$5) -> 15350.16 | AI67: =SUMIFS($E67:$AB67,$E$6:$AB$6,AI$5) -> 93476 | AJ67: =SUMIFS($E67:$AB67,$E$6:$AB$6,AJ$5) -> 0 | AK67: =SUMIFS($E67:$AB67,$E$6:$AB$6,AK$5) -> 0 | AM67: =SUMIFS($E67:$AB67,$E$7:$AB$7,AM$5) -> 21806.88 | AN67: =SUMIFS($E67:$AB67,$E$7:$AB$7,AN$5) -> 108826.16
A68: 6913 Eng Services | B68: 6913 | C68: Eng services | E68: =6825 -> 6825 | F68: =6937.5 -> 6937.5 | G68: =10500 -> 10500 | H68: =31475 -> 31475 | I68: =43637.5 -> 43637.5 | J68: =0 -> 0 | K68: =7000 -> 7000 | L68: =31575 -> 31575 | M68: =12100 -> 12100 | N68: =12750 -> 12750 | O68: =13500 -> 13500 | P68: =0 -> 0 | Q68: 12825 | R68: =0 -> 0 | S68: 21600 | T68: 2475 | U68: 0 | V68: 65988 | W68: 0 | X68: 0 | Y68: 0 | Z68: 0 | AA68: 0 | AB68: 0 | AD68: =SUMIFS($E68:$AB68,$E$6:$AB$6,AD$5) -> 24262.5 | AE68: =SUMIFS($E68:$AB68,$E$6:$AB$6,AE$5) -> 75112.5 | AF68: =SUMIFS($E68:$AB68,$E$6:$AB$6,AF$5) -> 50675 | AG68: =SUMIFS($E68:$AB68,$E$6:$AB$6,AG$5) -> 26250 | AH68: =SUMIFS($E68:$AB68,$E$6:$AB$6,AH$5) -> 34425 | AI68: =SUMIFS($E68:$AB68,$E$6:$AB$6,AI$5) -> 68463 | AJ68: =SUMIFS($E68:$AB68,$E$6:$AB$6,AJ$5) -> 0 | AK68: =SUMIFS($E68:$AB68,$E$6:$AB$6,AK$5) -> 0 | AM68: =SUMIFS($E68:$AB68,$E$7:$AB$7,AM$5) -> 176300 | AN68: =SUMIFS($E68:$AB68,$E$7:$AB$7,AN$5) -> 102888
A69: 6914 General research | B69: 6914 | C69: Eng services | E69: =0 -> 0 | F69: =0 -> 0 | G69: =0 -> 0 | H69: =325.59 -> 325.59 | I69: =0 -> 0 | J69: =0 -> 0 | K69: =0 -> 0 | L69: =0 -> 0 | M69: =0 -> 0 | N69: =0 -> 0 | O69: =0 -> 0 | P69: =0 -> 0 | ... AB69: =0 -> 0 | AD69: =SUMIFS($E69:$AB69,$E$6:$AB$6,AD$5) -> 0 | AE69: =SUMIFS($E69:$AB69,$E$6:$AB$6,AE$5) -> 325.59 | AF69: =SUMIFS($E69:$AB69,$E$6:$AB$6,AF$5) -> 0 | AG69: =SUMIFS($E69:$AB69,$E$6:$AB$6,AG$5) -> 0 | AH69: =SUMIFS($E69:$AB69,$E$6:$AB$6,AH$5) -> 0 | AI69: =SUMIFS($E69:$AB69,$E$6:$AB$6,AI$5) -> 0 | AJ69: =SUMIFS($E69:$AB69,$E$6:$AB$6,AJ$5) -> 0 | AK69: =SUMIFS($E69:$AB69,$E$6:$AB$6,AK$5) -> 0 | AM69: =SUMIFS($E69:$AB69,$E$7:$AB$7,AM$5) -> 325.59 | AN69: =SUMIFS($E69:$AB69,$E$7:$AB$7,AN$5) -> 0
A70: Total for 6910 Project Consulting Expense - all technical work | B70: 6910 | E70: =((((E65)+(E66))+(E67))+(E68))+(E69) -> 26825 | F70: =((((F65)+(F66))+(F67))+(F68))+(F69) -> 26937.5 | G70: =((((G65)+(G66))+(G67))+(G68))+(G69) -> 30500 | H70: =((((H65)+(H66))+(H67))+(H68))+(H69) -> 51800.59 | I70: =((((I65)+(I66))+(I67))+(I68))+(I69) -> 64977.5 | J70: =((((J65)+(J66))+(J67))+(J68))+(J69) -> 9000 | K70: =((((K65)+(K66))+(K67))+(K68))+(K69) -> 7000 | L70: =((((L65)+(L66))+(L67))+(L68))+(L69) -> 31575 | ... S70: =((((S65)+(S66))+(S67))+(S68))+(S69) -> 33316.72 | T70: 105573 | U70: 1539 | V70: 81227 | W70: 0 | X70: 0 | Y70: 0 | Z70: 0 | AA70: 0 | AB70: 0 | AD70: =SUMIFS($E70:$AB70,$E$6:$AB$6,AD$5) -> 84262.5 | AE70: =SUMIFS($E70:$AB70,$E$6:$AB$6,AE$5) -> 125778.09 | AF70: =SUMIFS($E70:$AB70,$E$6:$AB$6,AF$5) -> 55791.72 | AG70: =SUMIFS($E70:$AB70,$E$6:$AB$6,AG$5) -> 41600.16 | AH70: =SUMIFS($E70:$AB70,$E$6:$AB$6,AH$5) -> 56375.16 | AI70: =SUMIFS($E70:$AB70,$E$6:$AB$6,AI$5) -> 188339 | AJ70: =SUMIFS($E70:$AB70,$E$6:$AB$6,AJ$5) -> 0 | AK70: =SUMIFS($E70:$AB70,$E$6:$AB$6,AK$5) -> 0 | AM70: =SUMIFS($E70:$AB70,$E$7:$AB$7,AM$5) -> 307432.47 | AN70: =SUMIFS($E70:$AB70,$E$7:$AB$7,AN$5) -> 244714.16
A71: 6920 Corporate Consulting Expense | B71: 6920 | C71: PR | E71: =7917.96 -> 7917.96 | F71: =27087.48 -> 27087.48 | G71: =26716.4 -> 26716.4 | H71: =80725.72 -> 80725.72 | I71: =32705.28 -> 32705.28 | J71: =38587.67 -> 38587.67 | K71: =44965.5 -> 44965.5 | L71: =18997.77 -> 18997.77 | M71: =38589.3 -> 38589.3 | N71: =47989.91 -> 47989.91 | O71: =29086.26 -> 29086.26 | P71: =30435.94 -> 30435.94 | Q71: 32962.87 | R71: =0 -> 0 | S71: 63 | T71: 5868 | U71: 0 | V71: 0 | W71: 0 | X71: 159 | Y71: 0 | Z71: 0 | AA71: 0 | AB71: 0 | AD71: =SUMIFS($E71:$AB71,$E$6:$AB$6,AD$5) -> 61721.84 | AE71: =SUMIFS($E71:$AB71,$E$6:$AB$6,AE$5) -> 152018.67 | AF71: =SUMIFS($E71:$AB71,$E$6:$AB$6,AF$5) -> 102552.57 | AG71: =SUMIFS($E71:$AB71,$E$6:$AB$6,AG$5) -> 107512.11 | AH71: =SUMIFS($E71:$AB71,$E$6:$AB$6,AH$5) -> 33025.87 | AI71: =SUMIFS($E71:$AB71,$E$6:$AB$6,AI$5) -> 5868 | AJ71: =SUMIFS($E71:$AB71,$E$6:$AB$6,AJ$5) -> 159 | AK71: =SUMIFS($E71:$AB71,$E$6:$AB$6,AK$5) -> 0 | AM71: =SUMIFS($E71:$AB71,$E$7:$AB$7,AM$5) -> 423805.19 | AN71: =SUMIFS($E71:$AB71,$E$7:$AB$7,AN$5) -> 39052.87
A72: 6921 Accounting | B72: 6921 | C72: Audit Services | E72: =0 -> 0 | F72: =0 -> 0 | G72: =0 -> 0 | H72: =0 -> 0 | I72: =0 -> 0 | J72: =0 -> 0 | K72: =0 -> 0 | L72: =0 -> 0 | ... Q72: =0 -> 0 | R72: 11930.4 | S72: 15846.5 | T72: 57434 | U72: 5247 | V72: 11235 | W72: 13061 | X72: 20551 | Y72: 14142 | Z72: 16171 | AA72: 3358 | AB72: 36 | AD72: =SUMIFS($E72:$AB72,$E$6:$AB$6,AD$5) -> 0 | AE72: =SUMIFS($E72:$AB72,$E$6:$AB$6,AE$5) -> 0 | AF72: =SUMIFS($E72:$AB72,$E$6:$AB$6,AF$5) -> 0 | AG72: =SUMIFS($E72:$AB72,$E$6:$AB$6,AG$5) -> 0 | AH72: =SUMIFS($E72:$AB72,$E$6:$AB$6,AH$5) -> 27776.9 | AI72: =SUMIFS($E72:$AB72,$E$6:$AB$6,AI$5) -> 73916 | AJ72: =SUMIFS($E72:$AB72,$E$6:$AB$6,AJ$5) -> 47754 | AK72: =SUMIFS($E72:$AB72,$E$6:$AB$6,AK$5) -> 19565 | AM72: =SUMIFS($E72:$AB72,$E$7:$AB$7,AM$5) -> 0 | AN72: =SUMIFS($E72:$AB72,$E$7:$AB$7,AN$5) -> 169011.9
A73: 6922 Audit | B73: 6922 | C73: Accounting Services (incl software) | E73: =0 -> 0 | F73: =0 -> 0 | G73: =0 -> 0 | H73: =0 -> 0 | I73: =0 -> 0 | J73: =0 -> 0 | K73: =0 -> 0 | L73: =0 -> 0 | ... R73: =0 -> 0 | S73: 12480 | T73: 26000 | U73: 0 | V73: 22178 | W73: 4784 | X73: 0 | Y73: 0 | Z73: 0 | AA73: 0 | AB73: 15600 | AD73: =SUMIFS($E73:$AB73,$E$6:$AB$6,AD$5) -> 0 | AE73: =SUMIFS($E73:$AB73,$E$6:$AB$6,AE$5) -> 0 | AF73: =SUMIFS($E73:$AB73,$E$6:$AB$6,AF$5) -> 0 | AG73: =SUMIFS($E73:$AB73,$E$6:$AB$6,AG$5) -> 0 | AH73: =SUMIFS($E73:$AB73,$E$6:$AB$6,AH$5) -> 12480 | AI73: =SUMIFS($E73:$AB73,$E$6:$AB$6,AI$5) -> 48178 | AJ73: =SUMIFS($E73:$AB73,$E$6:$AB$6,AJ$5) -> 4784 | AK73: =SUMIFS($E73:$AB73,$E$6:$AB$6,AK$5) -> 15600 | AM73: =SUMIFS($E73:$AB73,$E$7:$AB$7,AM$5) -> 0 | AN73: =SUMIFS($E73:$AB73,$E$7:$AB$7,AN$5) -> 81042
A74: 6923 Tax | B74: 6923 | C74: Tax Services | E74: 0 | F74: 0 | G74: 0 | H74: 0 | I74: 0 | J74: 0 | K74: 0 | L74: 0 | M74: 0 | N74: 0 | O74: 0 | P74: 0 | Q74: 0 | R74: 0 | S74: 0 | T74: 2241 | U74: 0 | V74: 12787 | W74: 0 | X74: 693 | Y74: 2266 | Z74: 0 | AA74: 0 | AB74: 0 | AD74: =SUMIFS($E74:$AB74,$E$6:$AB$6,AD$5) -> 0 | AE74: =SUMIFS($E74:$AB74,$E$6:$AB$6,AE$5) -> 0 | AF74: =SUMIFS($E74:$AB74,$E$6:$AB$6,AF$5) -> 0 | AG74: =SUMIFS($E74:$AB74,$E$6:$AB$6,AG$5) -> 0 | AH74: =SUMIFS($E74:$AB74,$E$6:$AB$6,AH$5) -> 0 | AI74: =SUMIFS($E74:$AB74,$E$6:$AB$6,AI$5) -> 15028 | AJ74: =SUMIFS($E74:$AB74,$E$6:$AB$6,AJ$5) -> 2959 | AK74: =SUMIFS($E74:$AB74,$E$6:$AB$6,AK$5) -> 0 | AM74: =SUMIFS($E74:$AB74,$E$7:$AB$7,AM$5) -> 0 | AN74: =SUMIFS($E74:$AB74,$E$7:$AB$7,AN$5) -> 17987
A75: 6924 IT | B75: 6924 | C75: IT Services | E75: =0 -> 0 | F75: =0 -> 0 | G75: =0 -> 0 | H75: =0 -> 0 | I75: =0 -> 0 | J75: =0 -> 0 | K75: =0 -> 0 | L75: =0 -> 0 | ... Q75: =0 -> 0 | R75: 5847.73 | S75: 2774.8 | T75: 0 | U75: 5032 | V75: 9673 | W75: 3246 | X75: 3636 | Y75: 3338 | Z75: 3896 | AA75: 3887 | AB75: 3906 | AD75: =SUMIFS($E75:$AB75,$E$6:$AB$6,AD$5) -> 0 | AE75: =SUMIFS($E75:$AB75,$E$6:$AB$6,AE$5) -> 0 | AF75: =SUMIFS($E75:$AB75,$E$6:$AB$6,AF$5) -> 0 | AG75: =SUMIFS($E75:$AB75,$E$6:$AB$6,AG$5) -> 0 | AH75: =SUMIFS($E75:$AB75,$E$6:$AB$6,AH$5) -> 8622.53 | AI75: =SUMIFS($E75:$AB75,$E$6:$AB$6,AI$5) -> 14705 | AJ75: =SUMIFS($E75:$AB75,$E$6:$AB$6,AJ$5) -> 10220 | AK75: =SUMIFS($E75:$AB75,$E$6:$AB$6,AK$5) -> 11689 | AM75: =SUMIFS($E75:$AB75,$E$7:$AB$7,AM$5) -> 0 | AN75: =SUMIFS($E75:$AB75,$E$7:$AB$7,AN$5) -> 45236.53
A76: 6925 Other | B76: 6925 | C76: Other Consultants | E76: =0 -> 0 | F76: =0 -> 0 | G76: =0 -> 0 | H76: =0 -> 0 | I76: =0 -> 0 | J76: =0 -> 0 | K76: =0 -> 0 | L76: =0 -> 0 | ... R76: =0 -> 0 | S76: 20000 | T76: 0 | U76: 0 | V76: 100000 | W76: 26667 | X76: 0 | Y76: 74000 | Z76: 0 | AA76: 0 | AB76: 0 | AD76: =SUMIFS($E76:$AB76,$E$6:$AB$6,AD$5) -> 0 | AE76: =SUMIFS($E76:$AB76,$E$6:$AB$6,AE$5) -> 0 | AF76: =SUMIFS($E76:$AB76,$E$6:$AB$6,AF$5) -> 0 | AG76: =SUMIFS($E76:$AB76,$E$6:$AB$6,AG$5) -> 0 | AH76: =SUMIFS($E76:$AB76,$E$6:$AB$6,AH$5) -> 20000 | AI76: =SUMIFS($E76:$AB76,$E$6:$AB$6,AI$5) -> 100000 | AJ76: =SUMIFS($E76:$AB76,$E$6:$AB$6,AJ$5) -> 100667 | AK76: =SUMIFS($E76:$AB76,$E$6:$AB$6,AK$5) -> 0 | AM76: =SUMIFS($E76:$AB76,$E$7:$AB$7,AM$5) -> 0 | AN76: =SUMIFS($E76:$AB76,$E$7:$AB$7,AN$5) -> 220667
A77: Total for 6920 Corporate Consulting Expense | B77: 6920 | E77: =SUM(E71:E76) -> 7917.96 | F77: =SUM(F71:F76) -> 27087.48 | G77: =SUM(G71:G76) -> 26716.4 | H77: =SUM(H71:H76) -> 80725.72 | I77: =SUM(I71:I76) -> 32705.28 | J77: =SUM(J71:J76) -> 38587.67 | K77: =SUM(K71:K76) -> 44965.5 | L77: =SUM(L71:L76) -> 18997.77 | ... S77: =SUM(S71:S76) -> 51164.3 | T77: 91543 | U77: 10278 | V77: 155873 | W77: 47758 | X77: 25039 | Y77: 93747 | Z77: 20067 | AA77: 7246 | AB77: 19542 | AD77: =SUMIFS($E77:$AB77,$E$6:$AB$6,AD$5) -> 61721.84 | AE77: =SUMIFS($E77:$AB77,$E$6:$AB$6,AE$5) -> 152018.67 | AF77: =SUMIFS($E77:$AB77,$E$6:$AB$6,AF$5) -> 102552.57 | AG77: =SUMIFS($E77:$AB77,$E$6:$AB$6,AG$5) -> 107512.11 | AH77: =SUMIFS($E77:$AB77,$E$6:$AB$6,AH$5) -> 101905.3 | AI77: =SUMIFS($E77:$AB77,$E$6:$AB$6,AI$5) -> 257694 | AJ77: =SUMIFS($E77:$AB77,$E$6:$AB$6,AJ$5) -> 166544 | AK77: =SUMIFS($E77:$AB77,$E$6:$AB$6,AK$5) -> 46855 | AM77: =SUMIFS($E77:$AB77,$E$7:$AB$7,AM$5) -> 423805.19 | AN77: =SUMIFS($E77:$AB77,$E$7:$AB$7,AN$5) -> 572998.3
A78: Total for 6900 Consultant Expense | B78: 6900 | E78: =((E64)+(E70))+(E77) -> 34742.96 | F78: =((F64)+(F70))+(F77) -> 54024.98 | G78: =((G64)+(G70))+(G77) -> 57216.4 | H78: =((H64)+(H70))+(H77) -> 132526.31 | I78: =((I64)+(I70))+(I77) -> 97682.78 | J78: =((J64)+(J70))+(J77) -> 47587.67 | K78: =((K64)+(K70))+(K77) -> 51965.5 | L78: =((L64)+(L70))+(L77) -> 50572.77 | ... S78: =((S64)+(S70))+(S77) -> 84481.02 | T78: 197116 | U78: 11817 | V78: 237099 | W78: 47758 | X78: 25039 | Y78: 93747 | Z78: 20067 | AA78: 7246 | AB78: 19542 | AD78: =SUMIFS($E78:$AB78,$E$6:$AB$6,AD$5) -> 145984.34 | AE78: =SUMIFS($E78:$AB78,$E$6:$AB$6,AE$5) -> 277796.76 | AF78: =SUMIFS($E78:$AB78,$E$6:$AB$6,AF$5) -> 158344.29 | AG78: =SUMIFS($E78:$AB78,$E$6:$AB$6,AG$5) -> 149112.27 | AH78: =SUMIFS($E78:$AB78,$E$6:$AB$6,AH$5) -> 158280.46 | AI78: =SUMIFS($E78:$AB78,$E$6:$AB$6,AI$5) -> 446032 | AJ78: =SUMIFS($E78:$AB78,$E$6:$AB$6,AJ$5) -> 166544 | AK78: =SUMIFS($E78:$AB78,$E$6:$AB$6,AK$5) -> 46855 | AM78: =SUMIFS($E78:$AB78,$E$7:$AB$7,AM$5) -> 731237.66 | AN78: =SUMIFS($E78:$AB78,$E$7:$AB$7,AN$5) -> 817711.46
A79: 6950 Office Expense | B79: 6950 | E79: =0 -> 0 | F79: =0 -> 0 | G79: =0 -> 0 | H79: =0 -> 0 | I79: =0 -> 0 | J79: =0 -> 0 | K79: =0 -> 0 | L79: =0 -> 0 | ... S79: =0 -> 0 | T79: 0 | U79: 0 | V79: 0 | W79: 0 | X79: 0 | Y79: 0 | Z79: 0 | AA79: 0 | AB79: 0 | AD79: =SUMIFS($E79:$AB79,$E$6:$AB$6,AD$5) -> 0 | AE79: =SUMIFS($E79:$AB79,$E$6:$AB$6,AE$5) -> 0 | AF79: =SUMIFS($E79:$AB79,$E$6:$AB$6,AF$5) -> 0 | AG79: =SUMIFS($E79:$AB79,$E$6:$AB$6,AG$5) -> 0 | AH79: =SUMIFS($E79:$AB79,$E$6:$AB$6,AH$5) -> 0 | AI79: =SUMIFS($E79:$AB79,$E$6:$AB$6,AI$5) -> 0 | AJ79: =SUMIFS($E79:$AB79,$E$6:$AB$6,AJ$5) -> 0 | AK79: =SUMIFS($E79:$AB79,$E$6:$AB$6,AK$5) -> 0 | AM79: =SUMIFS($E79:$AB79,$E$7:$AB$7,AM$5) -> 0 | AN79: =SUMIFS($E79:$AB79,$E$7:$AB$7,AN$5) -> 0
A80: 6951 Rent | B80: 6951 | E80: =7750 -> 7750 | F80: =7750 -> 7750 | G80: =13282.06 -> 13282.06 | H80: =19999.57 -> 19999.57 | I80: =14249.57 -> 14249.57 | J80: =14249.57 -> 14249.57 | K80: =14249.57 -> 14249.57 | L80: =14249.57 -> 14249.57 | M80: =14249.57 -> 14249.57 | N80: =14249.57 -> 14249.57 | O80: =14249.57 -> 14249.57 | P80: =14249.57 -> 14249.57 | Q80: 14249.57 | R80: 14249.57 | S80: 14249.57 | T80: 16903 | U80: 16903 | V80: 16903 | W80: 16903 | X80: 16903 | Y80: 16903 | Z80: 19893 | AA80: 16903 | AB80: 16903 | AD80: =SUMIFS($E80:$AB80,$E$6:$AB$6,AD$5) -> 28782.06 | AE80: =SUMIFS($E80:$AB80,$E$6:$AB$6,AE$5) -> 48498.71 | AF80: =SUMIFS($E80:$AB80,$E$6:$AB$6,AF$5) -> 42748.71 | AG80: =SUMIFS($E80:$AB80,$E$6:$AB$6,AG$5) -> 42748.71 | AH80: =SUMIFS($E80:$AB80,$E$6:$AB$6,AH$5) -> 42748.71 | AI80: =SUMIFS($E80:$AB80,$E$6:$AB$6,AI$5) -> 50709 | AJ80: =SUMIFS($E80:$AB80,$E$6:$AB$6,AJ$5) -> 50709 | AK80: =SUMIFS($E80:$AB80,$E$6:$AB$6,AK$5) -> 53699 | AM80: =SUMIFS($E80:$AB80,$E$7:$AB$7,AM$5) -> 162778.19 | AN80: =SUMIFS($E80:$AB80,$E$7:$AB$7,AN$5) -> 197865.71
A81: 6952 Postage | B81: 6952 | E81: =0 -> 0 | F81: =8.58 -> 8.58 | G81: =0 -> 0 | H81: =293.15 -> 293.15 | I81: =347.99 -> 347.99 | J81: =365.99 -> 365.99 | K81: =0 -> 0 | L81: =63.94 -> 63.94 | M81: =135.06 -> 135.06 | N81: =837.46 -> 837.46 | O81: =9.75 -> 9.75 | P81: =143.82 -> 143.82 | Q81: 75.95 | R81: 58.84 | S81: 886.66 | T81: 297 | U81: 209 | V81: 603 | W81: 37 | X81: 1889 | Y81: 568 | Z81: 306 | AA81: 1546 | AB81: 770 | AD81: =SUMIFS($E81:$AB81,$E$6:$AB$6,AD$5) -> 8.58 | AE81: =SUMIFS($E81:$AB81,$E$6:$AB$6,AE$5) -> 1007.13 | AF81: =SUMIFS($E81:$AB81,$E$6:$AB$6,AF$5) -> 199 | AG81: =SUMIFS($E81:$AB81,$E$6:$AB$6,AG$5) -> 991.03 | AH81: =SUMIFS($E81:$AB81,$E$6:$AB$6,AH$5) -> 1021.45 | AI81: =SUMIFS($E81:$AB81,$E$6:$AB$6,AI$5) -> 1109 | AJ81: =SUMIFS($E81:$AB81,$E$6:$AB$6,AJ$5) -> 2494 | AK81: =SUMIFS($E81:$AB81,$E$6:$AB$6,AK$5) -> 2622 | AM81: =SUMIFS($E81:$AB81,$E$7:$AB$7,AM$5) -> 2205.74 | AN81: =SUMIFS($E81:$AB81,$E$7:$AB$7,AN$5) -> 7246.45
A82: 6953 Bank Charges | B82: 6953 | E82: =326.95 -> 326.95 | F82: =34.95 -> 34.95 | G82: =29.95 -> 29.95 | H82: =29.95 -> 29.95 | I82: =2442.05 -> 2442.05 | J82: =1808.23 -> 1808.23 | K82: =3123.33 -> 3123.33 | L82: =2924.64 -> 2924.64 | M82: =2738.17 -> 2738.17 | N82: =2458.89 -> 2458.89 | O82: =1718.92 -> 1718.92 | P82: =1531.97 -> 1531.97 | Q82: =0 -> 0 | R82: =0 -> 0 | S82: =0 -> 0 | T82: =0 -> 0 | U82: =0 -> 0 | V82: =0 -> 0 | W82: =0 -> 0 | X82: =0 -> 0 | ... AB82: =0 -> 0 | AD82: =SUMIFS($E82:$AB82,$E$6:$AB$6,AD$5) -> 391.85 | AE82: =SUMIFS($E82:$AB82,$E$6:$AB$6,AE$5) -> 4280.23 | AF82: =SUMIFS($E82:$AB82,$E$6:$AB$6,AF$5) -> 8786.14 | AG82: =SUMIFS($E82:$AB82,$E$6:$AB$6,AG$5) -> 5709.78 | AH82: =SUMIFS($E82:$AB82,$E$6:$AB$6,AH$5) -> 0 | AI82: =SUMIFS($E82:$AB82,$E$6:$AB$6,AI$5) -> 0 | AJ82: =SUMIFS($E82:$AB82,$E$6:$AB$6,AJ$5) -> 0 | AK82: =SUMIFS($E82:$AB82,$E$6:$AB$6,AK$5) -> 0 | AM82: =SUMIFS($E82:$AB82,$E$7:$AB$7,AM$5) -> 19168 | AN82: =SUMIFS($E82:$AB82,$E$7:$AB$7,AN$5) -> 0
